Workbook
Name mois: Feuil4!#REF!
Name mois: Feuil4!#REF!
Name mois: Feuil4!#REF!
Name mois: Feuil4!#REF!
Name mois_bon2: Feuil4!$E$1:$E$100
Name mois_modif: Feuil4!$E$4:$E$32
Name nature_credit: [1]tresorerie!$P$8:$P$13
Name nature_debit: [1]tresorerie!$S$8:$S$13
Name secteur: Feuil4!$A$1:$A$4

Sheet fond_dispo_rep_interet
A1: N° | B1: Nom épargnant | C1: 44470 | D1: 44501 | E1: 44531 | F1: 44562 | G1: 44593 | H1: 44621 | I1: 44652 | J1: 44682 | K1: 44713 | L1: 44743 | M1: 44774 | N1: 44805 | O1: 44835 | P1: 44866 | Q1: 44896 | R1: 44927 | S1: 44958 | T1: 44986 | U1: 45017 | V1: 45047 | W1: 45078 | X1: 45108
A2: 1 | B2: BOUSSEKO Narcisse | C2: 24286.429 | E2: 5714.2857
A3: 2 | B3: DONGMO Clémence | C3: 8095.4762 | E3: 1904.7619
A4: 3 | B4: DONTSOP Jackson | C4: 256191 | D4: 61667 | E4: 65476.524
A5: 4 | B5: IFOU Sylvia | C5: 0 | E5: 0
A6: 5 | B6: KUITCHE Chevalier de Dieu | C6: 56668.333 | E6: 13333.333
A7: 6 | B7: LELE SIAKA Hernandez | C7: 0 | D7: 125000 | E7: 0
A8: 7 | B8: MOMIE Emilie | C8: 16190.952 | E8: 3809.5238
A9: 8 | B9: MONTE Valdese | C9: 8095.4762 | E9: 1904.7619
A10: 9 | B10: NOUTSA Eugène | C10: 32381.905 | E10: 7619.0476
A11: 10 | B11: SONGOU Sainclaire | C11: 72859.286 | E11: 17142.857
A12: 11 | B12: TAKOULEU Richardson | C12: 72859.286 | E12: 17142.857
A13: 12 | B13: TCHIOFO Appolinie | C13: 72859.286 | E13: 17142.857
A14: 13 | B14: TCHIOFO Fidélia | C14: 56668.333 | D14: 70000 | E14: 13333.333
A15: 14 | B15: TCHIOFO Paulin | C15: 64763.81 | E15: 15238.095
A16: 15 | B16: TCHIOFO Rodine | C16: 72859.286 | E16: 17142.857
A17: 16 | B17: TCHIOFO Sorelle | C17: 64763.81 | E17: 15238.095
A18: 17 | B18: TITNKHEU Moïse | C18: 72859.286 | E18: 17142.857
A19: 18 | B19: WANGUN Parfait | C19: 72859.286 | E19: 17142.857
A20: 19 | B20: YOUDOM Nadine | C20: 64763.81 | E20: 15238.095
A21: 20 | B21: DAGOBERT | C21: 40000
A22: 21 | B22: DJEUNOU Donna | C22: 120000
A31: Total | C31: =SUM(C2:C30) -> 1250025 | D31: =SUM(D2:D30) -> 256667 | E31: =SUM(E2:E30) -> 261667 | F31: =SUM(F2:F30) -> 0 | G31: =SUM(G2:G30) -> 0 | H31: =SUM(H2:H30) -> 0 | I31: =SUM(I2:I30) -> 0 | J31: =SUM(J2:J30) -> 0 | ... X31: =SUM(X2:X30) -> 0

Sheet epargne_mensuelle_ancien
A1: N° | B1: Nom épargnant | C1: 44470 | D1: 44501 | E1: 44531 | F1: 44562 | G1: 44593 | H1: 44621 | I1: 44652 | J1: 44682 | K1: 44713 | L1: 44743 | M1: 44774 | N1: 44805 | O1: 44835 | P1: 44866 | Q1: 44896 | R1: 44927 | S1: 44958 | T1: 44986 | U1: 45017 | V1: 45047 | W1: 45078 | X1: 45108
A2: 1 | B2: BOUSSEKO Narcisse | C2: 24286.429 | E2: 5714.2857 | F2: 13685.714
A3: 2 | B3: DONGMO Clémence | C3: 8095.4762 | E3: 1904.7619 | F3: 4561.9048
A4: 3 | B4: DONTSOP Jackson | C4: 256191 | D4: 61667 | E4: 65476.524 | F4: 69611
A5: 4 | B5: IFOU Sylvia | C5: 0 | E5: 0 | F5: 0
A6: 5 | B6: KUITCHE Chevalier de Dieu | C6: 56668.333 | E6: 13333.333 | F6: 31933.333
A7: 6 | B7: LELE SIAKA Hernandez | C7: 0 | D7: 125000 | E7: 0 | F7: 0
A8: 7 | B8: MOMIE Emilie | C8: 16190.952 | E8: 3809.5238 | F8: 9123.8095
A9: 8 | B9: MONTE Valdese | C9: 8095.4762 | E9: 1904.7619 | F9: 4561.9048
A10: 9 | B10: NOUTSA Eugène | C10: 32381.905 | E10: 7619.0476 | F10: 18247.619
A11: 10 | B11: SONGOU Sainclaire | C11: 72859.286 | E11: 17142.857 | F11: 41057.143
A12: 11 | B12: TAKOULEU Richardson | C12: 72859.286 | E12: 17142.857 | F12: 41057.143
A13: 12 | B13: TCHIOFO Appolinie | C13: 72859.286 | E13: 17142.857 | F13: 41057.143
A14: 13 | B14: TCHIOFO Fidélia | C14: 56668.333 | D14: 70000 | E14: 13333.333 | F14: 31933.333
A15: 14 | B15: TCHIOFO Paulin | C15: 64763.81 | E15: 15238.095 | F15: 36495.238
A16: 15 | B16: TCHIOFO Rodine | C16: 72859.286 | E16: 17142.857 | F16: 71057.143
A17: 16 | B17: TCHIOFO Sorelle | C17: 64763.81 | E17: 15238.095 | F17: 36495.238
A18: 17 | B18: TITNKHEU Moïse | C18: 72859.286 | E18: 17142.857 | F18: 41057.143
A19: 18 | B19: WANGUN Parfait | C19: 72859.286 | E19: 17142.857 | F19: 41057.143
A20: 19 | B20: YOUDOM Nadine | C20: 64763.81 | E20: 15238.095 | F20: 36495.238
A21: 20 | B21: DAGOBERT | C21: 40000
A22: 21 | B22: DJEUNOU Donna | C22: 120000
A31: Total | C31: =SUM(C2:C30) -> 1250025 | D31: =SUM(D2:D30) -> 256667 | E31: =SUM(E2:E30) -> 261667 | F31: =SUM(F2:F30) -> 569487.19 | G31: =SUM(G2:G30) -> 0 | H31: =SUM(H2:H30) -> 0 | I31: =SUM(I2:I30) -> 0 | J31: =SUM(J2:J30) -> 0 | ... X31: =SUM(X2:X30) -> 0

Sheet epargne_mensuelle_reelle
A1: N° | B1: Nom épargnant | C1: 44470 | D1: 44501 | E1: 44531 | F1: 44562 | G1: 44593 | H1: 44621 | I1: 44652 | J1: 44682 | K1: 44713 | L1: 44743 | M1: 44774 | N1: 44805 | O1: 44835 | P1: 44866 | Q1: 44896 | R1: 44927 | S1: 44958 | T1: 44986 | U1: 45017 | V1: 45047 | W1: 45078 | X1: 45108
A2: 1 | B2: BOUSSEKO Narcisse
A3: 2 | B3: DONGMO Clémence
A4: 3 | B4: DONTSOP Jackson | C4: 240000 | D4: 61667 | E4: 61667 | F4: 60487
A5: 4 | B5: IFOU Sylvia
A6: 5 | B6: KUITCHE Chevalier de Dieu
A7: 6 | B7: LELE SIAKA Hernandez | D7: 125000
A8: 7 | B8: MOMIE Emilie
A9: 8 | B9: MONTE Valdese
A10: 9 | B10: NOUTSA Eugène
A11: 10 | B11: SONGOU Sainclaire
A12: 11 | B12: TAKOULEU Richardson
A13: 12 | B13: TCHIOFO Appolinie
A14: 13 | B14: TCHIOFO Fidélia | D14: 70000
A15: 14 | B15: TCHIOFO Paulin
A16: 15 | B16: TCHIOFO Rodine | F16: 30000
A17: 16 | B17: TCHIOFO Sorelle
A18: 17 | B18: TITNKHEU Moïse
A19: 18 | B19: WANGUN Parfait
A20: 19 | B20: YOUDOM Nadine
A21: 20 | B21: DAGOBERT | C21: 40000
A22: 21 | B22: DJEUNOU Donna | C22: 120000
A31: Total | C31: =SUM(C2:C30) -> 400000 | D31: =SUM(D2:D30) -> 256667 | E31: =SUM(E2:E30) -> 61667 | F31: =SUM(F2:F30) -> 90487 | G31: =SUM(G2:G30) -> 0 | H31: =SUM(H2:H30) -> 0 | I31: =SUM(I2:I30) -> 0 | J31: =SUM(J2:J30) -> 0 | ... X31: =SUM(X2:X30) -> 0
B33: Fonds transféré | C33: 850025 | E33: 200000 | F33: 134000 | G33: 50000
B34: Epargnes 2021 | F34: 350000
C35: =C31+C33 -> 1250025 | D35: =D31+D33 -> 256667 | E35: =E31+E33 -> 261667 | F35: =F31+F33+F34 -> 574487

Sheet apport_mensuel_calcul
A1: N° | B1: Nom épargnant | C1: Epargne Août. 2025 | D1: Interêt M | E1: Epargne Sept. 2025 | F1: AP. M+1 | G1: Intérêt M+1 | H1: Epargne Oct. 2025 | I1: AP. M+2 | J1: Intérêt M+2 | K1: Epargne Nov. 2025 | L1: AP. M+3 | M1: Intérêt M+3 | N1: Epargne Déc. 2025 | O1: AP. M+4 | P1: Intérêt M+4 | Q1: Epargne Janv. 2026 | R1: AP. M+5 | S1: Intérêt M+5 | T1: Epargne Fév. 2026 | U1: AP. M+6 | V1: Intérêt M+6 | W1: Epargne Mars. 2026 | X1: AP. M+7 | Y1: Intérêt M+7 | Z1: Epargne Avril. 2026 | AA1: AP. M+8 | AB1: Intérêt M+8 | AC1: Epargne Mai. 2026 | AD1: AP. M+9 | AE1: Intérêt M+9 | AF1: Epargne Juin. 2026 | AG1: AP. M+10 | AH1: Intérêt M+10 | AI1: Epargne Juil. 2026 | AJ1: AP. M+11 | AK1: Intérêt M+11 | AL1: Epargne Août. 2026 | AM1: AP. M+12 | AN1: Intérêt M+12 | AO1: Epargne Sept. 2026 | AP1: AP. M+13 | AQ1: Intérêt M+13 | AR1: Epargne Oct. 2026 | AS1: AP. M+14 | AT1: Intérêt M+14 | AU1: Epargne Nov. 2026 | AV1: AP. M+15 | AW1: Intérêt M+15 | AX1: Epargne Déc. 2026 | AY1: AP. M+16 | AZ1: Intérêt M+16 | BA1: Epargne Janv. 2027 | BB1: AP. M+17 | BC1: Intérêt M+17 | BD1: Epargne Fév. 2027 | BE1: AP. M+18 | BF1: Intérêt M+18 | BG1: Epargne Mars. 2027 | BH1: AP. M+19 | BI1: Intérêt M+19 | BJ1: Epargne Avril. 2027 | BK1: AP. M+20 | BL1: Intérêt M+20 | BM1: Epargne Mai. 2027 | BN1: AP. M+21 | BO1: Intérêt M+21 | BP1: Epargne Juin. 2027 | BQ1: AP. M+22 | BR1: Intérêt M+22 | BS1: Epargne Juil. 2027 | BT1: AP. M+23 | BU1: Intérêt M+23 | BV1: Total épargne | BW1: Total intérêt | BX1: Total théorique à percevoir | BY1: Bonus/Malus apuration anciennes dettes | BZ1: Total théorique +Bonus-Malus | CA1: Intérêt relatif | CB1: Part relative | CC1: Total net à percevoir
A2: =epargne_mensuelle!A2 -> 1 | B2: =epargne_mensuelle!B2 -> ACTIONNIRE1 | C2: =SUM(epargne_mensuelle!C2:E2) -> 956801.77 | D2: =(C2/C$48)*C$53 -> 120939.88 | E2: =epargne_mensuelle!F2 -> 0 | F2: =C2-(C2/C$48)*C$52+(C2/C$48)*C$53+E2+(C2/C$48)*C$54 -> 143244.18 | G2: =(F2/F$48)*E$53 -> 0 | H2: =epargne_mensuelle!G2 -> 0 | I2: =IF(F$48=0,F2+H2+((C2+E2)/(C$48+E$48))*E$54,F2-((F2/F$48)*E$52)+(F2/F$48)*E$53+H2+((C2+E2)/(C$48+E$48))*E$54) -> 163202.95 | J2: =(I2/I$48)*H$53 -> 15506.393 | K2: =epargne_mensuelle!H2 -> 0 | L2: =IF(I$48=0,I2+K2+((C2+E2+H2)/(C$48+E$48+H$48))*H$54,I2-((I2/I$48)*H$52)+(I2/I$48)*H$53+K2+((C2+E2+H2)/(C$48+E$48+H$48))*H$54) -> 138884.97 | M2: =(L2/L$48)*K$53 -> 5374.4158 | N2: =epargne_mensuelle!I2 -> 0 | O2: =IF(L$48=0,L2+N2+((C2+E2+H2+K2)/(C$48+E$48+H$48+K$48))*K$54,L2-((L2/L$48)*K$52)+(L2/L$48)*K$53+N2+((C2+E2+H2+K2)/(C$48+E$48+H$48+K$48))*K$54) -> 121697.98 | P2: =(O2/O$48)*N$53 -> 1924.1387 | Q2: =epargne_mensuelle!J2 -> 25000 | R2: =IF(O$48=0,O2+Q2+((C2+E2+H2+K2+N2)/(C$48+E$48+H$48+K$48+N$48))*N$54,O2-((O2/O$48)*N$52)+(O2/O$48)*N$53+Q2+((C2+E2+H2+K2+N2)/(C$48+E$48+H$48+K$48+N$48))*N$54) -> 213351.82 | S2: =(R2/R$48)*Q$53 -> 17729.448 | T2: =epargne_mensuelle!K2 -> 0 | U2: =IF(R$48=0,R2+T2+((C2+E2+H2+K2+N2+Q2)/(C$48+E$48+H$48+K$48+N$48+Q$48))*Q$54,R2-((R2/R$48)*Q$52)+(R2/R$48)*Q$53+T2+((C2+E2+H2+K2+N2+Q2)/(C$48+E$48+H$48+K$48+N$48+Q$48))*Q$54) -> 265756.74 | V2: =(U2/U$48)*T$53 -> 0 | W2: =epargne_mensuelle!L2 -> 0 | X2: =IF(U$48=0,U2+W2+((C2+E2+H2+K2+N2+Q2+T2)/(C$48+E$48+H$48+K$48+N$48+Q$48+T$48))*T$54,U2-((U2/U$48)*T$52)+(U2/U$48)*T$53+W2+((C2+E2+H2+K2+N2+Q2+T2)/(C$48+E$48+H$48+K$48+N$48+Q$48+T$48))*T$54) -> 265756.74 | Y2: =(X2/X$48)*W$53 -> 0 | Z2: =epargne_mensuelle!M2 -> 0 | AA2: =IF(X$48=0,X2+Z2+((C2+E2+H2+K2+N2+Q2+T2+W2)/(C$48+E$48+H$48+K$48+N$48+Q$48+T$48+W$48))*W$54,X2-((X2/X$48)*W$52)+(X2/X$48)*W$53+Z2+((C2+E2+H2+K2+N2+Q2+T2+W2)/(C$48+E$48+H$48+K$48+N$48+Q$48+T$48+W$48))*W$54) -> 265756.74 | AB2: =(AA2/AA$48)*Z$53 -> 0 | AC2: =epargne_mensuelle!N2 -> 0 | AD2: =IF(AA$48=0,AA2+AC2+((C2+E2+H2+K2+N2+Q2+T2+W2+Z2)/(C$48+E$48+H$48+K$48+N$48+Q$48+T$48+W$48+Z$48))*Z$54,AA2-((AA2/AA$48)*Z$52)+(AA2/AA$48)*Z$53+AC2+((C2+E2+H2+K2+N2+Q2+T2+W2+Z2)/(C$48+E$48+H$48+K$48+N$48+Q$48+T$48+W$48+Z$48))*Z$54) -> 265756.74 | AE2: =(AD2/AD$48)*AC$53 -> 0 | AF2: =epargne_mensuelle!O2 -> 0 | AG2: =IF(AD$48=0,AD2+AF2+((C2+E2+H2+K2+N2+Q2+T2+W2+Z2+AC2)/(C$48+E$48+H$48+K$48+N$48+Q$48+T$48+W$48+Z$48+AC$48))*AC$54,AD2-((AD2/AD$48)*AC$52)+(AD2/AD$48)*AC$53+AF2+((C2+E2+H2+K2+N2+Q2+T2+W2+Z2+AC2)/(C$48+E$48+H$48+K$48+N$48+Q$48+T$48+W$48+Z$48+AC$48))*AC$54) -> 265756.74 | AH2: =(AG2/AG$48)*AF$53 -> 0 | AI2: =epargne_mensuelle!P2 -> 0 | AJ2: =IF(AG$48=0,AG2+AI2+((C2+E2+H2+K2+N2+Q2+T2+W2+Z2+AC2+AF2)/(C$48+E$48+H$48+K$48+N$48+Q$48+T$48+W$48+Z$48+AC$48+AF$48))*AF$54,AG2-((AG2/AG$48)*AF$52)+(AG2/AG$48)*AF$53+AI2+((C2+E2+H2+K2+N2+Q2+T2+W2+Z2+AC2+AF2)/(C$48+E$48+H$48+K$48+N$48+Q$48+T$48+W$48+Z$48+AC$48+AF$48))*AF$54) -> 265756.74 | AK2: =(AJ2/AJ$48)*AI$53 -> 0 | AL2: =epargne_mensuelle!Q2 -> 0 | AM2: =IF(AJ$48=0,AJ2+AL2+((C2+E2+H2+K2+N2+Q2+T2+W2+Z2+AC2+AF2+AI2)/(C$48+E$48+H$48+K$48+N$48+Q$48+T$48+W$48+Z$48+AC$48+AF$48+AI$48))*AI$54,AJ2-((AJ2/AJ$48)*AI$52)+(AJ2/AJ$48)*AI$53+AL2+((C2+E2+H2+K2+N2+Q2+T2+W2+Z2+AC2+AF2+AI2)/(C$48+E$48+H$48+K$48+N$48+Q$48+T$48+W$48+Z$48+AC$48+AF$48+AI$48))*AI$54) -> 265756.74 | AN2: =(AM2/AM$48)*AL$53 -> 0 | AO2: =epargne_mensuelle!R2 -> 0 | AP2: =IF(AM$48=0,AM2+AO2+((C2+E2+H2+K2+N2+Q2+T2+W2+Z2+AC2+AF2+AI2+AL2)/(C$48+E$48+H$48+K$48+N$48+Q$48+T$48+W$48+Z$48+AC$48+AF$48+AI$48+AL$48))*AL$54,AM2-((AM2/AM$48)*AL$52)+(AM2/AM$48)*AL$53+AO2+((C2+E2+H2+K2+N2+Q2+T2+W2+Z2+AC2+AF2+AI2+AL2)/(C$48+E$48+H$48+K$48+N$48+Q$48+T$48+W$48+Z$48+AC$48+AF$48+AI$48+AL$48))*AL$54) -> 265756.74 | AQ2: =(AP2/AP$48)*AO$53 -> 0 | AR2: =epargne_mensuelle!S2 -> 0 | AS2: =IF(AP$48=0,AP2+AR2+((C2+E2+H2+K2+N2+Q2+T2+W2+Z2+AC2+AF2+AI2+AL2+AO2)/(C$48+E$48+H$48+K$48+N$48+Q$48+T$48+W$48+Z$48+AC$48+AF$48+AI$48+AL$48+AO$48))*AO$54,AP2-((AP2/AP$48)*AO$52)+(AP2/AP$48)*AO$53+AR2+((C2+E2+H2+K2+N2+Q2+T2+W2+Z2+AC2+AF2+AI2+AL2+AO2)/(C$48+E$48+H$48+K$48+N$48+Q$48+T$48+W$48+Z$48+AC$48+AF$48+AI$48+AL$48+AO$48))*AO$54) -> 265756.74 | AT2: =(AS2/AS$48)*AR$53 -> 0 | AU2: =epargne_mensuelle!T2 -> 0 | AV2: =IF(AS$48=0,AS2+AU2+((C2+E2+H2+K2+N2+Q2+T2+W2+Z2+AC2+AF2+AI2+AL2+AO2+AR2)/(C$48+E$48+H$48+K$48+N$48+Q$48+T$48+W$48+Z$48+AC$48+AF$48+AI$48+AL$48+AO$48+AR$48))*AR$54,AS2-((AS2/AS$48)*AR$52)+(AS2/AS$48)*AR$53+AU2+((C2+E2+H2+K2+N2+Q2+T2+W2+Z2+AC2+AF2+AI2+AL2+AO2+AR2)/(C$48+E$48+H$48+K$48+N$48+Q$48+T$48+W$48+Z$48+AC$48+AF$48+AI$48+AL$48+AO$48+AR$48))*AR$54) -> 265756.74 | AW2: =(AV2/AV$48)*AU$53 -> 0 | AX2: =epargne_mensuelle!U2 -> 0 | AY2: =IF(AV$48=0,AV2+AX2+((C2+E2+H2+K2+N2+Q2+T2+W2+Z2+AC2+AF2+AI2+AL2+AO2+AR2+AU2)/(C$48+E$48+H$48+K$48+N$48+Q$48+T$48+W$48+Z$48+AC$48+AF$48+AI$48+AL$48+AO$48+AR$48+AU$48))*AU$54,AV2-((AV2/AV$48)*AU$52)+(AV2/AV$48)*AU$53+AX2+((C2+E2+H2+K2+N2+Q2+T2+W2+Z2+AC2+AF2+AI2+AL2+AO2+AR2+AU2)/(C$48+E$48+H$48+K$48+N$48+Q$48+T$48+W$48+Z$48+AC$48+AF$48+AI$48+AL$48+AO$48+AR$48+AU$48))*AU$54) -> 265756.74 | AZ2: =(AY2/AY$48)*AX$53 -> 0 | BA2: =epargne_mensuelle!V2 -> 0 | BB2: =IF(AY$48=0,AY2+BA2+((C2+E2+H2+K2+N2+Q2+T2+W2+Z2+AC2+AF2+AI2+AL2+AO2+AR2+AU2+AX2)/(C$48+E$48+H$48+K$48+N$48+Q$48+T$48+W$48+Z$48+AC$48+AF$48+AI$48+AL$48+AO$48+AR$48+AU$48+AX$48))*AX$54,AY2-((AY2/AY$48)*AX$52)+(AY2/AY$48)*AX$53+BA2+((C2+E2+H2+K2+N2+Q2+T2+W2+Z2+AC2+AF2+AI2+AL2+AO2+AR2+AU2+AX2)/(C$48+E$48+H$48+K$48+N$48+Q$48+T$48+W$48+Z$48+AC$48+AF$48+AI$48+AL$48+AO$48+AR$48+AU$48+AX$48))*AX$54) -> 265756.74 | BC2: =(BB2/BB$48)*BA$53 -> 0 | BD2: =epargne_mensuelle!W2 -> 0 | BE2: =IF(BB$48=0,BB2+BD2+((C2+E2+H2+K2+N2+Q2+T2+W2+Z2+AC2+AF2+AI2+AL2+AO2+AR2+AU2+AX2+BA2)/(C$48+E$48+H$48+K$48+N$48+Q$48+T$48+W$48+Z$48+AC$48+AF$48+AI$48+AL$48+AO$48+AR$48+AU$48+AX$48+BA$48))*BA$54,BB2-((BB2/BB$48)*BA$52)+(BB2/BB$48)*BA$53+BD2+((C2+E2+H2+K2+N2+Q2+T2+W2+Z2+AC2+AF2+AI2+AL2+AO2+AR2+AU2+AX2+BA2)/(C$48+E$48+H$48+K$48+N$48+Q$48+T$48+W$48+Z$48+AC$48+AF$48+AI$48+AL$48+AO$48+AR$48+AU$48+AX$48+BA$48))*BA$54) -> 265756.74 | BF2: =(BE2/BE$48)*BD$53 -> 0 | BG2: =epargne_mensuelle!X2 -> 0 | BH2: =IF(BE$48=0,BE2+BG2+((C2+E2+H2+K2+N2+Q2+T2+W2+Z2+AC2+AF2+AI2+AL2+AO2+AR2+AU2+AX2+BA2+BD2)/(C$48+E$48+H$48+K$48+N$48+Q$48+T$48+W$48+Z$48+AC$48+AF$48+AI$48+AL$48+AO$48+AR$48+AU$48+AX$48+BA$48+BD$48))*BD$54,BE2-((BE2/BE$48)*BD$52)+(BE2/BE$48)*BD$53+BG2+((C2+E2+H2+K2+N2+Q2+T2+W2+Z2+AC2+AF2+AI2+AL2+AO2+AR2+AU2+AX2+BA2+BD2)/(C$48+E$48+H$48+K$48+N$48+Q$48+T$48+W$48+Z$48+AC$48+AF$48+AI$48+AL$48+AO$48+AR$48+AU$48+AX$48+BA$48+BD$48))*BD$54) -> 265756.74 | BI2: =(BH2/BH$48)*BG$53 -> 0 | BJ2: =epargne_mensuelle!Y2 -> 0 | BK2: =IF(BH$48=0,BH2+BJ2+((C2+E2+H2+K2+N2+Q2+T2+W2+Z2+AC2+AF2+AI2+AL2+AO2+AR2+AU2+AX2+BA2+BD2+BG2)/(C$48+E$48+H$48+K$48+N$48+Q$48+T$48+W$48+Z$48+AC$48+AF$48+AI$48+AL$48+AO$48+AR$48+AU$48+AX$48+BA$48+BD$48+BG$48))*BG$54,BH2-((BH2/BH$48)*BG$52)+(BH2/BH$48)*BG$53+BJ2+((C2+E2+H2+K2+N2+Q2+T2+W2+Z2+AC2+AF2+AI2+AL2+AO2+AR2+AU2+AX2+BA2+BD2+BG2)/(C$48+E$48+H$48+K$48+N$48+Q$48+T$48+W$48+Z$48+AC$48+AF$48+AI$48+AL$48+AO$48+AR$48+AU$48+AX$48+BA$48+BD$48+BG$48))*BG$54) -> 265756.74 | BL2: =(BK2/BK$48)*BJ$53 -> 0 | BM2: =epargne_mensuelle!Z2 -> 0 | BN2: =IF(BK$48=0,BK2+BM2+((C2+E2+H2+K2+N2+Q2+T2+W2+Z2+AC2+AF2+AI2+AL2+AO2+AR2+AU2+AX2+BA2+BD2+BG2+BJ2)/(C$48+E$48+H$48+K$48+N$48+Q$48+T$48+W$48+Z$48+AC$48+AF$48+AI$48+AL$48+AO$48+AR$48+AU$48+AX$48+BA$48+BD$48+BG$48+BJ$48))*BJ$54,BK2-((BK2/BK$48)*BJ$52)+(BK2/BK$48)*BJ$53+BM2+((C2+E2+H2+K2+N2+Q2+T2+W2+Z2+AC2+AF2+AI2+AL2+AO2+AR2+AU2+AX2+BA2+BD2+BG2+BJ2)/(C$48+E$48+H$48+K$48+N$48+Q$48+T$48+W$48+Z$48+AC$48+AF$48+AI$48+AL$48+AO$48+AR$48+AU$48+AX$48+BA$48+BD$48+BG$48+BJ$48))*BJ$54) -> 265756.74 | BO2: =(BN2/BN$48)*BM$53 -> 0 | BP2: =epargne_mensuelle!AA2 -> 0 | BQ2: =IF(BN$48=0,BN2+BP2+((F2+H2+K2+N2+Q2+T2+W2+Z2+AC2+AF2+AI2+AL2+AO2+AR2+AU2+AX2+BA2+BD2+BG2+BJ2+BM2)/(F$48+H$48+K$48+N$48+Q$48+T$48+W$48+Z$48+AC$48+AF$48+AI$48+AL$48+AO$48+AR$48+AU$48+AX$48+BA$48+BD$48+BG$48+BJ$48+BM$48))*BM$54,BN2-((BN2/BN$48)*BM$52)+(BN2/BN$48)*BM$53+BP2+((F2+H2+K2+N2+Q2+T2+W2+Z2+AC2+AF2+AI2+AL2+AO2+AR2+AU2+AX2+BA2+BD2+BG2+BJ2+BM2)/(F$48+H$48+K$48+N$48+Q$48+T$48+W$48+Z$48+AC$48+AF$48+AI$48+AL$48+AO$48+AR$48+AU$48+AX$48+BA$48+BD$48+BG$48+BJ$48+BM$48))*BM$54) -> 265756.74 | BR2: =(BQ2/BQ$48)*BP$53 -> 0 | BS2: =epargne_mensuelle!AB2 -> 0 | BT2: =IF(BQ$48=0,BQ2+BS2+((I2+K2+N2+Q2+T2+W2+Z2+AC2+AF2+AI2+AL2+AO2+AR2+AU2+AX2+BA2+BD2+BG2+BJ2+BM2+BP2)/(I$48+K$48+N$48+Q$48+T$48+W$48+Z$48+AC$48+AF$48+AI$48+AL$48+AO$48+AR$48+AU$48+AX$48+BA$48+BD$48+BG$48+BJ$48+BM$48+BP$48))*BP$54,BQ2-((BQ2/BQ$48)*BP$52)+(BQ2/BQ$48)*BP$53+BS2+((I2+K2+N2+Q2+T2+W2+Z2+AC2+AF2+AI2+AL2+AO2+AR2+AU2+AX2+BA2+BD2+BG2+BJ2+BM2+BP2)/(I$48+K$48+N$48+Q$48+T$48+W$48+Z$48+AC$48+AF$48+AI$48+AL$48+AO$48+AR$48+AU$48+AX$48+BA$48+BD$48+BG$48+BJ$48+BM$48+BP$48))*BP$54) -> 265756.74 | BU2: =(BT2/BT$48)*BS$53 -> 0 | BV2: =cumul_epargne!C2 -> 981801.77 | BW2: =D2+G2+J2+M2+P2+S2+V2+Y2+AB2+AE2+AH2+AK2+AN2+AQ2+AT2+AW2+AZ2+BC2+BF2+BI2+BL2+BO2+BR2+BU2 -> 161474.28 | BX2: =IF(BV2="",BW2,BV2+BW2) -> 1143276.1 | BZ2: =BX2+BY2 -> 1143276.1 | CA2: =IF(BV2="","",BW2/BV2) -> 0.16446729 | CB2: =BZ2/BZ$48 -> 0.025200719 | CC2: =CB2*(C$50-BW$58-BW$57) -> 109088.95 | CD2: =B2 -> ACTIONNIRE1
A3: =epargne_mensuelle!A3 -> 2 | B3: =epargne_mensuelle!B3 -> ACTIONNIRE2 | C3: =SUM(epargne_mensuelle!C3:E3) -> 270897.47 | D3: =(C3/C$48)*C$53 -> 34241.48 | E3: =epargne_mensuelle!F3 -> 0 | F3: =C3-(C3/C$48)*C$52+(C3/C$48)*C$53+E3+(C3/C$48)*C$54 -> 40556.453 | G3: =(F3/F$48)*E$53 -> 0 | H3: =epargne_mensuelle!G3 -> 300000 | I3: =IF(F$48=0,F3+H3+((C3+E3)/(C$48+E$48))*E$54,F3-((F3/F$48)*E$52)+(F3/F$48)*E$53+H3+((C3+E3)/(C$48+E$48))*E$54) -> 346207.34 | J3: =(I3/I$48)*H$53 -> 32894.179 | K3: =epargne_mensuelle!H3 -> 0 | L3: =IF(I$48=0,I3+K3+((C3+E3+H3)/(C$48+E$48+H$48))*H$54,I3-((I3/I$48)*H$52)+(I3/I$48)*H$53+K3+((C3+E3+H3)/(C$48+E$48+H$48))*H$54) -> 167933.8 | M3: =(L3/L$48)*K$53 -> 6498.515 | N3: =epargne_mensuelle!I3 -> 0 | O3: =IF(L$48=0,L3+N3+((C3+E3+H3+K3)/(C$48+E$48+H$48+K$48))*K$54,L3-((L3/L$48)*K$52)+(L3/L$48)*K$53+N3+((C3+E3+H3+K3)/(C$48+E$48+H$48+K$48))*K$54) -> 107160.87 | P3: =(O3/O$48)*N$53 -> 1694.2958 | Q3: =epargne_mensuelle!J3 -> 0 | R3: =IF(O$48=0,O3+Q3+((C3+E3+H3+K3+N3)/(C$48+E$48+H$48+K$48+N$48))*N$54,O3-((O3/O$48)*N$52)+(O3/O$48)*N$53+Q3+((C3+E3+H3+K3+N3)/(C$48+E$48+H$48+K$48+N$48))*N$54) -> 133822.24 | S3: =(R3/R$48)*Q$53 -> 11120.573 | T3: =epargne_mensuelle!K3 -> 0 | U3: =IF(R$48=0,R3+T3+((C3+E3+H3+K3+N3+Q3)/(C$48+E$48+H$48+K$48+N$48+Q$48))*Q$54,R3-((R3/R$48)*Q$52)+(R3/R$48)*Q$53+T3+((C3+E3+H3+K3+N3+Q3)/(C$48+E$48+H$48+K$48+N$48+Q$48))*Q$54) -> 161725.61 | V3: =(U3/U$48)*T$53 -> 0 | W3: =epargne_mensuelle!L3 -> 0 | X3: =IF(U$48=0,U3+W3+((C3+E3+H3+K3+N3+Q3+T3)/(C$48+E$48+H$48+K$48+N$48+Q$48+T$48))*T$54,U3-((U3/U$48)*T$52)+(U3/U$48)*T$53+W3+((C3+E3+H3+K3+N3+Q3+T3)/(C$48+E$48+H$48+K$48+N$48+Q$48+T$48))*T$54) -> 161725.61 | Y3: =(X3/X$48)*W$53 -> 0 | Z3: =epargne_mensuelle!M3 -> 0 | AA3: =IF(X$48=0,X3+Z3+((C3+E3+H3+K3+N3+Q3+T3+W3)/(C$48+E$48+H$48+K$48+N$48+Q$48+T$48+W$48))*W$54,X3-((X3/X$48)*W$52)+(X3/X$48)*W$53+Z3+((C3+E3+H3+K3+N3+Q3+T3+W3)/(C$48+E$48+H$48+K$48+N$48+Q$48+T$48+W$48))*W$54) -> 161725.61 | AB3: =(AA3/AA$48)*Z$53 -> 0 | AC3: =epargne_mensuelle!N3 -> 0 | AD3: =IF(AA$48=0,AA3+AC3+((C3+E3+H3+K3+N3+Q3+T3+W3+Z3)/(C$48+E$48+H$48+K$48+N$48+Q$48+T$48+W$48+Z$48))*Z$54,AA3-((AA3/AA$48)*Z$52)+(AA3/AA$48)*Z$53+AC3+((C3+E3+H3+K3+N3+Q3+T3+W3+Z3)/(C$48+E$48+H$48+K$48+N$48+Q$48+T$48+W$48+Z$48))*Z$54) -> 161725.61 | AE3: =(AD3/AD$48)*AC$53 -> 0 | AF3: =epargne_mensuelle!O3 -> 0 | AG3: =IF(AD$48=0,AD3+AF3+((C3+E3+H3+K3+N3+Q3+T3+W3+Z3+AC3)/(C$48+E$48+H$48+K$48+N$48+Q$48+T$48+W$48+Z$48+AC$48))*AC$54,AD3-((AD3/AD$48)*AC$52)+(AD3/AD$48)*AC$53+AF3+((C3+E3+H3+K3+N3+Q3+T3+W3+Z3+AC3)/(C$48+E$48+H$48+K$48+N$48+Q$48+T$48+W$48+Z$48+AC$48))*AC$54) -> 161725.61 | AH3: =(AG3/AG$48)*AF$53 -> 0 | AI3: =epargne_mensuelle!P3 -> 0 | AJ3: =IF(AG$48=0,AG3+AI3+((C3+E3+H3+K3+N3+Q3+T3+W3+Z3+AC3+AF3)/(C$48+E$48+H$48+K$48+N$48+Q$48+T$48+W$48+Z$48+AC$48+AF$48))*AF$54,AG3-((AG3/AG$48)*AF$52)+(AG3/AG$48)*AF$53+AI3+((C3+E3+H3+K3+N3+Q3+T3+W3+Z3+AC3+AF3)/(C$48+E$48+H$48+K$48+N$48+Q$48+T$48+W$48+Z$48+AC$48+AF$48))*AF$54) -> 161725.61 | AK3: =(AJ3/AJ$48)*AI$53 -> 0 | AL3: =epargne_mensuelle!Q3 -> 0 | AM3: =IF(AJ$48=0,AJ3+AL3+((C3+E3+H3+K3+N3+Q3+T3+W3+Z3+AC3+AF3+AI3)/(C$48+E$48+H$48+K$48+N$48+Q$48+T$48+W$48+Z$48+AC$48+AF$48+AI$48))*AI$54,AJ3-((AJ3/AJ$48)*AI$52)+(AJ3/AJ$48)*AI$53+AL3+((C3+E3+H3+K3+N3+Q3+T3+W3+Z3+AC3+AF3+AI3)/(C$48+E$48+H$48+K$48+N$48+Q$48+T$48+W$48+Z$48+AC$48+AF$48+AI$48))*AI$54) -> 161725.61 | AN3: =(AM3/AM$48)*AL$53 -> 0 | AO3: =epargne_mensuelle!R3 -> 0 | AP3: =IF(AM$48=0,AM3+AO3+((C3+E3+H3+K3+N3+Q3+T3+W3+Z3+AC3+AF3+AI3+AL3)/(C$48+E$48+H$48+K$48+N$48+Q$48+T$48+W$48+Z$48+AC$48+AF$48+AI$48+AL$48))*AL$54,AM3-((AM3/AM$48)*AL$52)+(AM3/AM$48)*AL$53+AO3+((C3+E3+H3+K3+N3+Q3+T3+W3+Z3+AC3+AF3+AI3+AL3)/(C$48+E$48+H$48+K$48+N$48+Q$48+T$48+W$48+Z$48+AC$48+AF$48+AI$48+AL$48))*AL$54) -> 161725.61 | AQ3: =(AP3/AP$48)*AO$53 -> 0 | AR3: =epargne_mensuelle!S3 -> 0 | AS3: =IF(AP$48=0,AP3+AR3+((C3+E3+H3+K3+N3+Q3+T3+W3+Z3+AC3+AF3+AI3+AL3+AO3)/(C$48+E$48+H$48+K$48+N$48+Q$48+T$48+W$48+Z$48+AC$48+AF$48+AI$48+AL$48+AO$48))*AO$54,AP3-((AP3/AP$48)*AO$52)+(AP3/AP$48)*AO$53+AR3+((C3+E3+H3+K3+N3+Q3+T3+W3+Z3+AC3+AF3+AI3+AL3+AO3)/(C$48+E$48+H$48+K$48+N$48+Q$48+T$48+W$48+Z$48+AC$48+AF$48+AI$48+AL$48+AO$48))*AO$54) -> 161725.61 | AT3: =(AS3/AS$48)*AR$53 -> 0 | AU3: =epargne_mensuelle!T3 -> 0 | AV3: =IF(AS$48=0,AS3+AU3+((C3+E3+H3+K3+N3+Q3+T3+W3+Z3+AC3+AF3+AI3+AL3+AO3+AR3)/(C$48+E$48+H$48+K$48+N$48+Q$48+T$48+W$48+Z$48+AC$48+AF$48+AI$48+AL$48+AO$48+AR$48))*AR$54,AS3-((AS3/AS$48)*AR$52)+(AS3/AS$48)*AR$53+AU3+((C3+E3+H3+K3+N3+Q3+T3+W3+Z3+AC3+AF3+AI3+AL3+AO3+AR3)/(C$48+E$48+H$48+K$48+N$48+Q$48+T$48+W$48+Z$48+AC$48+AF$48+AI$48+AL$48+AO$48+AR$48))*AR$54) -> 161725.61 | AW3: =(AV3/AV$48)*AU$53 -> 0 | AX3: =epargne_mensuelle!U3 -> 0 | AY3: =IF(AV$48=0,AV3+AX3+((C3+E3+H3+K3+N3+Q3+T3+W3+Z3+AC3+AF3+AI3+AL3+AO3+AR3+AU3)/(C$48+E$48+H$48+K$48+N$48+Q$48+T$48+W$48+Z$48+AC$48+AF$48+AI$48+AL$48+AO$48+AR$48+AU$48))*AU$54,AV3-((AV3/AV$48)*AU$52)+(AV3/AV$48)*AU$53+AX3+((C3+E3+H3+K3+N3+Q3+T3+W3+Z3+AC3+AF3+AI3+AL3+AO3+AR3+AU3)/(C$48+E$48+H$48+K$48+N$48+Q$48+T$48+W$48+Z$48+AC$48+AF$48+AI$48+AL$48+AO$48+AR$48+AU$48))*AU$54) -> 161725.61 | AZ3: =(AY3/AY$48)*AX$53 -> 0 | BA3: =epargne_mensuelle!V3 -> 0 | BB3: =IF(AY$48=0,AY3+BA3+((C3+E3+H3+K3+N3+Q3+T3+W3+Z3+AC3+AF3+AI3+AL3+AO3+AR3+AU3+AX3)/(C$48+E$48+H$48+K$48+N$48+Q$48+T$48+W$48+Z$48+AC$48+AF$48+AI$48+AL$48+AO$48+AR$48+AU$48+AX$48))*AX$54,AY3-((AY3/AY$48)*AX$52)+(AY3/AY$48)*AX$53+BA3+((C3+E3+H3+K3+N3+Q3+T3+W3+Z3+AC3+AF3+AI3+AL3+AO3+AR3+AU3+AX3)/(C$48+E$48+H$48+K$48+N$48+Q$48+T$48+W$48+Z$48+AC$48+AF$48+AI$48+AL$48+AO$48+AR$48+AU$48+AX$48))*AX$54) -> 161725.61 | BC3: =(BB3/BB$48)*BA$53 -> 0 | BD3: =epargne_mensuelle!W3 -> 0 | BE3: =IF(BB$48=0,BB3+BD3+((C3+E3+H3+K3+N3+Q3+T3+W3+Z3+AC3+AF3+AI3+AL3+AO3+AR3+AU3+AX3+BA3)/(C$48+E$48+H$48+K$48+N$48+Q$48+T$48+W$48+Z$48+AC$48+AF$48+AI$48+AL$48+AO$48+AR$48+AU$48+AX$48+BA$48))*BA$54,BB3-((BB3/BB$48)*BA$52)+(BB3/BB$48)*BA$53+BD3+((C3+E3+H3+K3+N3+Q3+T3+W3+Z3+AC3+AF3+AI3+AL3+AO3+AR3+AU3+AX3+BA3)/(C$48+E$48+H$48+K$48+N$48+Q$48+T$48+W$48+Z$48+AC$48+AF$48+AI$48+AL$48+AO$48+AR$48+AU$48+AX$48+BA$48))*BA$54) -> 161725.61 | BF3: =(BE3/BE$48)*BD$53 -> 0 | BG3: =epargne_mensuelle!X3 -> 0 | BH3: =IF(BE$48=0,BE3+BG3+((C3+E3+H3+K3+N3+Q3+T3+W3+Z3+AC3+AF3+AI3+AL3+AO3+AR3+AU3+AX3+BA3+BD3)/(C$48+E$48+H$48+K$48+N$48+Q$48+T$48+W$48+Z$48+AC$48+AF$48+AI$48+AL$48+AO$48+AR$48+AU$48+AX$48+BA$48+BD$48))*BD$54,BE3-((BE3/BE$48)*BD$52)+(BE3/BE$48)*BD$53+BG3+((C3+E3+H3+K3+N3+Q3+T3+W3+Z3+AC3+AF3+AI3+AL3+AO3+AR3+AU3+AX3+BA3+BD3)/(C$48+E$48+H$48+K$48+N$48+Q$48+T$48+W$48+Z$48+AC$48+AF$48+AI$48+AL$48+AO$48+AR$48+AU$48+AX$48+BA$48+BD$48))*BD$54) -> 161725.61 | BI3: =(BH3/BH$48)*BG$53 -> 0 | BJ3: =epargne_mensuelle!Y3 -> 0 | BK3: =IF(BH$48=0,BH3+BJ3+((C3+E3+H3+K3+N3+Q3+T3+W3+Z3+AC3+AF3+AI3+AL3+AO3+AR3+AU3+AX3+BA3+BD3+BG3)/(C$48+E$48+H$48+K$48+N$48+Q$48+T$48+W$48+Z$48+AC$48+AF$48+AI$48+AL$48+AO$48+AR$48+AU$48+AX$48+BA$48+BD$48+BG$48))*BG$54,BH3-((BH3/BH$48)*BG$52)+(BH3/BH$48)*BG$53+BJ3+((C3+E3+H3+K3+N3+Q3+T3+W3+Z3+AC3+AF3+AI3+AL3+AO3+AR3+AU3+AX3+BA3+BD3+BG3)/(C$48+E$48+H$48+K$48+N$48+Q$48+T$48+W$48+Z$48+AC$48+AF$48+AI$48+AL$48+AO$48+AR$48+AU$48+AX$48+BA$48+BD$48+BG$48))*BG$54) -> 161725.61 | BL3: =(BK3/BK$48)*BJ$53 -> 0 | BM3: =epargne_mensuelle!Z3 -> 0 | BN3: =IF(BK$48=0,BK3+BM3+((C3+E3+H3+K3+N3+Q3+T3+W3+Z3+AC3+AF3+AI3+AL3+AO3+AR3+AU3+AX3+BA3+BD3+BG3+BJ3)/(C$48+E$48+H$48+K$48+N$48+Q$48+T$48+W$48+Z$48+AC$48+AF$48+AI$48+AL$48+AO$48+AR$48+AU$48+AX$48+BA$48+BD$48+BG$48+BJ$48))*BJ$54,BK3-((BK3/BK$48)*BJ$52)+(BK3/BK$48)*BJ$53+BM3+((C3+E3+H3+K3+N3+Q3+T3+W3+Z3+AC3+AF3+AI3+AL3+AO3+AR3+AU3+AX3+BA3+BD3+BG3+BJ3)/(C$48+E$48+H$48+K$48+N$48+Q$48+T$48+W$48+Z$48+AC$48+AF$48+AI$48+AL$48+AO$48+AR$48+AU$48+AX$48+BA$48+BD$48+BG$48+BJ$48))*BJ$54) -> 161725.61 | BO3: =(BN3/BN$48)*BM$53 -> 0 | BP3: =epargne_mensuelle!AA3 -> 0 | BQ3: =IF(BN$48=0,BN3+BP3+((F3+H3+K3+N3+Q3+T3+W3+Z3+AC3+AF3+AI3+AL3+AO3+AR3+AU3+AX3+BA3+BD3+BG3+BJ3+BM3)/(F$48+H$48+K$48+N$48+Q$48+T$48+W$48+Z$48+AC$48+AF$48+AI$48+AL$48+AO$48+AR$48+AU$48+AX$48+BA$48+BD$48+BG$48+BJ$48+BM$48))*BM$54,BN3-((BN3/BN$48)*BM$52)+(BN3/BN$48)*BM$53+BP3+((F3+H3+K3+N3+Q3+T3+W3+Z3+AC3+AF3+AI3+AL3+AO3+AR3+AU3+AX3+BA3+BD3+BG3+BJ3+BM3)/(F$48+H$48+K$48+N$48+Q$48+T$48+W$48+Z$48+AC$48+AF$48+AI$48+AL$48+AO$48+AR$48+AU$48+AX$48+BA$48+BD$48+BG$48+BJ$48+BM$48))*BM$54) -> 161725.61 | BR3: =(BQ3/BQ$48)*BP$53 -> 0 | BS3: =epargne_mensuelle!AB3 -> 0 | BT3: =IF(BQ$48=0,BQ3+BS3+((I3+K3+N3+Q3+T3+W3+Z3+AC3+AF3+AI3+AL3+AO3+AR3+AU3+AX3+BA3+BD3+BG3+BJ3+BM3+BP3)/(I$48+K$48+N$48+Q$48+T$48+W$48+Z$48+AC$48+AF$48+AI$48+AL$48+AO$48+AR$48+AU$48+AX$48+BA$48+BD$48+BG$48+BJ$48+BM$48+BP$48))*BP$54,BQ3-((BQ3/BQ$48)*BP$52)+(BQ3/BQ$48)*BP$53+BS3+((I3+K3+N3+Q3+T3+W3+Z3+AC3+AF3+AI3+AL3+AO3+AR3+AU3+AX3+BA3+BD3+BG3+BJ3+BM3+BP3)/(I$48+K$48+N$48+Q$48+T$48+W$48+Z$48+AC$48+AF$48+AI$48+AL$48+AO$48+AR$48+AU$48+AX$48+BA$48+BD$48+BG$48+BJ$48+BM$48+BP$48))*BP$54) -> 161725.61 | BU3: =(BT3/BT$48)*BS$53 -> 0 | BV3: =cumul_epargne!C3 -> 570897.47 | BW3: =D3+G3+J3+M3+P3+S3+V3+Y3+AB3+AE3+AH3+AK3+AN3+AQ3+AT3+AW3+AZ3+BC3+BF3+BI3+BL3+BO3+BR3+BU3 -> 86449.043 | BX3: =IF(BV3="",BW3,BV3+BW3) -> 657346.51 | BZ3: =BX3+BY3 -> 657346.51 | CA3: =IF(BV3="","",BW3/BV3) -> 0.15142657 | CB3: =BZ3/BZ$48 -> 0.014489593 | CC3: =CB3*(C$50-BW$58-BW$57) -> 62722.594 | CD3: =B3 -> ACTIONNIRE2
A4: =epargne_mensuelle!A4 -> 3 | B4: =epargne_mensuelle!B4 -> ACTIONNIRE3 | C4: =SUM(epargne_mensuelle!C4:E4) -> 4008079.8 | D4: =(C4/C$48)*C$53 -> 506621.87 | E4: =epargne_mensuelle!F4 -> 0 | F4: =C4-(C4/C$48)*C$52+(C4/C$48)*C$53+E4+(C4/C$48)*C$54 -> 600055.43 | G4: =(F4/F$48)*E$53 -> 0 | H4: =epargne_mensuelle!G4 -> 0 | I4: =IF(F$48=0,F4+H4+((C4+E4)/(C$48+E$48))*E$54,F4-((F4/F$48)*E$52)+(F4/F$48)*E$53+H4+((C4+E4)/(C$48+E$48))*E$54) -> 683663.51 | J4: =(I4/I$48)*H$53 -> 64956.883 | K4: =epargne_mensuelle!H4 -> 0 | L4: =IF(I$48=0,I4+K4+((C4+E4+H4)/(C$48+E$48+H$48))*H$54,I4-((I4/I$48)*H$52)+(I4/I$48)*H$53+K4+((C4+E4+H4)/(C$48+E$48+H$48))*H$54) -> 581794.52 | M4: =(L4/L$48)*K$53 -> 22513.636 | N4: =epargne_mensuelle!I4 -> 0 | O4: =IF(L$48=0,L4+N4+((C4+E4+H4+K4)/(C$48+E$48+H$48+K$48))*K$54,L4-((L4/L$48)*K$52)+(L4/L$48)*K$53+N4+((C4+E4+H4+K4)/(C$48+E$48+H$48+K$48))*K$54) -> 509797.57 | P4: =(O4/O$48)*N$53 -> 8060.2917 | Q4: =epargne_mensuelle!J4 -> 0 | R4: =IF(O$48=0,O4+Q4+((C4+E4+H4+K4+N4)/(C$48+E$48+H$48+K$48+N$48))*N$54,O4-((O4/O$48)*N$52)+(O4/O$48)*N$53+Q4+((C4+E4+H4+K4+N4)/(C$48+E$48+H$48+K$48+N$48))*N$54) -> 789013.09 | S4: =(R4/R$48)*Q$53 -> 65566.662 | T4: =epargne_mensuelle!K4 -> 0 | U4: =IF(R$48=0,R4+T4+((C4+E4+H4+K4+N4+Q4)/(C$48+E$48+H$48+K$48+N$48+Q$48))*Q$54,R4-((R4/R$48)*Q$52)+(R4/R$48)*Q$53+T4+((C4+E4+H4+K4+N4+Q4)/(C$48+E$48+H$48+K$48+N$48+Q$48))*Q$54) -> 1024519.3 | V4: =(U4/U$48)*T$53 -> 0 | W4: =epargne_mensuelle!L4 -> 0 | X4: =IF(U$48=0,U4+W4+((C4+E4+H4+K4+N4+Q4+T4)/(C$48+E$48+H$48+K$48+N$48+Q$48+T$48))*T$54,U4-((U4/U$48)*T$52)+(U4/U$48)*T$53+W4+((C4+E4+H4+K4+N4+Q4+T4)/(C$48+E$48+H$48+K$48+N$48+Q$48+T$48))*T$54) -> 1024519.3 | Y4: =(X4/X$48)*W$53 -> 0 | Z4: =epargne_mensuelle!M4 -> 0 | AA4: =IF(X$48=0,X4+Z4+((C4+E4+H4+K4+N4+Q4+T4+W4)/(C$48+E$48+H$48+K$48+N$48+Q$48+T$48+W$48))*W$54,X4-((X4/X$48)*W$52)+(X4/X$48)*W$53+Z4+((C4+E4+H4+K4+N4+Q4+T4+W4)/(C$48+E$48+H$48+K$48+N$48+Q$48+T$48+W$48))*W$54) -> 1024519.3 | AB4: =(AA4/AA$48)*Z$53 -> 0 | AC4: =epargne_mensuelle!N4 -> 0 | AD4: =IF(AA$48=0,AA4+AC4+((C4+E4+H4+K4+N4+Q4+T4+W4+Z4)/(C$48+E$48+H$48+K$48+N$48+Q$48+T$48+W$48+Z$48))*Z$54,AA4-((AA4/AA$48)*Z$52)+(AA4/AA$48)*Z$53+AC4+((C4+E4+H4+K4+N4+Q4+T4+W4+Z4)/(C$48+E$48+H$48+K$48+N$48+Q$48+T$48+W$48+Z$48))*Z$54) -> 1024519.3 | AE4: =(AD4/AD$48)*AC$53 -> 0 | AF4: =epargne_mensuelle!O4 -> 0 | AG4: =IF(AD$48=0,AD4+AF4+((C4+E4+H4+K4+N4+Q4+T4+W4+Z4+AC4)/(C$48+E$48+H$48+K$48+N$48+Q$48+T$48+W$48+Z$48+AC$48))*AC$54,AD4-((AD4/AD$48)*AC$52)+(AD4/AD$48)*AC$53+AF4+((C4+E4+H4+K4+N4+Q4+T4+W4+Z4+AC4)/(C$48+E$48+H$48+K$48+N$48+Q$48+T$48+W$48+Z$48+AC$48))*AC$54) -> 1024519.3 | AH4: =(AG4/AG$48)*AF$53 -> 0 | AI4: =epargne_mensuelle!P4 -> 0 | AJ4: =IF(AG$48=0,AG4+AI4+((C4+E4+H4+K4+N4+Q4+T4+W4+Z4+AC4+AF4)/(C$48+E$48+H$48+K$48+N$48+Q$48+T$48+W$48+Z$48+AC$48+AF$48))*AF$54,AG4-((AG4/AG$48)*AF$52)+(AG4/AG$48)*AF$53+AI4+((C4+E4+H4+K4+N4+Q4+T4+W4+Z4+AC4+AF4)/(C$48+E$48+H$48+K$48+N$48+Q$48+T$48+W$48+Z$48+AC$48+AF$48))*AF$54) -> 1024519.3 | AK4: =(AJ4/AJ$48)*AI$53 -> 0 | AL4: =epargne_mensuelle!Q4 -> 0 | AM4: =IF(AJ$48=0,AJ4+AL4+((C4+E4+H4+K4+N4+Q4+T4+W4+Z4+AC4+AF4+AI4)/(C$48+E$48+H$48+K$48+N$48+Q$48+T$48+W$48+Z$48+AC$48+AF$48+AI$48))*AI$54,AJ4-((AJ4/AJ$48)*AI$52)+(AJ4/AJ$48)*AI$53+AL4+((C4+E4+H4+K4+N4+Q4+T4+W4+Z4+AC4+AF4+AI4)/(C$48+E$48+H$48+K$48+N$48+Q$48+T$48+W$48+Z$48+AC$48+AF$48+AI$48))*AI$54) -> 1024519.3 | AN4: =(AM4/AM$48)*AL$53 -> 0 | AO4: =epargne_mensuelle!R4 -> 0 | AP4: =IF(AM$48=0,AM4+AO4+((C4+E4+H4+K4+N4+Q4+T4+W4+Z4+AC4+AF4+AI4+AL4)/(C$48+E$48+H$48+K$48+N$48+Q$48+T$48+W$48+Z$48+AC$48+AF$48+AI$48+AL$48))*AL$54,AM4-((AM4/AM$48)*AL$52)+(AM4/AM$48)*AL$53+AO4+((C4+E4+H4+K4+N4+Q4+T4+W4+Z4+AC4+AF4+AI4+AL4)/(C$48+E$48+H$48+K$48+N$48+Q$48+T$48+W$48+Z$48+AC$48+AF$48+AI$48+AL$48))*AL$54) -> 1024519.3 | AQ4: =(AP4/AP$48)*AO$53 -> 0 | AR4: =epargne_mensuelle!S4 -> 0 | AS4: =IF(AP$48=0,AP4+AR4+((C4+E4+H4+K4+N4+Q4+T4+W4+Z4+AC4+AF4+AI4+AL4+AO4)/(C$48+E$48+H$48+K$48+N$48+Q$48+T$48+W$48+Z$48+AC$48+AF$48+AI$48+AL$48+AO$48))*AO$54,AP4-((AP4/AP$48)*AO$52)+(AP4/AP$48)*AO$53+AR4+((C4+E4+H4+K4+N4+Q4+T4+W4+Z4+AC4+AF4+AI4+AL4+AO4)/(C$48+E$48+H$48+K$48+N$48+Q$48+T$48+W$48+Z$48+AC$48+AF$48+AI$48+AL$48+AO$48))*AO$54) -> 1024519.3 | AT4: =(AS4/AS$48)*AR$53 -> 0 | AU4: =epargne_mensuelle!T4 -> 0 | AV4: =IF(AS$48=0,AS4+AU4+((C4+E4+H4+K4+N4+Q4+T4+W4+Z4+AC4+AF4+AI4+AL4+AO4+AR4)/(C$48+E$48+H$48+K$48+N$48+Q$48+T$48+W$48+Z$48+AC$48+AF$48+AI$48+AL$48+AO$48+AR$48))*AR$54,AS4-((AS4/AS$48)*AR$52)+(AS4/AS$48)*AR$53+AU4+((C4+E4+H4+K4+N4+Q4+T4+W4+Z4+AC4+AF4+AI4+AL4+AO4+AR4)/(C$48+E$48+H$48+K$48+N$48+Q$48+T$48+W$48+Z$48+AC$48+AF$48+AI$48+AL$48+AO$48+AR$48))*AR$54) -> 1024519.3 | AW4: =(AV4/AV$48)*AU$53 -> 0 | AX4: =epargne_mensuelle!U4 -> 0 | AY4: =IF(AV$48=0,AV4+AX4+((C4+E4+H4+K4+N4+Q4+T4+W4+Z4+AC4+AF4+AI4+AL4+AO4+AR4+AU4)/(C$48+E$48+H$48+K$48+N$48+Q$48+T$48+W$48+Z$48+AC$48+AF$48+AI$48+AL$48+AO$48+AR$48+AU$48))*AU$54,AV4-((AV4/AV$48)*AU$52)+(AV4/AV$48)*AU$53+AX4+((C4+E4+H4+K4+N4+Q4+T4+W4+Z4+AC4+AF4+AI4+AL4+AO4+AR4+AU4)/(C$48+E$48+H$48+K$48+N$48+Q$48+T$48+W$48+Z$48+AC$48+AF$48+AI$48+AL$48+AO$48+AR$48+AU$48))*AU$54) -> 1024519.3 | AZ4: =(AY4/AY$48)*AX$53 -> 0 | BA4: =epargne_mensuelle!V4 -> 0 | BB4: =IF(AY$48=0,AY4+BA4+((C4+E4+H4+K4+N4+Q4+T4+W4+Z4+AC4+AF4+AI4+AL4+AO4+AR4+AU4+AX4)/(C$48+E$48+H$48+K$48+N$48+Q$48+T$48+W$48+Z$48+AC$48+AF$48+AI$48+AL$48+AO$48+AR$48+AU$48+AX$48))*AX$54,AY4-((AY4/AY$48)*AX$52)+(AY4/AY$48)*AX$53+BA4+((C4+E4+H4+K4+N4+Q4+T4+W4+Z4+AC4+AF4+AI4+AL4+AO4+AR4+AU4+AX4)/(C$48+E$48+H$48+K$48+N$48+Q$48+T$48+W$48+Z$48+AC$48+AF$48+AI$48+AL$48+AO$48+AR$48+AU$48+AX$48))*AX$54) -> 1024519.3 | BC4: =(BB4/BB$48)*BA$53 -> 0 | BD4: =epargne_mensuelle!W4 -> 0 | BE4: =IF(BB$48=0,BB4+BD4+((C4+E4+H4+K4+N4+Q4+T4+W4+Z4+AC4+AF4+AI4+AL4+AO4+AR4+AU4+AX4+BA4)/(C$48+E$48+H$48+K$48+N$48+Q$48+T$48+W$48+Z$48+AC$48+AF$48+AI$48+AL$48+AO$48+AR$48+AU$48+AX$48+BA$48))*BA$54,BB4-((BB4/BB$48)*BA$52)+(BB4/BB$48)*BA$53+BD4+((C4+E4+H4+K4+N4+Q4+T4+W4+Z4+AC4+AF4+AI4+AL4+AO4+AR4+AU4+AX4+BA4)/(C$48+E$48+H$48+K$48+N$48+Q$48+T$48+W$48+Z$48+AC$48+AF$48+AI$48+AL$48+AO$48+AR$48+AU$48+AX$48+BA$48))*BA$54) -> 1024519.3 | BF4: =(BE4/BE$48)*BD$53 -> 0 | BG4: =epargne_mensuelle!X4 -> 0 | BH4: =IF(BE$48=0,BE4+BG4+((C4+E4+H4+K4+N4+Q4+T4+W4+Z4+AC4+AF4+AI4+AL4+AO4+AR4+AU4+AX4+BA4+BD4)/(C$48+E$48+H$48+K$48+N$48+Q$48+T$48+W$48+Z$48+AC$48+AF$48+AI$48+AL$48+AO$48+AR$48+AU$48+AX$48+BA$48+BD$48))*BD$54,BE4-((BE4/BE$48)*BD$52)+(BE4/BE$48)*BD$53+BG4+((C4+E4+H4+K4+N4+Q4+T4+W4+Z4+AC4+AF4+AI4+AL4+AO4+AR4+AU4+AX4+BA4+BD4)/(C$48+E$48+H$48+K$48+N$48+Q$48+T$48+W$48+Z$48+AC$48+AF$48+AI$48+AL$48+AO$48+AR$48+AU$48+AX$48+BA$48+BD$48))*BD$54) -> 1024519.3 | BI4: =(BH4/BH$48)*BG$53 -> 0 | BJ4: =epargne_mensuelle!Y4 -> 0 | BK4: =IF(BH$48=0,BH4+BJ4+((C4+E4+H4+K4+N4+Q4+T4+W4+Z4+AC4+AF4+AI4+AL4+AO4+AR4+AU4+AX4+BA4+BD4+BG4)/(C$48+E$48+H$48+K$48+N$48+Q$48+T$48+W$48+Z$48+AC$48+AF$48+AI$48+AL$48+AO$48+AR$48+AU$48+AX$48+BA$48+BD$48+BG$48))*BG$54,BH4-((BH4/BH$48)*BG$52)+(BH4/BH$48)*BG$53+BJ4+((C4+E4+H4+K4+N4+Q4+T4+W4+Z4+AC4+AF4+AI4+AL4+AO4+AR4+AU4+AX4+BA4+BD4+BG4)/(C$48+E$48+H$48+K$48+N$48+Q$48+T$48+W$48+Z$48+AC$48+AF$48+AI$48+AL$48+AO$48+AR$48+AU$48+AX$48+BA$48+BD$48+BG$48))*BG$54) -> 1024519.3 | BL4: =(BK4/BK$48)*BJ$53 -> 0 | BM4: =epargne_mensuelle!Z4 -> 0 | BN4: =IF(BK$48=0,BK4+BM4+((C4+E4+H4+K4+N4+Q4+T4+W4+Z4+AC4+AF4+AI4+AL4+AO4+AR4+AU4+AX4+BA4+BD4+BG4+BJ4)/(C$48+E$48+H$48+K$48+N$48+Q$48+T$48+W$48+Z$48+AC$48+AF$48+AI$48+AL$48+AO$48+AR$48+AU$48+AX$48+BA$48+BD$48+BG$48+BJ$48))*BJ$54,BK4-((BK4/BK$48)*BJ$52)+(BK4/BK$48)*BJ$53+BM4+((C4+E4+H4+K4+N4+Q4+T4+W4+Z4+AC4+AF4+AI4+AL4+AO4+AR4+AU4+AX4+BA4+BD4+BG4+BJ4)/(C$48+E$48+H$48+K$48+N$48+Q$48+T$48+W$48+Z$48+AC$48+AF$48+AI$48+AL$48+AO$48+AR$48+AU$48+AX$48+BA$48+BD$48+BG$48+BJ$48))*BJ$54) -> 1024519.3 | BO4: =(BN4/BN$48)*BM$53 -> 0 | BP4: =epargne_mensuelle!AA4 -> 0 | BQ4: =IF(BN$48=0,BN4+BP4+((F4+H4+K4+N4+Q4+T4+W4+Z4+AC4+AF4+AI4+AL4+AO4+AR4+AU4+AX4+BA4+BD4+BG4+BJ4+BM4)/(F$48+H$48+K$48+N$48+Q$48+T$48+W$48+Z$48+AC$48+AF$48+AI$48+AL$48+AO$48+AR$48+AU$48+AX$48+BA$48+BD$48+BG$48+BJ$48+BM$48))*BM$54,BN4-((BN4/BN$48)*BM$52)+(BN4/BN$48)*BM$53+BP4+((F4+H4+K4+N4+Q4+T4+W4+Z4+AC4+AF4+AI4+AL4+AO4+AR4+AU4+AX4+BA4+BD4+BG4+BJ4+BM4)/(F$48+H$48+K$48+N$48+Q$48+T$48+W$48+Z$48+AC$48+AF$48+AI$48+AL$48+AO$48+AR$48+AU$48+AX$48+BA$48+BD$48+BG$48+BJ$48+BM$48))*BM$54) -> 1024519.3 | BR4: =(BQ4/BQ$48)*BP$53 -> 0 | BS4: =epargne_mensuelle!AB4 -> 0 | BT4: =IF(BQ$48=0,BQ4+BS4+((I4+K4+N4+Q4+T4+W4+Z4+AC4+AF4+AI4+AL4+AO4+AR4+AU4+AX4+BA4+BD4+BG4+BJ4+BM4+BP4)/(I$48+K$48+N$48+Q$48+T$48+W$48+Z$48+AC$48+AF$48+AI$48+AL$48+AO$48+AR$48+AU$48+AX$48+BA$48+BD$48+BG$48+BJ$48+BM$48+BP$48))*BP$54,BQ4-((BQ4/BQ$48)*BP$52)+(BQ4/BQ$48)*BP$53+BS4+((I4+K4+N4+Q4+T4+W4+Z4+AC4+AF4+AI4+AL4+AO4+AR4+AU4+AX4+BA4+BD4+BG4+BJ4+BM4+BP4)/(I$48+K$48+N$48+Q$48+T$48+W$48+Z$48+AC$48+AF$48+AI$48+AL$48+AO$48+AR$48+AU$48+AX$48+BA$48+BD$48+BG$48+BJ$48+BM$48+BP$48))*BP$54) -> 1024519.3 | BU4: =(BT4/BT$48)*BS$53 -> 0 | BV4: =cumul_epargne!C4 -> 4008079.8 | BW4: =D4+G4+J4+M4+P4+S4+V4+Y4+AB4+AE4+AH4+AK4+AN4+AQ4+AT4+AW4+AZ4+BC4+BF4+BI4+BL4+BO4+BR4+BU4 -> 667719.35 | BX4: =IF(BV4="",BW4,BV4+BW4) -> 4675799.1 | BZ4: =BX4+BY4 -> 4675799.1 | CA4: =IF(BV4="","",BW4/BV4) -> 0.16659333 | CB4: =BZ4/BZ$48 -> 0.10306653 | CC4: =CB4*(C$50-BW$58-BW$57) -> 446154.72 | CD4: =B4 -> ACTIONNIRE3
A5: =epargne_mensuelle!A5 -> 4 | B5: =epargne_mensuelle!B5 -> ACTIONNIRE4 | C5: =SUM(epargne_mensuelle!C5:E5) -> 372369.77 | D5: =(C5/C$48)*C$53 -> 47067.593 | E5: =epargne_mensuelle!F5 -> 0 | F5: =C5-(C5/C$48)*C$52+(C5/C$48)*C$53+E5+(C5/C$48)*C$54 -> 55748.018 | G5: =(F5/F$48)*E$53 -> 0 | H5: =epargne_mensuelle!G5 -> 0 | I5: =IF(F$48=0,F5+H5+((C5+E5)/(C$48+E$48))*E$54,F5-((F5/F$48)*E$52)+(F5/F$48)*E$53+H5+((C5+E5)/(C$48+E$48))*E$54) -> 63515.607 | J5: =(I5/I$48)*H$53 -> 6034.8049 | K5: =epargne_mensuelle!H5 -> 0 | L5: =IF(I$48=0,I5+K5+((C5+E5+H5)/(C$48+E$48+H$48))*H$54,I5-((I5/I$48)*H$52)+(I5/I$48)*H$53+K5+((C5+E5+H5)/(C$48+E$48+H$48))*H$54) -> 54051.492 | M5: =(L5/L$48)*K$53 -> 2091.6244 | N5: =epargne_mensuelle!I5 -> 0 | O5: =IF(L$48=0,L5+N5+((C5+E5+H5+K5)/(C$48+E$48+H$48+K$48))*K$54,L5-((L5/L$48)*K$52)+(L5/L$48)*K$53+N5+((C5+E5+H5+K5)/(C$48+E$48+H$48+K$48))*K$54) -> 47362.631 | P5: =(O5/O$48)*N$53 -> 748.83962 | Q5: =epargne_mensuelle!J5 -> 0 | R5: =IF(O$48=0,O5+Q5+((C5+E5+H5+K5+N5)/(C$48+E$48+H$48+K$48+N$48))*N$54,O5-((O5/O$48)*N$52)+(O5/O$48)*N$53+Q5+((C5+E5+H5+K5+N5)/(C$48+E$48+H$48+K$48+N$48))*N$54) -> 73303.087 | S5: =(R5/R$48)*Q$53 -> 6091.4563 | T5: =epargne_mensuelle!K5 -> 0 | U5: =IF(R$48=0,R5+T5+((C5+E5+H5+K5+N5+Q5)/(C$48+E$48+H$48+K$48+N$48+Q$48))*Q$54,R5-((R5/R$48)*Q$52)+(R5/R$48)*Q$53+T5+((C5+E5+H5+K5+N5+Q5)/(C$48+E$48+H$48+K$48+N$48+Q$48))*Q$54) -> 95182.74 | V5: =(U5/U$48)*T$53 -> 0 | W5: =epargne_mensuelle!L5 -> 0 | X5: =IF(U$48=0,U5+W5+((C5+E5+H5+K5+N5+Q5+T5)/(C$48+E$48+H$48+K$48+N$48+Q$48+T$48))*T$54,U5-((U5/U$48)*T$52)+(U5/U$48)*T$53+W5+((C5+E5+H5+K5+N5+Q5+T5)/(C$48+E$48+H$48+K$48+N$48+Q$48+T$48))*T$54) -> 95182.74 | Y5: =(X5/X$48)*W$53 -> 0 | Z5: =epargne_mensuelle!M5 -> 0 | AA5: =IF(X$48=0,X5+Z5+((C5+E5+H5+K5+N5+Q5+T5+W5)/(C$48+E$48+H$48+K$48+N$48+Q$48+T$48+W$48))*W$54,X5-((X5/X$48)*W$52)+(X5/X$48)*W$53+Z5+((C5+E5+H5+K5+N5+Q5+T5+W5)/(C$48+E$48+H$48+K$48+N$48+Q$48+T$48+W$48))*W$54) -> 95182.74 | AB5: =(AA5/AA$48)*Z$53 -> 0 | AC5: =epargne_mensuelle!N5 -> 0 | AD5: =IF(AA$48=0,AA5+AC5+((C5+E5+H5+K5+N5+Q5+T5+W5+Z5)/(C$48+E$48+H$48+K$48+N$48+Q$48+T$48+W$48+Z$48))*Z$54,AA5-((AA5/AA$48)*Z$52)+(AA5/AA$48)*Z$53+AC5+((C5+E5+H5+K5+N5+Q5+T5+W5+Z5)/(C$48+E$48+H$48+K$48+N$48+Q$48+T$48+W$48+Z$48))*Z$54) -> 95182.74 | AE5: =(AD5/AD$48)*AC$53 -> 0 | AF5: =epargne_mensuelle!O5 -> 0 | AG5: =IF(AD$48=0,AD5+AF5+((C5+E5+H5+K5+N5+Q5+T5+W5+Z5+AC5)/(C$48+E$48+H$48+K$48+N$48+Q$48+T$48+W$48+Z$48+AC$48))*AC$54,AD5-((AD5/AD$48)*AC$52)+(AD5/AD$48)*AC$53+AF5+((C5+E5+H5+K5+N5+Q5+T5+W5+Z5+AC5)/(C$48+E$48+H$48+K$48+N$48+Q$48+T$48+W$48+Z$48+AC$48))*AC$54) -> 95182.74 | AH5: =(AG5/AG$48)*AF$53 -> 0 | AI5: =epargne_mensuelle!P5 -> 0 | AJ5: =IF(AG$48=0,AG5+AI5+((C5+E5+H5+K5+N5+Q5+T5+W5+Z5+AC5+AF5)/(C$48+E$48+H$48+K$48+N$48+Q$48+T$48+W$48+Z$48+AC$48+AF$48))*AF$54,AG5-((AG5/AG$48)*AF$52)+(AG5/AG$48)*AF$53+AI5+((C5+E5+H5+K5+N5+Q5+T5+W5+Z5+AC5+AF5)/(C$48+E$48+H$48+K$48+N$48+Q$48+T$48+W$48+Z$48+AC$48+AF$48))*AF$54) -> 95182.74 | AK5: =(AJ5/AJ$48)*AI$53 -> 0 | AL5: =epargne_mensuelle!Q5 -> 0 | AM5: =IF(AJ$48=0,AJ5+AL5+((C5+E5+H5+K5+N5+Q5+T5+W5+Z5+AC5+AF5+AI5)/(C$48+E$48+H$48+K$48+N$48+Q$48+T$48+W$48+Z$48+AC$48+AF$48+AI$48))*AI$54,AJ5-((AJ5/AJ$48)*AI$52)+(AJ5/AJ$48)*AI$53+AL5+((C5+E5+H5+K5+N5+Q5+T5+W5+Z5+AC5+AF5+AI5)/(C$48+E$48+H$48+K$48+N$48+Q$48+T$48+W$48+Z$48+AC$48+AF$48+AI$48))*AI$54) -> 95182.74 | AN5: =(AM5/AM$48)*AL$53 -> 0 | AO5: =epargne_mensuelle!R5 -> 0 | AP5: =IF(AM$48=0,AM5+AO5+((C5+E5+H5+K5+N5+Q5+T5+W5+Z5+AC5+AF5+AI5+AL5)/(C$48+E$48+H$48+K$48+N$48+Q$48+T$48+W$48+Z$48+AC$48+AF$48+AI$48+AL$48))*AL$54,AM5-((AM5/AM$48)*AL$52)+(AM5/AM$48)*AL$53+AO5+((C5+E5+H5+K5+N5+Q5+T5+W5+Z5+AC5+AF5+AI5+AL5)/(C$48+E$48+H$48+K$48+N$48+Q$48+T$48+W$48+Z$48+AC$48+AF$48+AI$48+AL$48))*AL$54) -> 95182.74 | AQ5: =(AP5/AP$48)*AO$53 -> 0 | AR5: =epargne_mensuelle!S5 -> 0 | AS5: =IF(AP$48=0,AP5+AR5+((C5+E5+H5+K5+N5+Q5+T5+W5+Z5+AC5+AF5+AI5+AL5+AO5)/(C$48+E$48+H$48+K$48+N$48+Q$48+T$48+W$48+Z$48+AC$48+AF$48+AI$48+AL$48+AO$48))*AO$54,AP5-((AP5/AP$48)*AO$52)+(AP5/AP$48)*AO$53+AR5+((C5+E5+H5+K5+N5+Q5+T5+W5+Z5+AC5+AF5+AI5+AL5+AO5)/(C$48+E$48+H$48+K$48+N$48+Q$48+T$48+W$48+Z$48+AC$48+AF$48+AI$48+AL$48+AO$48))*AO$54) -> 95182.74 | AT5: =(AS5/AS$48)*AR$53 -> 0 | AU5: =epargne_mensuelle!T5 -> 0 | AV5: =IF(AS$48=0,AS5+AU5+((C5+E5+H5+K5+N5+Q5+T5+W5+Z5+AC5+AF5+AI5+AL5+AO5+AR5)/(C$48+E$48+H$48+K$48+N$48+Q$48+T$48+W$48+Z$48+AC$48+AF$48+AI$48+AL$48+AO$48+AR$48))*AR$54,AS5-((AS5/AS$48)*AR$52)+(AS5/AS$48)*AR$53+AU5+((C5+E5+H5+K5+N5+Q5+T5+W5+Z5+AC5+AF5+AI5+AL5+AO5+AR5)/(C$48+E$48+H$48+K$48+N$48+Q$48+T$48+W$48+Z$48+AC$48+AF$48+AI$48+AL$48+AO$48+AR$48))*AR$54) -> 95182.74 | AW5: =(AV5/AV$48)*AU$53 -> 0 | AX5: =epargne_mensuelle!U5 -> 0 | AY5: =IF(AV$48=0,AV5+AX5+((C5+E5+H5+K5+N5+Q5+T5+W5+Z5+AC5+AF5+AI5+AL5+AO5+AR5+AU5)/(C$48+E$48+H$48+K$48+N$48+Q$48+T$48+W$48+Z$48+AC$48+AF$48+AI$48+AL$48+AO$48+AR$48+AU$48))*AU$54,AV5-((AV5/AV$48)*AU$52)+(AV5/AV$48)*AU$53+AX5+((C5+E5+H5+K5+N5+Q5+T5+W5+Z5+AC5+AF5+AI5+AL5+AO5+AR5+AU5)/(C$48+E$48+H$48+K$48+N$48+Q$48+T$48+W$48+Z$48+AC$48+AF$48+AI$48+AL$48+AO$48+AR$48+AU$48))*AU$54) -> 95182.74 | AZ5: =(AY5/AY$48)*AX$53 -> 0 | BA5: =epargne_mensuelle!V5 -> 0 | BB5: =IF(AY$48=0,AY5+BA5+((C5+E5+H5+K5+N5+Q5+T5+W5+Z5+AC5+AF5+AI5+AL5+AO5+AR5+AU5+AX5)/(C$48+E$48+H$48+K$48+N$48+Q$48+T$48+W$48+Z$48+AC$48+AF$48+AI$48+AL$48+AO$48+AR$48+AU$48+AX$48))*AX$54,AY5-((AY5/AY$48)*AX$52)+(AY5/AY$48)*AX$53+BA5+((C5+E5+H5+K5+N5+Q5+T5+W5+Z5+AC5+AF5+AI5+AL5+AO5+AR5+AU5+AX5)/(C$48+E$48+H$48+K$48+N$48+Q$48+T$48+W$48+Z$48+AC$48+AF$48+AI$48+AL$48+AO$48+AR$48+AU$48+AX$48))*AX$54) -> 95182.74 | BC5: =(BB5/BB$48)*BA$53 -> 0 | BD5: =epargne_mensuelle!W5 -> 0 | BE5: =IF(BB$48=0,BB5+BD5+((C5+E5+H5+K5+N5+Q5+T5+W5+Z5+AC5+AF5+AI5+AL5+AO5+AR5+AU5+AX5+BA5)/(C$48+E$48+H$48+K$48+N$48+Q$48+T$48+W$48+Z$48+AC$48+AF$48+AI$48+AL$48+AO$48+AR$48+AU$48+AX$48+BA$48))*BA$54,BB5-((BB5/BB$48)*BA$52)+(BB5/BB$48)*BA$53+BD5+((C5+E5+H5+K5+N5+Q5+T5+W5+Z5+AC5+AF5+AI5+AL5+AO5+AR5+AU5+AX5+BA5)/(C$48+E$48+H$48+K$48+N$48+Q$48+T$48+W$48+Z$48+AC$48+AF$48+AI$48+AL$48+AO$48+AR$48+AU$48+AX$48+BA$48))*BA$54) -> 95182.74 | BF5: =(BE5/BE$48)*BD$53 -> 0 | BG5: =epargne_mensuelle!X5 -> 0 | BH5: =IF(BE$48=0,BE5+BG5+((C5+E5+H5+K5+N5+Q5+T5+W5+Z5+AC5+AF5+AI5+AL5+AO5+AR5+AU5+AX5+BA5+BD5)/(C$48+E$48+H$48+K$48+N$48+Q$48+T$48+W$48+Z$48+AC$48+AF$48+AI$48+AL$48+AO$48+AR$48+AU$48+AX$48+BA$48+BD$48))*BD$54,BE5-((BE5/BE$48)*BD$52)+(BE5/BE$48)*BD$53+BG5+((C5+E5+H5+K5+N5+Q5+T5+W5+Z5+AC5+AF5+AI5+AL5+AO5+AR5+AU5+AX5+BA5+BD5)/(C$48+E$48+H$48+K$48+N$48+Q$48+T$48+W$48+Z$48+AC$48+AF$48+AI$48+AL$48+AO$48+AR$48+AU$48+AX$48+BA$48+BD$48))*BD$54) -> 95182.74 | BI5: =(BH5/BH$48)*BG$53 -> 0 | BJ5: =epargne_mensuelle!Y5 -> 0 | BK5: =IF(BH$48=0,BH5+BJ5+((C5+E5+H5+K5+N5+Q5+T5+W5+Z5+AC5+AF5+AI5+AL5+AO5+AR5+AU5+AX5+BA5+BD5+BG5)/(C$48+E$48+H$48+K$48+N$48+Q$48+T$48+W$48+Z$48+AC$48+AF$48+AI$48+AL$48+AO$48+AR$48+AU$48+AX$48+BA$48+BD$48+BG$48))*BG$54,BH5-((BH5/BH$48)*BG$52)+(BH5/BH$48)*BG$53+BJ5+((C5+E5+H5+K5+N5+Q5+T5+W5+Z5+AC5+AF5+AI5+AL5+AO5+AR5+AU5+AX5+BA5+BD5+BG5)/(C$48+E$48+H$48+K$48+N$48+Q$48+T$48+W$48+Z$48+AC$48+AF$48+AI$48+AL$48+AO$48+AR$48+AU$48+AX$48+BA$48+BD$48+BG$48))*BG$54) -> 95182.74 | BL5: =(BK5/BK$48)*BJ$53 -> 0 | BM5: =epargne_mensuelle!Z5 -> 0 | BN5: =IF(BK$48=0,BK5+BM5+((C5+E5+H5+K5+N5+Q5+T5+W5+Z5+AC5+AF5+AI5+AL5+AO5+AR5+AU5+AX5+BA5+BD5+BG5+BJ5)/(C$48+E$48+H$48+K$48+N$48+Q$48+T$48+W$48+Z$48+AC$48+AF$48+AI$48+AL$48+AO$48+AR$48+AU$48+AX$48+BA$48+BD$48+BG$48+BJ$48))*BJ$54,BK5-((BK5/BK$48)*BJ$52)+(BK5/BK$48)*BJ$53+BM5+((C5+E5+H5+K5+N5+Q5+T5+W5+Z5+AC5+AF5+AI5+AL5+AO5+AR5+AU5+AX5+BA5+BD5+BG5+BJ5)/(C$48+E$48+H$48+K$48+N$48+Q$48+T$48+W$48+Z$48+AC$48+AF$48+AI$48+AL$48+AO$48+AR$48+AU$48+AX$48+BA$48+BD$48+BG$48+BJ$48))*BJ$54) -> 95182.74 | BO5: =(BN5/BN$48)*BM$53 -> 0 | BP5: =epargne_mensuelle!AA5 -> 0 | BQ5: =IF(BN$48=0,BN5+BP5+((F5+H5+K5+N5+Q5+T5+W5+Z5+AC5+AF5+AI5+AL5+AO5+AR5+AU5+AX5+BA5+BD5+BG5+BJ5+BM5)/(F$48+H$48+K$48+N$48+Q$48+T$48+W$48+Z$48+AC$48+AF$48+AI$48+AL$48+AO$48+AR$48+AU$48+AX$48+BA$48+BD$48+BG$48+BJ$48+BM$48))*BM$54,BN5-((BN5/BN$48)*BM$52)+(BN5/BN$48)*BM$53+BP5+((F5+H5+K5+N5+Q5+T5+W5+Z5+AC5+AF5+AI5+AL5+AO5+AR5+AU5+AX5+BA5+BD5+BG5+BJ5+BM5)/(F$48+H$48+K$48+N$48+Q$48+T$48+W$48+Z$48+AC$48+AF$48+AI$48+AL$48+AO$48+AR$48+AU$48+AX$48+BA$48+BD$48+BG$48+BJ$48+BM$48))*BM$54) -> 95182.74 | BR5: =(BQ5/BQ$48)*BP$53 -> 0 | BS5: =epargne_mensuelle!AB5 -> 0 | BT5: =IF(BQ$48=0,BQ5+BS5+((I5+K5+N5+Q5+T5+W5+Z5+AC5+AF5+AI5+AL5+AO5+AR5+AU5+AX5+BA5+BD5+BG5+BJ5+BM5+BP5)/(I$48+K$48+N$48+Q$48+T$48+W$48+Z$48+AC$48+AF$48+AI$48+AL$48+AO$48+AR$48+AU$48+AX$48+BA$48+BD$48+BG$48+BJ$48+BM$48+BP$48))*BP$54,BQ5-((BQ5/BQ$48)*BP$52)+(BQ5/BQ$48)*BP$53+BS5+((I5+K5+N5+Q5+T5+W5+Z5+AC5+AF5+AI5+AL5+AO5+AR5+AU5+AX5+BA5+BD5+BG5+BJ5+BM5+BP5)/(I$48+K$48+N$48+Q$48+T$48+W$48+Z$48+AC$48+AF$48+AI$48+AL$48+AO$48+AR$48+AU$48+AX$48+BA$48+BD$48+BG$48+BJ$48+BM$48+BP$48))*BP$54) -> 95182.74 | BU5: =(BT5/BT$48)*BS$53 -> 0 | BV5: =cumul_epargne!C5 -> 372369.77 | BW5: =D5+G5+J5+M5+P5+S5+V5+Y5+AB5+AE5+AH5+AK5+AN5+AQ5+AT5+AW5+AZ5+BC5+BF5+BI5+BL5+BO5+BR5+BU5 -> 62034.319 | BX5: =IF(BV5="",BW5,BV5+BW5) -> 434404.08 | BZ5: =BX5+BY5 -> 434404.08 | CA5: =IF(BV5="","",BW5/BV5) -> 0.16659333 | CB5: =BZ5/BZ$48 -> 0.0095753735 | CC5: =CB5*(C$50-BW$58-BW$57) -> 41449.905 | CD5: =B5 -> ACTIONNIRE4
A6: =epargne_mensuelle!A6 -> 5 | B6: =epargne_mensuelle!B6 -> ACTIONNIRE5 | C6: =SUM(epargne_mensuelle!C6:E6) -> 1393753.8 | D6: =(C6/C$48)*C$53 -> 176170.69 | E6: =epargne_mensuelle!F6 -> 0 | F6: =C6-(C6/C$48)*C$52+(C6/C$48)*C$53+E6+(C6/C$48)*C$54 -> 208660.91 | G6: =(F6/F$48)*E$53 -> 0 | H6: =epargne_mensuelle!G6 -> 0 | I6: =IF(F$48=0,F6+H6+((C6+E6)/(C$48+E$48))*E$54,F6-((F6/F$48)*E$52)+(F6/F$48)*E$53+H6+((C6+E6)/(C$48+E$48))*E$54) -> 237734.45 | J6: =(I6/I$48)*H$53 -> 22587.85 | K6: =epargne_mensuelle!H6 -> 0 | L6: =IF(I$48=0,I6+K6+((C6+E6+H6)/(C$48+E$48+H$48))*H$54,I6-((I6/I$48)*H$52)+(I6/I$48)*H$53+K6+((C6+E6+H6)/(C$48+E$48+H$48))*H$54) -> 202310.93 | M6: =(L6/L$48)*K$53 -> 7828.803 | N6: =epargne_mensuelle!I6 -> 0 | O6: =IF(L$48=0,L6+N6+((C6+E6+H6+K6)/(C$48+E$48+H$48+K$48))*K$54,L6-((L6/L$48)*K$52)+(L6/L$48)*K$53+N6+((C6+E6+H6+K6)/(C$48+E$48+H$48+K$48))*K$54) -> 177274.99 | P6: =(O6/O$48)*N$53 -> 2802.854 | Q6: =epargne_mensuelle!J6 -> 0 | R6: =IF(O$48=0,O6+Q6+((C6+E6+H6+K6+N6)/(C$48+E$48+H$48+K$48+N$48))*N$54,O6-((O6/O$48)*N$52)+(O6/O$48)*N$53+Q6+((C6+E6+H6+K6+N6)/(C$48+E$48+H$48+K$48+N$48))*N$54) -> 274368.3 | S6: =(R6/R$48)*Q$53 -> 22799.892 | T6: =epargne_mensuelle!K6 -> 0 | U6: =IF(R$48=0,R6+T6+((C6+E6+H6+K6+N6+Q6)/(C$48+E$48+H$48+K$48+N$48+Q$48))*Q$54,R6-((R6/R$48)*Q$52)+(R6/R$48)*Q$53+T6+((C6+E6+H6+K6+N6+Q6)/(C$48+E$48+H$48+K$48+N$48+Q$48))*Q$54) -> 356262.3 | V6: =(U6/U$48)*T$53 -> 0 | W6: =epargne_mensuelle!L6 -> 0 | X6: =IF(U$48=0,U6+W6+((C6+E6+H6+K6+N6+Q6+T6)/(C$48+E$48+H$48+K$48+N$48+Q$48+T$48))*T$54,U6-((U6/U$48)*T$52)+(U6/U$48)*T$53+W6+((C6+E6+H6+K6+N6+Q6+T6)/(C$48+E$48+H$48+K$48+N$48+Q$48+T$48))*T$54) -> 356262.3 | Y6: =(X6/X$48)*W$53 -> 0 | Z6: =epargne_mensuelle!M6 -> 0 | AA6: =IF(X$48=0,X6+Z6+((C6+E6+H6+K6+N6+Q6+T6+W6)/(C$48+E$48+H$48+K$48+N$48+Q$48+T$48+W$48))*W$54,X6-((X6/X$48)*W$52)+(X6/X$48)*W$53+Z6+((C6+E6+H6+K6+N6+Q6+T6+W6)/(C$48+E$48+H$48+K$48+N$48+Q$48+T$48+W$48))*W$54) -> 356262.3 | AB6: =(AA6/AA$48)*Z$53 -> 0 | AC6: =epargne_mensuelle!N6 -> 0 | AD6: =IF(AA$48=0,AA6+AC6+((C6+E6+H6+K6+N6+Q6+T6+W6+Z6)/(C$48+E$48+H$48+K$48+N$48+Q$48+T$48+W$48+Z$48))*Z$54,AA6-((AA6/AA$48)*Z$52)+(AA6/AA$48)*Z$53+AC6+((C6+E6+H6+K6+N6+Q6+T6+W6+Z6)/(C$48+E$48+H$48+K$48+N$48+Q$48+T$48+W$48+Z$48))*Z$54) -> 356262.3 | AE6: =(AD6/AD$48)*AC$53 -> 0 | AF6: =epargne_mensuelle!O6 -> 0 | AG6: =IF(AD$48=0,AD6+AF6+((C6+E6+H6+K6+N6+Q6+T6+W6+Z6+AC6)/(C$48+E$48+H$48+K$48+N$48+Q$48+T$48+W$48+Z$48+AC$48))*AC$54,AD6-((AD6/AD$48)*AC$52)+(AD6/AD$48)*AC$53+AF6+((C6+E6+H6+K6+N6+Q6+T6+W6+Z6+AC6)/(C$48+E$48+H$48+K$48+N$48+Q$48+T$48+W$48+Z$48+AC$48))*AC$54) -> 356262.3 | AH6: =(AG6/AG$48)*AF$53 -> 0 | AI6: =epargne_mensuelle!P6 -> 0 | AJ6: =IF(AG$48=0,AG6+AI6+((C6+E6+H6+K6+N6+Q6+T6+W6+Z6+AC6+AF6)/(C$48+E$48+H$48+K$48+N$48+Q$48+T$48+W$48+Z$48+AC$48+AF$48))*AF$54,AG6-((AG6/AG$48)*AF$52)+(AG6/AG$48)*AF$53+AI6+((C6+E6+H6+K6+N6+Q6+T6+W6+Z6+AC6+AF6)/(C$48+E$48+H$48+K$48+N$48+Q$48+T$48+W$48+Z$48+AC$48+AF$48))*AF$54) -> 356262.3 | AK6: =(AJ6/AJ$48)*AI$53 -> 0 | AL6: =epargne_mensuelle!Q6 -> 0 | AM6: =IF(AJ$48=0,AJ6+AL6+((C6+E6+H6+K6+N6+Q6+T6+W6+Z6+AC6+AF6+AI6)/(C$48+E$48+H$48+K$48+N$48+Q$48+T$48+W$48+Z$48+AC$48+AF$48+AI$48))*AI$54,AJ6-((AJ6/AJ$48)*AI$52)+(AJ6/AJ$48)*AI$53+AL6+((C6+E6+H6+K6+N6+Q6+T6+W6+Z6+AC6+AF6+AI6)/(C$48+E$48+H$48+K$48+N$48+Q$48+T$48+W$48+Z$48+AC$48+AF$48+AI$48))*AI$54) -> 356262.3 | AN6: =(AM6/AM$48)*AL$53 -> 0 | AO6: =epargne_mensuelle!R6 -> 0 | AP6: =IF(AM$48=0,AM6+AO6+((C6+E6+H6+K6+N6+Q6+T6+W6+Z6+AC6+AF6+AI6+AL6)/(C$48+E$48+H$48+K$48+N$48+Q$48+T$48+W$48+Z$48+AC$48+AF$48+AI$48+AL$48))*AL$54,AM6-((AM6/AM$48)*AL$52)+(AM6/AM$48)*AL$53+AO6+((C6+E6+H6+K6+N6+Q6+T6+W6+Z6+AC6+AF6+AI6+AL6)/(C$48+E$48+H$48+K$48+N$48+Q$48+T$48+W$48+Z$48+AC$48+AF$48+AI$48+AL$48))*AL$54) -> 356262.3 | AQ6: =(AP6/AP$48)*AO$53 -> 0 | AR6: =epargne_mensuelle!S6 -> 0 | AS6: =IF(AP$48=0,AP6+AR6+((C6+E6+H6+K6+N6+Q6+T6+W6+Z6+AC6+AF6+AI6+AL6+AO6)/(C$48+E$48+H$48+K$48+N$48+Q$48+T$48+W$48+Z$48+AC$48+AF$48+AI$48+AL$48+AO$48))*AO$54,AP6-((AP6/AP$48)*AO$52)+(AP6/AP$48)*AO$53+AR6+((C6+E6+H6+K6+N6+Q6+T6+W6+Z6+AC6+AF6+AI6+AL6+AO6)/(C$48+E$48+H$48+K$48+N$48+Q$48+T$48+W$48+Z$48+AC$48+AF$48+AI$48+AL$48+AO$48))*AO$54) -> 356262.3 | AT6: =(AS6/AS$48)*AR$53 -> 0 | AU6: =epargne_mensuelle!T6 -> 0 | AV6: =IF(AS$48=0,AS6+AU6+((C6+E6+H6+K6+N6+Q6+T6+W6+Z6+AC6+AF6+AI6+AL6+AO6+AR6)/(C$48+E$48+H$48+K$48+N$48+Q$48+T$48+W$48+Z$48+AC$48+AF$48+AI$48+AL$48+AO$48+AR$48))*AR$54,AS6-((AS6/AS$48)*AR$52)+(AS6/AS$48)*AR$53+AU6+((C6+E6+H6+K6+N6+Q6+T6+W6+Z6+AC6+AF6+AI6+AL6+AO6+AR6)/(C$48+E$48+H$48+K$48+N$48+Q$48+T$48+W$48+Z$48+AC$48+AF$48+AI$48+AL$48+AO$48+AR$48))*AR$54) -> 356262.3 | AW6: =(AV6/AV$48)*AU$53 -> 0 | AX6: =epargne_mensuelle!U6 -> 0 | AY6: =IF(AV$48=0,AV6+AX6+((C6+E6+H6+K6+N6+Q6+T6+W6+Z6+AC6+AF6+AI6+AL6+AO6+AR6+AU6)/(C$48+E$48+H$48+K$48+N$48+Q$48+T$48+W$48+Z$48+AC$48+AF$48+AI$48+AL$48+AO$48+AR$48+AU$48))*AU$54,AV6-((AV6/AV$48)*AU$52)+(AV6/AV$48)*AU$53+AX6+((C6+E6+H6+K6+N6+Q6+T6+W6+Z6+AC6+AF6+AI6+AL6+AO6+AR6+AU6)/(C$48+E$48+H$48+K$48+N$48+Q$48+T$48+W$48+Z$48+AC$48+AF$48+AI$48+AL$48+AO$48+AR$48+AU$48))*AU$54) -> 356262.3 | AZ6: =(AY6/AY$48)*AX$53 -> 0 | BA6: =epargne_mensuelle!V6 -> 0 | BB6: =IF(AY$48=0,AY6+BA6+((C6+E6+H6+K6+N6+Q6+T6+W6+Z6+AC6+AF6+AI6+AL6+AO6+AR6+AU6+AX6)/(C$48+E$48+H$48+K$48+N$48+Q$48+T$48+W$48+Z$48+AC$48+AF$48+AI$48+AL$48+AO$48+AR$48+AU$48+AX$48))*AX$54,AY6-((AY6/AY$48)*AX$52)+(AY6/AY$48)*AX$53+BA6+((C6+E6+H6+K6+N6+Q6+T6+W6+Z6+AC6+AF6+AI6+AL6+AO6+AR6+AU6+AX6)/(C$48+E$48+H$48+K$48+N$48+Q$48+T$48+W$48+Z$48+AC$48+AF$48+AI$48+AL$48+AO$48+AR$48+AU$48+AX$48))*AX$54) -> 356262.3 | BC6: =(BB6/BB$48)*BA$53 -> 0 | BD6: =epargne_mensuelle!W6 -> 0 | BE6: =IF(BB$48=0,BB6+BD6+((C6+E6+H6+K6+N6+Q6+T6+W6+Z6+AC6+AF6+AI6+AL6+AO6+AR6+AU6+AX6+BA6)/(C$48+E$48+H$48+K$48+N$48+Q$48+T$48+W$48+Z$48+AC$48+AF$48+AI$48+AL$48+AO$48+AR$48+AU$48+AX$48+BA$48))*BA$54,BB6-((BB6/BB$48)*BA$52)+(BB6/BB$48)*BA$53+BD6+((C6+E6+H6+K6+N6+Q6+T6+W6+Z6+AC6+AF6+AI6+AL6+AO6+AR6+AU6+AX6+BA6)/(C$48+E$48+H$48+K$48+N$48+Q$48+T$48+W$48+Z$48+AC$48+AF$48+AI$48+AL$48+AO$48+AR$48+AU$48+AX$48+BA$48))*BA$54) -> 356262.3 | BF6: =(BE6/BE$48)*BD$53 -> 0 | BG6: =epargne_mensuelle!X6 -> 0 | BH6: =IF(BE$48=0,BE6+BG6+((C6+E6+H6+K6+N6+Q6+T6+W6+Z6+AC6+AF6+AI6+AL6+AO6+AR6+AU6+AX6+BA6+BD6)/(C$48+E$48+H$48+K$48+N$48+Q$48+T$48+W$48+Z$48+AC$48+AF$48+AI$48+AL$48+AO$48+AR$48+AU$48+AX$48+BA$48+BD$48))*BD$54,BE6-((BE6/BE$48)*BD$52)+(BE6/BE$48)*BD$53+BG6+((C6+E6+H6+K6+N6+Q6+T6+W6+Z6+AC6+AF6+AI6+AL6+AO6+AR6+AU6+AX6+BA6+BD6)/(C$48+E$48+H$48+K$48+N$48+Q$48+T$48+W$48+Z$48+AC$48+AF$48+AI$48+AL$48+AO$48+AR$48+AU$48+AX$48+BA$48+BD$48))*BD$54) -> 356262.3 | BI6: =(BH6/BH$48)*BG$53 -> 0 | BJ6: =epargne_mensuelle!Y6 -> 0 | BK6: =IF(BH$48=0,BH6+BJ6+((C6+E6+H6+K6+N6+Q6+T6+W6+Z6+AC6+AF6+AI6+AL6+AO6+AR6+AU6+AX6+BA6+BD6+BG6)/(C$48+E$48+H$48+K$48+N$48+Q$48+T$48+W$48+Z$48+AC$48+AF$48+AI$48+AL$48+AO$48+AR$48+AU$48+AX$48+BA$48+BD$48+BG$48))*BG$54,BH6-((BH6/BH$48)*BG$52)+(BH6/BH$48)*BG$53+BJ6+((C6+E6+H6+K6+N6+Q6+T6+W6+Z6+AC6+AF6+AI6+AL6+AO6+AR6+AU6+AX6+BA6+BD6+BG6)/(C$48+E$48+H$48+K$48+N$48+Q$48+T$48+W$48+Z$48+AC$48+AF$48+AI$48+AL$48+AO$48+AR$48+AU$48+AX$48+BA$48+BD$48+BG$48))*BG$54) -> 356262.3 | BL6: =(BK6/BK$48)*BJ$53 -> 0 | BM6: =epargne_mensuelle!Z6 -> 0 | BN6: =IF(BK$48=0,BK6+BM6+((C6+E6+H6+K6+N6+Q6+T6+W6+Z6+AC6+AF6+AI6+AL6+AO6+AR6+AU6+AX6+BA6+BD6+BG6+BJ6)/(C$48+E$48+H$48+K$48+N$48+Q$48+T$48+W$48+Z$48+AC$48+AF$48+AI$48+AL$48+AO$48+AR$48+AU$48+AX$48+BA$48+BD$48+BG$48+BJ$48))*BJ$54,BK6-((BK6/BK$48)*BJ$52)+(BK6/BK$48)*BJ$53+BM6+((C6+E6+H6+K6+N6+Q6+T6+W6+Z6+AC6+AF6+AI6+AL6+AO6+AR6+AU6+AX6+BA6+BD6+BG6+BJ6)/(C$48+E$48+H$48+K$48+N$48+Q$48+T$48+W$48+Z$48+AC$48+AF$48+AI$48+AL$48+AO$48+AR$48+AU$48+AX$48+BA$48+BD$48+BG$48+BJ$48))*BJ$54) -> 356262.3 | BO6: =(BN6/BN$48)*BM$53 -> 0 | BP6: =epargne_mensuelle!AA6 -> 0 | BQ6: =IF(BN$48=0,BN6+BP6+((F6+H6+K6+N6+Q6+T6+W6+Z6+AC6+AF6+AI6+AL6+AO6+AR6+AU6+AX6+BA6+BD6+BG6+BJ6+BM6)/(F$48+H$48+K$48+N$48+Q$48+T$48+W$48+Z$48+AC$48+AF$48+AI$48+AL$48+AO$48+AR$48+AU$48+AX$48+BA$48+BD$48+BG$48+BJ$48+BM$48))*BM$54,BN6-((BN6/BN$48)*BM$52)+(BN6/BN$48)*BM$53+BP6+((F6+H6+K6+N6+Q6+T6+W6+Z6+AC6+AF6+AI6+AL6+AO6+AR6+AU6+AX6+BA6+BD6+BG6+BJ6+BM6)/(F$48+H$48+K$48+N$48+Q$48+T$48+W$48+Z$48+AC$48+AF$48+AI$48+AL$48+AO$48+AR$48+AU$48+AX$48+BA$48+BD$48+BG$48+BJ$48+BM$48))*BM$54) -> 356262.3 | BR6: =(BQ6/BQ$48)*BP$53 -> 0 | BS6: =epargne_mensuelle!AB6 -> 0 | BT6: =IF(BQ$48=0,BQ6+BS6+((I6+K6+N6+Q6+T6+W6+Z6+AC6+AF6+AI6+AL6+AO6+AR6+AU6+AX6+BA6+BD6+BG6+BJ6+BM6+BP6)/(I$48+K$48+N$48+Q$48+T$48+W$48+Z$48+AC$48+AF$48+AI$48+AL$48+AO$48+AR$48+AU$48+AX$48+BA$48+BD$48+BG$48+BJ$48+BM$48+BP$48))*BP$54,BQ6-((BQ6/BQ$48)*BP$52)+(BQ6/BQ$48)*BP$53+BS6+((I6+K6+N6+Q6+T6+W6+Z6+AC6+AF6+AI6+AL6+AO6+AR6+AU6+AX6+BA6+BD6+BG6+BJ6+BM6+BP6)/(I$48+K$48+N$48+Q$48+T$48+W$48+Z$48+AC$48+AF$48+AI$48+AL$48+AO$48+AR$48+AU$48+AX$48+BA$48+BD$48+BG$48+BJ$48+BM$48+BP$48))*BP$54) -> 356262.3 | BU6: =(BT6/BT$48)*BS$53 -> 0 | BV6: =cumul_epargne!C6 -> 1393753.8 | BW6: =D6+G6+J6+M6+P6+S6+V6+Y6+AB6+AE6+AH6+AK6+AN6+AQ6+AT6+AW6+AZ6+BC6+BF6+BI6+BL6+BO6+BR6+BU6 -> 232190.09 | BX6: =IF(BV6="",BW6,BV6+BW6) -> 1625943.9 | BZ6: =BX6+BY6 -> 1625943.9 | CA6: =IF(BV6="","",BW6/BV6) -> 0.16659333 | CB6: =BZ6/BZ$48 -> 0.035839949 | CC6: =CB6*(C$50-BW$58-BW$57) -> 155144.08 | CD6: =B6 -> ACTIONNIRE5
A7: =epargne_mensuelle!A7 -> 6 | B7: =epargne_mensuelle!B7 -> ACTIONNIRE6 | C7: =SUM(epargne_mensuelle!C7:E7) -> 829601.83 | D7: =(C7/C$48)*C$53 -> 104861.79 | E7: =epargne_mensuelle!F7 -> 0 | F7: =C7-(C7/C$48)*C$52+(C7/C$48)*C$53+E7+(C7/C$48)*C$54 -> 124200.89 | G7: =(F7/F$48)*E$53 -> 0 | H7: =epargne_mensuelle!G7 -> 0 | I7: =IF(F$48=0,F7+H7+((C7+E7)/(C$48+E$48))*E$54,F7-((F7/F$48)*E$52)+(F7/F$48)*E$53+H7+((C7+E7)/(C$48+E$48))*E$54) -> 141506.29 | J7: =(I7/I$48)*H$53 -> 13444.929 | K7: =epargne_mensuelle!H7 -> 0 | L7: =IF(I$48=0,I7+K7+((C7+E7+H7)/(C$48+E$48+H$48))*H$54,I7-((I7/I$48)*H$52)+(I7/I$48)*H$53+K7+((C7+E7+H7)/(C$48+E$48+H$48))*H$54) -> 120421.21 | M7: =(L7/L$48)*K$53 -> 4659.9257 | N7: =epargne_mensuelle!I7 -> 0 | O7: =IF(L$48=0,L7+N7+((C7+E7+H7+K7)/(C$48+E$48+H$48+K$48))*K$54,L7-((L7/L$48)*K$52)+(L7/L$48)*K$53+N7+((C7+E7+H7+K7)/(C$48+E$48+H$48+K$48))*K$54) -> 105519.11 | P7: =(O7/O$48)*N$53 -> 1668.3383 | Q7: =epargne_mensuelle!J7 -> 0 | R7: =IF(O$48=0,O7+Q7+((C7+E7+H7+K7+N7)/(C$48+E$48+H$48+K$48+N$48))*N$54,O7-((O7/O$48)*N$52)+(O7/O$48)*N$53+Q7+((C7+E7+H7+K7+N7)/(C$48+E$48+H$48+K$48+N$48))*N$54) -> 163311.8 | S7: =(R7/R$48)*Q$53 -> 13571.143 | T7: =epargne_mensuelle!K7 -> 0 | U7: =IF(R$48=0,R7+T7+((C7+E7+H7+K7+N7+Q7)/(C$48+E$48+H$48+K$48+N$48+Q$48))*Q$54,R7-((R7/R$48)*Q$52)+(R7/R$48)*Q$53+T7+((C7+E7+H7+K7+N7+Q7)/(C$48+E$48+H$48+K$48+N$48+Q$48))*Q$54) -> 212057.43 | V7: =(U7/U$48)*T$53 -> 0 | W7: =epargne_mensuelle!L7 -> 0 | X7: =IF(U$48=0,U7+W7+((C7+E7+H7+K7+N7+Q7+T7)/(C$48+E$48+H$48+K$48+N$48+Q$48+T$48))*T$54,U7-((U7/U$48)*T$52)+(U7/U$48)*T$53+W7+((C7+E7+H7+K7+N7+Q7+T7)/(C$48+E$48+H$48+K$48+N$48+Q$48+T$48))*T$54) -> 212057.43 | Y7: =(X7/X$48)*W$53 -> 0 | Z7: =epargne_mensuelle!M7 -> 0 | AA7: =IF(X$48=0,X7+Z7+((C7+E7+H7+K7+N7+Q7+T7+W7)/(C$48+E$48+H$48+K$48+N$48+Q$48+T$48+W$48))*W$54,X7-((X7/X$48)*W$52)+(X7/X$48)*W$53+Z7+((C7+E7+H7+K7+N7+Q7+T7+W7)/(C$48+E$48+H$48+K$48+N$48+Q$48+T$48+W$48))*W$54) -> 212057.43 | AB7: =(AA7/AA$48)*Z$53 -> 0 | AC7: =epargne_mensuelle!N7 -> 0 | AD7: =IF(AA$48=0,AA7+AC7+((C7+E7+H7+K7+N7+Q7+T7+W7+Z7)/(C$48+E$48+H$48+K$48+N$48+Q$48+T$48+W$48+Z$48))*Z$54,AA7-((AA7/AA$48)*Z$52)+(AA7/AA$48)*Z$53+AC7+((C7+E7+H7+K7+N7+Q7+T7+W7+Z7)/(C$48+E$48+H$48+K$48+N$48+Q$48+T$48+W$48+Z$48))*Z$54) -> 212057.43 | AE7: =(AD7/AD$48)*AC$53 -> 0 | AF7: =epargne_mensuelle!O7 -> 0 | AG7: =IF(AD$48=0,AD7+AF7+((C7+E7+H7+K7+N7+Q7+T7+W7+Z7+AC7)/(C$48+E$48+H$48+K$48+N$48+Q$48+T$48+W$48+Z$48+AC$48))*AC$54,AD7-((AD7/AD$48)*AC$52)+(AD7/AD$48)*AC$53+AF7+((C7+E7+H7+K7+N7+Q7+T7+W7+Z7+AC7)/(C$48+E$48+H$48+K$48+N$48+Q$48+T$48+W$48+Z$48+AC$48))*AC$54) -> 212057.43 | AH7: =(AG7/AG$48)*AF$53 -> 0 | AI7: =epargne_mensuelle!P7 -> 0 | AJ7: =IF(AG$48=0,AG7+AI7+((C7+E7+H7+K7+N7+Q7+T7+W7+Z7+AC7+AF7)/(C$48+E$48+H$48+K$48+N$48+Q$48+T$48+W$48+Z$48+AC$48+AF$48))*AF$54,AG7-((AG7/AG$48)*AF$52)+(AG7/AG$48)*AF$53+AI7+((C7+E7+H7+K7+N7+Q7+T7+W7+Z7+AC7+AF7)/(C$48+E$48+H$48+K$48+N$48+Q$48+T$48+W$48+Z$48+AC$48+AF$48))*AF$54) -> 212057.43 | AK7: =(AJ7/AJ$48)*AI$53 -> 0 | AL7: =epargne_mensuelle!Q7 -> 0 | AM7: =IF(AJ$48=0,AJ7+AL7+((C7+E7+H7+K7+N7+Q7+T7+W7+Z7+AC7+AF7+AI7)/(C$48+E$48+H$48+K$48+N$48+Q$48+T$48+W$48+Z$48+AC$48+AF$48+AI$48))*AI$54,AJ7-((AJ7/AJ$48)*AI$52)+(AJ7/AJ$48)*AI$53+AL7+((C7+E7+H7+K7+N7+Q7+T7+W7+Z7+AC7+AF7+AI7)/(C$48+E$48+H$48+K$48+N$48+Q$48+T$48+W$48+Z$48+AC$48+AF$48+AI$48))*AI$54) -> 212057.43 | AN7: =(AM7/AM$48)*AL$53 -> 0 | AO7: =epargne_mensuelle!R7 -> 0 | AP7: =IF(AM$48=0,AM7+AO7+((C7+E7+H7+K7+N7+Q7+T7+W7+Z7+AC7+AF7+AI7+AL7)/(C$48+E$48+H$48+K$48+N$48+Q$48+T$48+W$48+Z$48+AC$48+AF$48+AI$48+AL$48))*AL$54,AM7-((AM7/AM$48)*AL$52)+(AM7/AM$48)*AL$53+AO7+((C7+E7+H7+K7+N7+Q7+T7+W7+Z7+AC7+AF7+AI7+AL7)/(C$48+E$48+H$48+K$48+N$48+Q$48+T$48+W$48+Z$48+AC$48+AF$48+AI$48+AL$48))*AL$54) -> 212057.43 | AQ7: =(AP7/AP$48)*AO$53 -> 0 | AR7: =epargne_mensuelle!S7 -> 0 | AS7: =IF(AP$48=0,AP7+AR7+((C7+E7+H7+K7+N7+Q7+T7+W7+Z7+AC7+AF7+AI7+AL7+AO7)/(C$48+E$48+H$48+K$48+N$48+Q$48+T$48+W$48+Z$48+AC$48+AF$48+AI$48+AL$48+AO$48))*AO$54,AP7-((AP7/AP$48)*AO$52)+(AP7/AP$48)*AO$53+AR7+((C7+E7+H7+K7+N7+Q7+T7+W7+Z7+AC7+AF7+AI7+AL7+AO7)/(C$48+E$48+H$48+K$48+N$48+Q$48+T$48+W$48+Z$48+AC$48+AF$48+AI$48+AL$48+AO$48))*AO$54) -> 212057.43 | AT7: =(AS7/AS$48)*AR$53 -> 0 | AU7: =epargne_mensuelle!T7 -> 0 | AV7: =IF(AS$48=0,AS7+AU7+((C7+E7+H7+K7+N7+Q7+T7+W7+Z7+AC7+AF7+AI7+AL7+AO7+AR7)/(C$48+E$48+H$48+K$48+N$48+Q$48+T$48+W$48+Z$48+AC$48+AF$48+AI$48+AL$48+AO$48+AR$48))*AR$54,AS7-((AS7/AS$48)*AR$52)+(AS7/AS$48)*AR$53+AU7+((C7+E7+H7+K7+N7+Q7+T7+W7+Z7+AC7+AF7+AI7+AL7+AO7+AR7)/(C$48+E$48+H$48+K$48+N$48+Q$48+T$48+W$48+Z$48+AC$48+AF$48+AI$48+AL$48+AO$48+AR$48))*AR$54) -> 212057.43 | AW7: =(AV7/AV$48)*AU$53 -> 0 | AX7: =epargne_mensuelle!U7 -> 0 | AY7: =IF(AV$48=0,AV7+AX7+((C7+E7+H7+K7+N7+Q7+T7+W7+Z7+AC7+AF7+AI7+AL7+AO7+AR7+AU7)/(C$48+E$48+H$48+K$48+N$48+Q$48+T$48+W$48+Z$48+AC$48+AF$48+AI$48+AL$48+AO$48+AR$48+AU$48))*AU$54,AV7-((AV7/AV$48)*AU$52)+(AV7/AV$48)*AU$53+AX7+((C7+E7+H7+K7+N7+Q7+T7+W7+Z7+AC7+AF7+AI7+AL7+AO7+AR7+AU7)/(C$48+E$48+H$48+K$48+N$48+Q$48+T$48+W$48+Z$48+AC$48+AF$48+AI$48+AL$48+AO$48+AR$48+AU$48))*AU$54) -> 212057.43 | AZ7: =(AY7/AY$48)*AX$53 -> 0 | BA7: =epargne_mensuelle!V7 -> 0 | BB7: =IF(AY$48=0,AY7+BA7+((C7+E7+H7+K7+N7+Q7+T7+W7+Z7+AC7+AF7+AI7+AL7+AO7+AR7+AU7+AX7)/(C$48+E$48+H$48+K$48+N$48+Q$48+T$48+W$48+Z$48+AC$48+AF$48+AI$48+AL$48+AO$48+AR$48+AU$48+AX$48))*AX$54,AY7-((AY7/AY$48)*AX$52)+(AY7/AY$48)*AX$53+BA7+((C7+E7+H7+K7+N7+Q7+T7+W7+Z7+AC7+AF7+AI7+AL7+AO7+AR7+AU7+AX7)/(C$48+E$48+H$48+K$48+N$48+Q$48+T$48+W$48+Z$48+AC$48+AF$48+AI$48+AL$48+AO$48+AR$48+AU$48+AX$48))*AX$54) -> 212057.43 | BC7: =(BB7/BB$48)*BA$53 -> 0 | BD7: =epargne_mensuelle!W7 -> 0 | BE7: =IF(BB$48=0,BB7+BD7+((C7+E7+H7+K7+N7+Q7+T7+W7+Z7+AC7+AF7+AI7+AL7+AO7+AR7+AU7+AX7+BA7)/(C$48+E$48+H$48+K$48+N$48+Q$48+T$48+W$48+Z$48+AC$48+AF$48+AI$48+AL$48+AO$48+AR$48+AU$48+AX$48+BA$48))*BA$54,BB7-((BB7/BB$48)*BA$52)+(BB7/BB$48)*BA$53+BD7+((C7+E7+H7+K7+N7+Q7+T7+W7+Z7+AC7+AF7+AI7+AL7+AO7+AR7+AU7+AX7+BA7)/(C$48+E$48+H$48+K$48+N$48+Q$48+T$48+W$48+Z$48+AC$48+AF$48+AI$48+AL$48+AO$48+AR$48+AU$48+AX$48+BA$48))*BA$54) -> 212057.43 | BF7: =(BE7/BE$48)*BD$53 -> 0 | BG7: =epargne_mensuelle!X7 -> 0 | BH7: =IF(BE$48=0,BE7+BG7+((C7+E7+H7+K7+N7+Q7+T7+W7+Z7+AC7+AF7+AI7+AL7+AO7+AR7+AU7+AX7+BA7+BD7)/(C$48+E$48+H$48+K$48+N$48+Q$48+T$48+W$48+Z$48+AC$48+AF$48+AI$48+AL$48+AO$48+AR$48+AU$48+AX$48+BA$48+BD$48))*BD$54,BE7-((BE7/BE$48)*BD$52)+(BE7/BE$48)*BD$53+BG7+((C7+E7+H7+K7+N7+Q7+T7+W7+Z7+AC7+AF7+AI7+AL7+AO7+AR7+AU7+AX7+BA7+BD7)/(C$48+E$48+H$48+K$48+N$48+Q$48+T$48+W$48+Z$48+AC$48+AF$48+AI$48+AL$48+AO$48+AR$48+AU$48+AX$48+BA$48+BD$48))*BD$54) -> 212057.43 | BI7: =(BH7/BH$48)*BG$53 -> 0 | BJ7: =epargne_mensuelle!Y7 -> 0 | BK7: =IF(BH$48=0,BH7+BJ7+((C7+E7+H7+K7+N7+Q7+T7+W7+Z7+AC7+AF7+AI7+AL7+AO7+AR7+AU7+AX7+BA7+BD7+BG7)/(C$48+E$48+H$48+K$48+N$48+Q$48+T$48+W$48+Z$48+AC$48+AF$48+AI$48+AL$48+AO$48+AR$48+AU$48+AX$48+BA$48+BD$48+BG$48))*BG$54,BH7-((BH7/BH$48)*BG$52)+(BH7/BH$48)*BG$53+BJ7+((C7+E7+H7+K7+N7+Q7+T7+W7+Z7+AC7+AF7+AI7+AL7+AO7+AR7+AU7+AX7+BA7+BD7+BG7)/(C$48+E$48+H$48+K$48+N$48+Q$48+T$48+W$48+Z$48+AC$48+AF$48+AI$48+AL$48+AO$48+AR$48+AU$48+AX$48+BA$48+BD$48+BG$48))*BG$54) -> 212057.43 | BL7: =(BK7/BK$48)*BJ$53 -> 0 | BM7: =epargne_mensuelle!Z7 -> 0 | BN7: =IF(BK$48=0,BK7+BM7+((C7+E7+H7+K7+N7+Q7+T7+W7+Z7+AC7+AF7+AI7+AL7+AO7+AR7+AU7+AX7+BA7+BD7+BG7+BJ7)/(C$48+E$48+H$48+K$48+N$48+Q$48+T$48+W$48+Z$48+AC$48+AF$48+AI$48+AL$48+AO$48+AR$48+AU$48+AX$48+BA$48+BD$48+BG$48+BJ$48))*BJ$54,BK7-((BK7/BK$48)*BJ$52)+(BK7/BK$48)*BJ$53+BM7+((C7+E7+H7+K7+N7+Q7+T7+W7+Z7+AC7+AF7+AI7+AL7+AO7+AR7+AU7+AX7+BA7+BD7+BG7+BJ7)/(C$48+E$48+H$48+K$48+N$48+Q$48+T$48+W$48+Z$48+AC$48+AF$48+AI$48+AL$48+AO$48+AR$48+AU$48+AX$48+BA$48+BD$48+BG$48+BJ$48))*BJ$54) -> 212057.43 | BO7: =(BN7/BN$48)*BM$53 -> 0 | BP7: =epargne_mensuelle!AA7 -> 0 | BQ7: =IF(BN$48=0,BN7+BP7+((F7+H7+K7+N7+Q7+T7+W7+Z7+AC7+AF7+AI7+AL7+AO7+AR7+AU7+AX7+BA7+BD7+BG7+BJ7+BM7)/(F$48+H$48+K$48+N$48+Q$48+T$48+W$48+Z$48+AC$48+AF$48+AI$48+AL$48+AO$48+AR$48+AU$48+AX$48+BA$48+BD$48+BG$48+BJ$48+BM$48))*BM$54,BN7-((BN7/BN$48)*BM$52)+(BN7/BN$48)*BM$53+BP7+((F7+H7+K7+N7+Q7+T7+W7+Z7+AC7+AF7+AI7+AL7+AO7+AR7+AU7+AX7+BA7+BD7+BG7+BJ7+BM7)/(F$48+H$48+K$48+N$48+Q$48+T$48+W$48+Z$48+AC$48+AF$48+AI$48+AL$48+AO$48+AR$48+AU$48+AX$48+BA$48+BD$48+BG$48+BJ$48+BM$48))*BM$54) -> 212057.43 | BR7: =(BQ7/BQ$48)*BP$53 -> 0 | BS7: =epargne_mensuelle!AB7 -> 0 | BT7: =IF(BQ$48=0,BQ7+BS7+((I7+K7+N7+Q7+T7+W7+Z7+AC7+AF7+AI7+AL7+AO7+AR7+AU7+AX7+BA7+BD7+BG7+BJ7+BM7+BP7)/(I$48+K$48+N$48+Q$48+T$48+W$48+Z$48+AC$48+AF$48+AI$48+AL$48+AO$48+AR$48+AU$48+AX$48+BA$48+BD$48+BG$48+BJ$48+BM$48+BP$48))*BP$54,BQ7-((BQ7/BQ$48)*BP$52)+(BQ7/BQ$48)*BP$53+BS7+((I7+K7+N7+Q7+T7+W7+Z7+AC7+AF7+AI7+AL7+AO7+AR7+AU7+AX7+BA7+BD7+BG7+BJ7+BM7+BP7)/(I$48+K$48+N$48+Q$48+T$48+W$48+Z$48+AC$48+AF$48+AI$48+AL$48+AO$48+AR$48+AU$48+AX$48+BA$48+BD$48+BG$48+BJ$48+BM$48+BP$48))*BP$54) -> 212057.43 | BU7: =(BT7/BT$48)*BS$53 -> 0 | BV7: =cumul_epargne!C7 -> 829601.83 | BW7: =D7+G7+J7+M7+P7+S7+V7+Y7+AB7+AE7+AH7+AK7+AN7+AQ7+AT7+AW7+AZ7+BC7+BF7+BI7+BL7+BO7+BR7+BU7 -> 138206.13 | BX7: =IF(BV7="",BW7,BV7+BW7) -> 967807.96 | BZ7: =BX7+BY7 -> 967807.96 | CA7: =IF(BV7="","",BW7/BV7) -> 0.16659333 | CB7: =BZ7/BZ$48 -> 0.021332955 | CC7: =CB7*(C$50-BW$58-BW$57) -> 92346.159 | CD7: =B7 -> ACTIONNIRE6
A8: =epargne_mensuelle!A8 -> 7 | B8: =epargne_mensuelle!B8 -> ACTIONNIRE7 | C8: =SUM(epargne_mensuelle!C8:E8) -> 840018.32 | D8: =(C8/C$48)*C$53 -> 106178.44 | E8: =epargne_mensuelle!F8 -> 0 | F8: =C8-(C8/C$48)*C$52+(C8/C$48)*C$53+E8+(C8/C$48)*C$54 -> 125760.36 | G8: =(F8/F$48)*E$53 -> 0 | H8: =epargne_mensuelle!G8 -> 0 | I8: =IF(F$48=0,F8+H8+((C8+E8)/(C$48+E$48))*E$54,F8-((F8/F$48)*E$52)+(F8/F$48)*E$53+H8+((C8+E8)/(C$48+E$48))*E$54) -> 143283.04 | J8: =(I8/I$48)*H$53 -> 13613.744 | K8: =epargne_mensuelle!H8 -> 0 | L8: =IF(I$48=0,I8+K8+((C8+E8+H8)/(C$48+E$48+H$48))*H$54,I8-((I8/I$48)*H$52)+(I8/I$48)*H$53+K8+((C8+E8+H8)/(C$48+E$48+H$48))*H$54) -> 121933.22 | M8: =(L8/L$48)*K$53 -> 4718.4358 | N8: =epargne_mensuelle!I8 -> 0 | O8: =IF(L$48=0,L8+N8+((C8+E8+H8+K8)/(C$48+E$48+H$48+K$48))*K$54,L8-((L8/L$48)*K$52)+(L8/L$48)*K$53+N8+((C8+E8+H8+K8)/(C$48+E$48+H$48+K$48))*K$54) -> 106844.01 | P8: =(O8/O$48)*N$53 -> 1689.2859 | Q8: =epargne_mensuelle!J8 -> 0 | R8: =IF(O$48=0,O8+Q8+((C8+E8+H8+K8+N8)/(C$48+E$48+H$48+K$48+N$48))*N$54,O8-((O8/O$48)*N$52)+(O8/O$48)*N$53+Q8+((C8+E8+H8+K8+N8)/(C$48+E$48+H$48+K$48+N$48))*N$54) -> 165362.34 | S8: =(R8/R$48)*Q$53 -> 13741.542 | T8: =epargne_mensuelle!K8 -> 0 | U8: =IF(R$48=0,R8+T8+((C8+E8+H8+K8+N8+Q8)/(C$48+E$48+H$48+K$48+N$48+Q$48))*Q$54,R8-((R8/R$48)*Q$52)+(R8/R$48)*Q$53+T8+((C8+E8+H8+K8+N8+Q8)/(C$48+E$48+H$48+K$48+N$48+Q$48))*Q$54) -> 214720.03 | V8: =(U8/U$48)*T$53 -> 0 | W8: =epargne_mensuelle!L8 -> 0 | X8: =IF(U$48=0,U8+W8+((C8+E8+H8+K8+N8+Q8+T8)/(C$48+E$48+H$48+K$48+N$48+Q$48+T$48))*T$54,U8-((U8/U$48)*T$52)+(U8/U$48)*T$53+W8+((C8+E8+H8+K8+N8+Q8+T8)/(C$48+E$48+H$48+K$48+N$48+Q$48+T$48))*T$54) -> 214720.03 | Y8: =(X8/X$48)*W$53 -> 0 | Z8: =epargne_mensuelle!M8 -> 0 | AA8: =IF(X$48=0,X8+Z8+((C8+E8+H8+K8+N8+Q8+T8+W8)/(C$48+E$48+H$48+K$48+N$48+Q$48+T$48+W$48))*W$54,X8-((X8/X$48)*W$52)+(X8/X$48)*W$53+Z8+((C8+E8+H8+K8+N8+Q8+T8+W8)/(C$48+E$48+H$48+K$48+N$48+Q$48+T$48+W$48))*W$54) -> 214720.03 | AB8: =(AA8/AA$48)*Z$53 -> 0 | AC8: =epargne_mensuelle!N8 -> 0 | AD8: =IF(AA$48=0,AA8+AC8+((C8+E8+H8+K8+N8+Q8+T8+W8+Z8)/(C$48+E$48+H$48+K$48+N$48+Q$48+T$48+W$48+Z$48))*Z$54,AA8-((AA8/AA$48)*Z$52)+(AA8/AA$48)*Z$53+AC8+((C8+E8+H8+K8+N8+Q8+T8+W8+Z8)/(C$48+E$48+H$48+K$48+N$48+Q$48+T$48+W$48+Z$48))*Z$54) -> 214720.03 | AE8: =(AD8/AD$48)*AC$53 -> 0 | AF8: =epargne_mensuelle!O8 -> 0 | AG8: =IF(AD$48=0,AD8+AF8+((C8+E8+H8+K8+N8+Q8+T8+W8+Z8+AC8)/(C$48+E$48+H$48+K$48+N$48+Q$48+T$48+W$48+Z$48+AC$48))*AC$54,AD8-((AD8/AD$48)*AC$52)+(AD8/AD$48)*AC$53+AF8+((C8+E8+H8+K8+N8+Q8+T8+W8+Z8+AC8)/(C$48+E$48+H$48+K$48+N$48+Q$48+T$48+W$48+Z$48+AC$48))*AC$54) -> 214720.03 | AH8: =(AG8/AG$48)*AF$53 -> 0 | AI8: =epargne_mensuelle!P8 -> 0 | AJ8: =IF(AG$48=0,AG8+AI8+((C8+E8+H8+K8+N8+Q8+T8+W8+Z8+AC8+AF8)/(C$48+E$48+H$48+K$48+N$48+Q$48+T$48+W$48+Z$48+AC$48+AF$48))*AF$54,AG8-((AG8/AG$48)*AF$52)+(AG8/AG$48)*AF$53+AI8+((C8+E8+H8+K8+N8+Q8+T8+W8+Z8+AC8+AF8)/(C$48+E$48+H$48+K$48+N$48+Q$48+T$48+W$48+Z$48+AC$48+AF$48))*AF$54) -> 214720.03 | AK8: =(AJ8/AJ$48)*AI$53 -> 0 | AL8: =epargne_mensuelle!Q8 -> 0 | AM8: =IF(AJ$48=0,AJ8+AL8+((C8+E8+H8+K8+N8+Q8+T8+W8+Z8+AC8+AF8+AI8)/(C$48+E$48+H$48+K$48+N$48+Q$48+T$48+W$48+Z$48+AC$48+AF$48+AI$48))*AI$54,AJ8-((AJ8/AJ$48)*AI$52)+(AJ8/AJ$48)*AI$53+AL8+((C8+E8+H8+K8+N8+Q8+T8+W8+Z8+AC8+AF8+AI8)/(C$48+E$48+H$48+K$48+N$48+Q$48+T$48+W$48+Z$48+AC$48+AF$48+AI$48))*AI$54) -> 214720.03 | AN8: =(AM8/AM$48)*AL$53 -> 0 | AO8: =epargne_mensuelle!R8 -> 0 | AP8: =IF(AM$48=0,AM8+AO8+((C8+E8+H8+K8+N8+Q8+T8+W8+Z8+AC8+AF8+AI8+AL8)/(C$48+E$48+H$48+K$48+N$48+Q$48+T$48+W$48+Z$48+AC$48+AF$48+AI$48+AL$48))*AL$54,AM8-((AM8/AM$48)*AL$52)+(AM8/AM$48)*AL$53+AO8+((C8+E8+H8+K8+N8+Q8+T8+W8+Z8+AC8+AF8+AI8+AL8)/(C$48+E$48+H$48+K$48+N$48+Q$48+T$48+W$48+Z$48+AC$48+AF$48+AI$48+AL$48))*AL$54) -> 214720.03 | AQ8: =(AP8/AP$48)*AO$53 -> 0 | AR8: =epargne_mensuelle!S8 -> 0 | AS8: =IF(AP$48=0,AP8+AR8+((C8+E8+H8+K8+N8+Q8+T8+W8+Z8+AC8+AF8+AI8+AL8+AO8)/(C$48+E$48+H$48+K$48+N$48+Q$48+T$48+W$48+Z$48+AC$48+AF$48+AI$48+AL$48+AO$48))*AO$54,AP8-((AP8/AP$48)*AO$52)+(AP8/AP$48)*AO$53+AR8+((C8+E8+H8+K8+N8+Q8+T8+W8+Z8+AC8+AF8+AI8+AL8+AO8)/(C$48+E$48+H$48+K$48+N$48+Q$48+T$48+W$48+Z$48+AC$48+AF$48+AI$48+AL$48+AO$48))*AO$54) -> 214720.03 | AT8: =(AS8/AS$48)*AR$53 -> 0 | AU8: =epargne_mensuelle!T8 -> 0 | AV8: =IF(AS$48=0,AS8+AU8+((C8+E8+H8+K8+N8+Q8+T8+W8+Z8+AC8+AF8+AI8+AL8+AO8+AR8)/(C$48+E$48+H$48+K$48+N$48+Q$48+T$48+W$48+Z$48+AC$48+AF$48+AI$48+AL$48+AO$48+AR$48))*AR$54,AS8-((AS8/AS$48)*AR$52)+(AS8/AS$48)*AR$53+AU8+((C8+E8+H8+K8+N8+Q8+T8+W8+Z8+AC8+AF8+AI8+AL8+AO8+AR8)/(C$48+E$48+H$48+K$48+N$48+Q$48+T$48+W$48+Z$48+AC$48+AF$48+AI$48+AL$48+AO$48+AR$48))*AR$54) -> 214720.03 | AW8: =(AV8/AV$48)*AU$53 -> 0 | AX8: =epargne_mensuelle!U8 -> 0 | AY8: =IF(AV$48=0,AV8+AX8+((C8+E8+H8+K8+N8+Q8+T8+W8+Z8+AC8+AF8+AI8+AL8+AO8+AR8+AU8)/(C$48+E$48+H$48+K$48+N$48+Q$48+T$48+W$48+Z$48+AC$48+AF$48+AI$48+AL$48+AO$48+AR$48+AU$48))*AU$54,AV8-((AV8/AV$48)*AU$52)+(AV8/AV$48)*AU$53+AX8+((C8+E8+H8+K8+N8+Q8+T8+W8+Z8+AC8+AF8+AI8+AL8+AO8+AR8+AU8)/(C$48+E$48+H$48+K$48+N$48+Q$48+T$48+W$48+Z$48+AC$48+AF$48+AI$48+AL$48+AO$48+AR$48+AU$48))*AU$54) -> 214720.03 | AZ8: =(AY8/AY$48)*AX$53 -> 0 | BA8: =epargne_mensuelle!V8 -> 0 | BB8: =IF(AY$48=0,AY8+BA8+((C8+E8+H8+K8+N8+Q8+T8+W8+Z8+AC8+AF8+AI8+AL8+AO8+AR8+AU8+AX8)/(C$48+E$48+H$48+K$48+N$48+Q$48+T$48+W$48+Z$48+AC$48+AF$48+AI$48+AL$48+AO$48+AR$48+AU$48+AX$48))*AX$54,AY8-((AY8/AY$48)*AX$52)+(AY8/AY$48)*AX$53+BA8+((C8+E8+H8+K8+N8+Q8+T8+W8+Z8+AC8+AF8+AI8+AL8+AO8+AR8+AU8+AX8)/(C$48+E$48+H$48+K$48+N$48+Q$48+T$48+W$48+Z$48+AC$48+AF$48+AI$48+AL$48+AO$48+AR$48+AU$48+AX$48))*AX$54) -> 214720.03 | BC8: =(BB8/BB$48)*BA$53 -> 0 | BD8: =epargne_mensuelle!W8 -> 0 | BE8: =IF(BB$48=0,BB8+BD8+((C8+E8+H8+K8+N8+Q8+T8+W8+Z8+AC8+AF8+AI8+AL8+AO8+AR8+AU8+AX8+BA8)/(C$48+E$48+H$48+K$48+N$48+Q$48+T$48+W$48+Z$48+AC$48+AF$48+AI$48+AL$48+AO$48+AR$48+AU$48+AX$48+BA$48))*BA$54,BB8-((BB8/BB$48)*BA$52)+(BB8/BB$48)*BA$53+BD8+((C8+E8+H8+K8+N8+Q8+T8+W8+Z8+AC8+AF8+AI8+AL8+AO8+AR8+AU8+AX8+BA8)/(C$48+E$48+H$48+K$48+N$48+Q$48+T$48+W$48+Z$48+AC$48+AF$48+AI$48+AL$48+AO$48+AR$48+AU$48+AX$48+BA$48))*BA$54) -> 214720.03 | BF8: =(BE8/BE$48)*BD$53 -> 0 | BG8: =epargne_mensuelle!X8 -> 0 | BH8: =IF(BE$48=0,BE8+BG8+((C8+E8+H8+K8+N8+Q8+T8+W8+Z8+AC8+AF8+AI8+AL8+AO8+AR8+AU8+AX8+BA8+BD8)/(C$48+E$48+H$48+K$48+N$48+Q$48+T$48+W$48+Z$48+AC$48+AF$48+AI$48+AL$48+AO$48+AR$48+AU$48+AX$48+BA$48+BD$48))*BD$54,BE8-((BE8/BE$48)*BD$52)+(BE8/BE$48)*BD$53+BG8+((C8+E8+H8+K8+N8+Q8+T8+W8+Z8+AC8+AF8+AI8+AL8+AO8+AR8+AU8+AX8+BA8+BD8)/(C$48+E$48+H$48+K$48+N$48+Q$48+T$48+W$48+Z$48+AC$48+AF$48+AI$48+AL$48+AO$48+AR$48+AU$48+AX$48+BA$48+BD$48))*BD$54) -> 214720.03 | BI8: =(BH8/BH$48)*BG$53 -> 0 | BJ8: =epargne_mensuelle!Y8 -> 0 | BK8: =IF(BH$48=0,BH8+BJ8+((C8+E8+H8+K8+N8+Q8+T8+W8+Z8+AC8+AF8+AI8+AL8+AO8+AR8+AU8+AX8+BA8+BD8+BG8)/(C$48+E$48+H$48+K$48+N$48+Q$48+T$48+W$48+Z$48+AC$48+AF$48+AI$48+AL$48+AO$48+AR$48+AU$48+AX$48+BA$48+BD$48+BG$48))*BG$54,BH8-((BH8/BH$48)*BG$52)+(BH8/BH$48)*BG$53+BJ8+((C8+E8+H8+K8+N8+Q8+T8+W8+Z8+AC8+AF8+AI8+AL8+AO8+AR8+AU8+AX8+BA8+BD8+BG8)/(C$48+E$48+H$48+K$48+N$48+Q$48+T$48+W$48+Z$48+AC$48+AF$48+AI$48+AL$48+AO$48+AR$48+AU$48+AX$48+BA$48+BD$48+BG$48))*BG$54) -> 214720.03 | BL8: =(BK8/BK$48)*BJ$53 -> 0 | BM8: =epargne_mensuelle!Z8 -> 0 | BN8: =IF(BK$48=0,BK8+BM8+((C8+E8+H8+K8+N8+Q8+T8+W8+Z8+AC8+AF8+AI8+AL8+AO8+AR8+AU8+AX8+BA8+BD8+BG8+BJ8)/(C$48+E$48+H$48+K$48+N$48+Q$48+T$48+W$48+Z$48+AC$48+AF$48+AI$48+AL$48+AO$48+AR$48+AU$48+AX$48+BA$48+BD$48+BG$48+BJ$48))*BJ$54,BK8-((BK8/BK$48)*BJ$52)+(BK8/BK$48)*BJ$53+BM8+((C8+E8+H8+K8+N8+Q8+T8+W8+Z8+AC8+AF8+AI8+AL8+AO8+AR8+AU8+AX8+BA8+BD8+BG8+BJ8)/(C$48+E$48+H$48+K$48+N$48+Q$48+T$48+W$48+Z$48+AC$48+AF$48+AI$48+AL$48+AO$48+AR$48+AU$48+AX$48+BA$48+BD$48+BG$48+BJ$48))*BJ$54) -> 214720.03 | BO8: =(BN8/BN$48)*BM$53 -> 0 | BP8: =epargne_mensuelle!AA8 -> 0 | BQ8: =IF(BN$48=0,BN8+BP8+((F8+H8+K8+N8+Q8+T8+W8+Z8+AC8+AF8+AI8+AL8+AO8+AR8+AU8+AX8+BA8+BD8+BG8+BJ8+BM8)/(F$48+H$48+K$48+N$48+Q$48+T$48+W$48+Z$48+AC$48+AF$48+AI$48+AL$48+AO$48+AR$48+AU$48+AX$48+BA$48+BD$48+BG$48+BJ$48+BM$48))*BM$54,BN8-((BN8/BN$48)*BM$52)+(BN8/BN$48)*BM$53+BP8+((F8+H8+K8+N8+Q8+T8+W8+Z8+AC8+AF8+AI8+AL8+AO8+AR8+AU8+AX8+BA8+BD8+BG8+BJ8+BM8)/(F$48+H$48+K$48+N$48+Q$48+T$48+W$48+Z$48+AC$48+AF$48+AI$48+AL$48+AO$48+AR$48+AU$48+AX$48+BA$48+BD$48+BG$48+BJ$48+BM$48))*BM$54) -> 214720.03 | BR8: =(BQ8/BQ$48)*BP$53 -> 0 | BS8: =epargne_mensuelle!AB8 -> 0 | BT8: =IF(BQ$48=0,BQ8+BS8+((I8+K8+N8+Q8+T8+W8+Z8+AC8+AF8+AI8+AL8+AO8+AR8+AU8+AX8+BA8+BD8+BG8+BJ8+BM8+BP8)/(I$48+K$48+N$48+Q$48+T$48+W$48+Z$48+AC$48+AF$48+AI$48+AL$48+AO$48+AR$48+AU$48+AX$48+BA$48+BD$48+BG$48+BJ$48+BM$48+BP$48))*BP$54,BQ8-((BQ8/BQ$48)*BP$52)+(BQ8/BQ$48)*BP$53+BS8+((I8+K8+N8+Q8+T8+W8+Z8+AC8+AF8+AI8+AL8+AO8+AR8+AU8+AX8+BA8+BD8+BG8+BJ8+BM8+BP8)/(I$48+K$48+N$48+Q$48+T$48+W$48+Z$48+AC$48+AF$48+AI$48+AL$48+AO$48+AR$48+AU$48+AX$48+BA$48+BD$48+BG$48+BJ$48+BM$48+BP$48))*BP$54) -> 214720.03 | BU8: =(BT8/BT$48)*BS$53 -> 0 | BV8: =cumul_epargne!C8 -> 840018.32 | BW8: =D8+G8+J8+M8+P8+S8+V8+Y8+AB8+AE8+AH8+AK8+AN8+AQ8+AT8+AW8+AZ8+BC8+BF8+BI8+BL8+BO8+BR8+BU8 -> 139941.45 | BX8: =IF(BV8="",BW8,BV8+BW8) -> 979959.77 | BZ8: =BX8+BY8 -> 979959.77 | CA8: =IF(BV8="","",BW8/BV8) -> 0.16659333 | CB8: =BZ8/BZ$48 -> 0.021600812 | CC8: =CB8*(C$50-BW$58-BW$57) -> 93505.658 | CD8: =B8 -> ACTIONNIRE7
A9: =epargne_mensuelle!A9 -> 8 | B9: =epargne_mensuelle!B9 -> ACTIONNIRE8 | C9: =SUM(epargne_mensuelle!C9:E9) -> 5000758.2 | D9: =(C9/C$48)*C$53 -> 632096.57 | E9: =epargne_mensuelle!F9 -> 0 | F9: =C9-(C9/C$48)*C$52+(C9/C$48)*C$53+E9+(C9/C$48)*C$54 -> 748670.76 | G9: =(F9/F$48)*E$53 -> 0 | H9: =epargne_mensuelle!G9 -> 1000000 | I9: =IF(F$48=0,F9+H9+((C9+E9)/(C$48+E$48))*E$54,F9-((F9/F$48)*E$52)+(F9/F$48)*E$53+H9+((C9+E9)/(C$48+E$48))*E$54) -> 1852986 | J9: =(I9/I$48)*H$53 -> 176057.66 | K9: =epargne_mensuelle!H9 -> 0 | L9: =IF(I$48=0,I9+K9+((C9+E9+H9)/(C$48+E$48+H$48))*H$54,I9-((I9/I$48)*H$52)+(I9/I$48)*H$53+K9+((C9+E9+H9)/(C$48+E$48+H$48))*H$54) -> 1154592.4 | M9: =(L9/L$48)*K$53 -> 44679.13 | N9: =epargne_mensuelle!I9 -> 0 | O9: =IF(L$48=0,L9+N9+((C9+E9+H9+K9)/(C$48+E$48+H$48+K$48))*K$54,L9-((L9/L$48)*K$52)+(L9/L$48)*K$53+N9+((C9+E9+H9+K9)/(C$48+E$48+H$48+K$48))*K$54) -> 878407.97 | P9: =(O9/O$48)*N$53 -> 13888.306 | Q9: =epargne_mensuelle!J9 -> 0 | R9: =IF(O$48=0,O9+Q9+((C9+E9+H9+K9+N9)/(C$48+E$48+H$48+K$48+N$48))*N$54,O9-((O9/O$48)*N$52)+(O9/O$48)*N$53+Q9+((C9+E9+H9+K9+N9)/(C$48+E$48+H$48+K$48+N$48))*N$54) -> 1252742.6 | S9: =(R9/R$48)*Q$53 -> 104102.39 | T9: =epargne_mensuelle!K9 -> 0 | U9: =IF(R$48=0,R9+T9+((C9+E9+H9+K9+N9+Q9)/(C$48+E$48+H$48+K$48+N$48+Q$48))*Q$54,R9-((R9/R$48)*Q$52)+(R9/R$48)*Q$53+T9+((C9+E9+H9+K9+N9+Q9)/(C$48+E$48+H$48+K$48+N$48+Q$48))*Q$54) -> 1586529.9 | V9: =(U9/U$48)*T$53 -> 0 | W9: =epargne_mensuelle!L9 -> 0 | X9: =IF(U$48=0,U9+W9+((C9+E9+H9+K9+N9+Q9+T9)/(C$48+E$48+H$48+K$48+N$48+Q$48+T$48))*T$54,U9-((U9/U$48)*T$52)+(U9/U$48)*T$53+W9+((C9+E9+H9+K9+N9+Q9+T9)/(C$48+E$48+H$48+K$48+N$48+Q$48+T$48))*T$54) -> 1586529.9 | Y9: =(X9/X$48)*W$53 -> 0 | Z9: =epargne_mensuelle!M9 -> 0 | AA9: =IF(X$48=0,X9+Z9+((C9+E9+H9+K9+N9+Q9+T9+W9)/(C$48+E$48+H$48+K$48+N$48+Q$48+T$48+W$48))*W$54,X9-((X9/X$48)*W$52)+(X9/X$48)*W$53+Z9+((C9+E9+H9+K9+N9+Q9+T9+W9)/(C$48+E$48+H$48+K$48+N$48+Q$48+T$48+W$48))*W$54) -> 1586529.9 | AB9: =(AA9/AA$48)*Z$53 -> 0 | AC9: =epargne_mensuelle!N9 -> 0 | AD9: =IF(AA$48=0,AA9+AC9+((C9+E9+H9+K9+N9+Q9+T9+W9+Z9)/(C$48+E$48+H$48+K$48+N$48+Q$48+T$48+W$48+Z$48))*Z$54,AA9-((AA9/AA$48)*Z$52)+(AA9/AA$48)*Z$53+AC9+((C9+E9+H9+K9+N9+Q9+T9+W9+Z9)/(C$48+E$48+H$48+K$48+N$48+Q$48+T$48+W$48+Z$48))*Z$54) -> 1586529.9 | AE9: =(AD9/AD$48)*AC$53 -> 0 | AF9: =epargne_mensuelle!O9 -> 0 | AG9: =IF(AD$48=0,AD9+AF9+((C9+E9+H9+K9+N9+Q9+T9+W9+Z9+AC9)/(C$48+E$48+H$48+K$48+N$48+Q$48+T$48+W$48+Z$48+AC$48))*AC$54,AD9-((AD9/AD$48)*AC$52)+(AD9/AD$48)*AC$53+AF9+((C9+E9+H9+K9+N9+Q9+T9+W9+Z9+AC9)/(C$48+E$48+H$48+K$48+N$48+Q$48+T$48+W$48+Z$48+AC$48))*AC$54) -> 1586529.9 | AH9: =(AG9/AG$48)*AF$53 -> 0 | AI9: =epargne_mensuelle!P9 -> 0 | AJ9: =IF(AG$48=0,AG9+AI9+((C9+E9+H9+K9+N9+Q9+T9+W9+Z9+AC9+AF9)/(C$48+E$48+H$48+K$48+N$48+Q$48+T$48+W$48+Z$48+AC$48+AF$48))*AF$54,AG9-((AG9/AG$48)*AF$52)+(AG9/AG$48)*AF$53+AI9+((C9+E9+H9+K9+N9+Q9+T9+W9+Z9+AC9+AF9)/(C$48+E$48+H$48+K$48+N$48+Q$48+T$48+W$48+Z$48+AC$48+AF$48))*AF$54) -> 1586529.9 | AK9: =(AJ9/AJ$48)*AI$53 -> 0 | AL9: =epargne_mensuelle!Q9 -> 0 | AM9: =IF(AJ$48=0,AJ9+AL9+((C9+E9+H9+K9+N9+Q9+T9+W9+Z9+AC9+AF9+AI9)/(C$48+E$48+H$48+K$48+N$48+Q$48+T$48+W$48+Z$48+AC$48+AF$48+AI$48))*AI$54,AJ9-((AJ9/AJ$48)*AI$52)+(AJ9/AJ$48)*AI$53+AL9+((C9+E9+H9+K9+N9+Q9+T9+W9+Z9+AC9+AF9+AI9)/(C$48+E$48+H$48+K$48+N$48+Q$48+T$48+W$48+Z$48+AC$48+AF$48+AI$48))*AI$54) -> 1586529.9 | AN9: =(AM9/AM$48)*AL$53 -> 0 | AO9: =epargne_mensuelle!R9 -> 0 | AP9: =IF(AM$48=0,AM9+AO9+((C9+E9+H9+K9+N9+Q9+T9+W9+Z9+AC9+AF9+AI9+AL9)/(C$48+E$48+H$48+K$48+N$48+Q$48+T$48+W$48+Z$48+AC$48+AF$48+AI$48+AL$48))*AL$54,AM9-((AM9/AM$48)*AL$52)+(AM9/AM$48)*AL$53+AO9+((C9+E9+H9+K9+N9+Q9+T9+W9+Z9+AC9+AF9+AI9+AL9)/(C$48+E$48+H$48+K$48+N$48+Q$48+T$48+W$48+Z$48+AC$48+AF$48+AI$48+AL$48))*AL$54) -> 1586529.9 | AQ9: =(AP9/AP$48)*AO$53 -> 0 | AR9: =epargne_mensuelle!S9 -> 0 | AS9: =IF(AP$48=0,AP9+AR9+((C9+E9+H9+K9+N9+Q9+T9+W9+Z9+AC9+AF9+AI9+AL9+AO9)/(C$48+E$48+H$48+K$48+N$48+Q$48+T$48+W$48+Z$48+AC$48+AF$48+AI$48+AL$48+AO$48))*AO$54,AP9-((AP9/AP$48)*AO$52)+(AP9/AP$48)*AO$53+AR9+((C9+E9+H9+K9+N9+Q9+T9+W9+Z9+AC9+AF9+AI9+AL9+AO9)/(C$48+E$48+H$48+K$48+N$48+Q$48+T$48+W$48+Z$48+AC$48+AF$48+AI$48+AL$48+AO$48))*AO$54) -> 1586529.9 | AT9: =(AS9/AS$48)*AR$53 -> 0 | AU9: =epargne_mensuelle!T9 -> 0 | AV9: =IF(AS$48=0,AS9+AU9+((C9+E9+H9+K9+N9+Q9+T9+W9+Z9+AC9+AF9+AI9+AL9+AO9+AR9)/(C$48+E$48+H$48+K$48+N$48+Q$48+T$48+W$48+Z$48+AC$48+AF$48+AI$48+AL$48+AO$48+AR$48))*AR$54,AS9-((AS9/AS$48)*AR$52)+(AS9/AS$48)*AR$53+AU9+((C9+E9+H9+K9+N9+Q9+T9+W9+Z9+AC9+AF9+AI9+AL9+AO9+AR9)/(C$48+E$48+H$48+K$48+N$48+Q$48+T$48+W$48+Z$48+AC$48+AF$48+AI$48+AL$48+AO$48+AR$48))*AR$54) -> 1586529.9 | AW9: =(AV9/AV$48)*AU$53 -> 0 | AX9: =epargne_mensuelle!U9 -> 0 | AY9: =IF(AV$48=0,AV9+AX9+((C9+E9+H9+K9+N9+Q9+T9+W9+Z9+AC9+AF9+AI9+AL9+AO9+AR9+AU9)/(C$48+E$48+H$48+K$48+N$48+Q$48+T$48+W$48+Z$48+AC$48+AF$48+AI$48+AL$48+AO$48+AR$48+AU$48))*AU$54,AV9-((AV9/AV$48)*AU$52)+(AV9/AV$48)*AU$53+AX9+((C9+E9+H9+K9+N9+Q9+T9+W9+Z9+AC9+AF9+AI9+AL9+AO9+AR9+AU9)/(C$48+E$48+H$48+K$48+N$48+Q$48+T$48+W$48+Z$48+AC$48+AF$48+AI$48+AL$48+AO$48+AR$48+AU$48))*AU$54) -> 1586529.9 | AZ9: =(AY9/AY$48)*AX$53 -> 0 | BA9: =epargne_mensuelle!V9 -> 0 | BB9: =IF(AY$48=0,AY9+BA9+((C9+E9+H9+K9+N9+Q9+T9+W9+Z9+AC9+AF9+AI9+AL9+AO9+AR9+AU9+AX9)/(C$48+E$48+H$48+K$48+N$48+Q$48+T$48+W$48+Z$48+AC$48+AF$48+AI$48+AL$48+AO$48+AR$48+AU$48+AX$48))*AX$54,AY9-((AY9/AY$48)*AX$52)+(AY9/AY$48)*AX$53+BA9+((C9+E9+H9+K9+N9+Q9+T9+W9+Z9+AC9+AF9+AI9+AL9+AO9+AR9+AU9+AX9)/(C$48+E$48+H$48+K$48+N$48+Q$48+T$48+W$48+Z$48+AC$48+AF$48+AI$48+AL$48+AO$48+AR$48+AU$48+AX$48))*AX$54) -> 1586529.9 | BC9: =(BB9/BB$48)*BA$53 -> 0 | BD9: =epargne_mensuelle!W9 -> 0 | BE9: =IF(BB$48=0,BB9+BD9+((C9+E9+H9+K9+N9+Q9+T9+W9+Z9+AC9+AF9+AI9+AL9+AO9+AR9+AU9+AX9+BA9)/(C$48+E$48+H$48+K$48+N$48+Q$48+T$48+W$48+Z$48+AC$48+AF$48+AI$48+AL$48+AO$48+AR$48+AU$48+AX$48+BA$48))*BA$54,BB9-((BB9/BB$48)*BA$52)+(BB9/BB$48)*BA$53+BD9+((C9+E9+H9+K9+N9+Q9+T9+W9+Z9+AC9+AF9+AI9+AL9+AO9+AR9+AU9+AX9+BA9)/(C$48+E$48+H$48+K$48+N$48+Q$48+T$48+W$48+Z$48+AC$48+AF$48+AI$48+AL$48+AO$48+AR$48+AU$48+AX$48+BA$48))*BA$54) -> 1586529.9 | BF9: =(BE9/BE$48)*BD$53 -> 0 | BG9: =epargne_mensuelle!X9 -> 0 | BH9: =IF(BE$48=0,BE9+BG9+((C9+E9+H9+K9+N9+Q9+T9+W9+Z9+AC9+AF9+AI9+AL9+AO9+AR9+AU9+AX9+BA9+BD9)/(C$48+E$48+H$48+K$48+N$48+Q$48+T$48+W$48+Z$48+AC$48+AF$48+AI$48+AL$48+AO$48+AR$48+AU$48+AX$48+BA$48+BD$48))*BD$54,BE9-((BE9/BE$48)*BD$52)+(BE9/BE$48)*BD$53+BG9+((C9+E9+H9+K9+N9+Q9+T9+W9+Z9+AC9+AF9+AI9+AL9+AO9+AR9+AU9+AX9+BA9+BD9)/(C$48+E$48+H$48+K$48+N$48+Q$48+T$48+W$48+Z$48+AC$48+AF$48+AI$48+AL$48+AO$48+AR$48+AU$48+AX$48+BA$48+BD$48))*BD$54) -> 1586529.9 | BI9: =(BH9/BH$48)*BG$53 -> 0 | BJ9: =epargne_mensuelle!Y9 -> 0 | BK9: =IF(BH$48=0,BH9+BJ9+((C9+E9+H9+K9+N9+Q9+T9+W9+Z9+AC9+AF9+AI9+AL9+AO9+AR9+AU9+AX9+BA9+BD9+BG9)/(C$48+E$48+H$48+K$48+N$48+Q$48+T$48+W$48+Z$48+AC$48+AF$48+AI$48+AL$48+AO$48+AR$48+AU$48+AX$48+BA$48+BD$48+BG$48))*BG$54,BH9-((BH9/BH$48)*BG$52)+(BH9/BH$48)*BG$53+BJ9+((C9+E9+H9+K9+N9+Q9+T9+W9+Z9+AC9+AF9+AI9+AL9+AO9+AR9+AU9+AX9+BA9+BD9+BG9)/(C$48+E$48+H$48+K$48+N$48+Q$48+T$48+W$48+Z$48+AC$48+AF$48+AI$48+AL$48+AO$48+AR$48+AU$48+AX$48+BA$48+BD$48+BG$48))*BG$54) -> 1586529.9 | BL9: =(BK9/BK$48)*BJ$53 -> 0 | BM9: =epargne_mensuelle!Z9 -> 0 | BN9: =IF(BK$48=0,BK9+BM9+((C9+E9+H9+K9+N9+Q9+T9+W9+Z9+AC9+AF9+AI9+AL9+AO9+AR9+AU9+AX9+BA9+BD9+BG9+BJ9)/(C$48+E$48+H$48+K$48+N$48+Q$48+T$48+W$48+Z$48+AC$48+AF$48+AI$48+AL$48+AO$48+AR$48+AU$48+AX$48+BA$48+BD$48+BG$48+BJ$48))*BJ$54,BK9-((BK9/BK$48)*BJ$52)+(BK9/BK$48)*BJ$53+BM9+((C9+E9+H9+K9+N9+Q9+T9+W9+Z9+AC9+AF9+AI9+AL9+AO9+AR9+AU9+AX9+BA9+BD9+BG9+BJ9)/(C$48+E$48+H$48+K$48+N$48+Q$48+T$48+W$48+Z$48+AC$48+AF$48+AI$48+AL$48+AO$48+AR$48+AU$48+AX$48+BA$48+BD$48+BG$48+BJ$48))*BJ$54) -> 1586529.9 | BO9: =(BN9/BN$48)*BM$53 -> 0 | BP9: =epargne_mensuelle!AA9 -> 0 | BQ9: =IF(BN$48=0,BN9+BP9+((F9+H9+K9+N9+Q9+T9+W9+Z9+AC9+AF9+AI9+AL9+AO9+AR9+AU9+AX9+BA9+BD9+BG9+BJ9+BM9)/(F$48+H$48+K$48+N$48+Q$48+T$48+W$48+Z$48+AC$48+AF$48+AI$48+AL$48+AO$48+AR$48+AU$48+AX$48+BA$48+BD$48+BG$48+BJ$48+BM$48))*BM$54,BN9-((BN9/BN$48)*BM$52)+(BN9/BN$48)*BM$53+BP9+((F9+H9+K9+N9+Q9+T9+W9+Z9+AC9+AF9+AI9+AL9+AO9+AR9+AU9+AX9+BA9+BD9+BG9+BJ9+BM9)/(F$48+H$48+K$48+N$48+Q$48+T$48+W$48+Z$48+AC$48+AF$48+AI$48+AL$48+AO$48+AR$48+AU$48+AX$48+BA$48+BD$48+BG$48+BJ$48+BM$48))*BM$54) -> 1586529.9 | BR9: =(BQ9/BQ$48)*BP$53 -> 0 | BS9: =epargne_mensuelle!AB9 -> 0 | BT9: =IF(BQ$48=0,BQ9+BS9+((I9+K9+N9+Q9+T9+W9+Z9+AC9+AF9+AI9+AL9+AO9+AR9+AU9+AX9+BA9+BD9+BG9+BJ9+BM9+BP9)/(I$48+K$48+N$48+Q$48+T$48+W$48+Z$48+AC$48+AF$48+AI$48+AL$48+AO$48+AR$48+AU$48+AX$48+BA$48+BD$48+BG$48+BJ$48+BM$48+BP$48))*BP$54,BQ9-((BQ9/BQ$48)*BP$52)+(BQ9/BQ$48)*BP$53+BS9+((I9+K9+N9+Q9+T9+W9+Z9+AC9+AF9+AI9+AL9+AO9+AR9+AU9+AX9+BA9+BD9+BG9+BJ9+BM9+BP9)/(I$48+K$48+N$48+Q$48+T$48+W$48+Z$48+AC$48+AF$48+AI$48+AL$48+AO$48+AR$48+AU$48+AX$48+BA$48+BD$48+BG$48+BJ$48+BM$48+BP$48))*BP$54) -> 1586529.9 | BU9: =(BT9/BT$48)*BS$53 -> 0 | BV9: =cumul_epargne!C9 -> 6000758.2 | BW9: =D9+G9+J9+M9+P9+S9+V9+Y9+AB9+AE9+AH9+AK9+AN9+AQ9+AT9+AW9+AZ9+BC9+BF9+BI9+BL9+BO9+BR9+BU9 -> 970824.06 | BX9: =IF(BV9="",BW9,BV9+BW9) -> 6971582.3 | BZ9: =BX9+BY9 -> 6971582.3 | CA9: =IF(BV9="","",BW9/BV9) -> 0.16178357 | CB9: =BZ9/BZ$48 -> 0.15367145 | CC9: =CB9*(C$50-BW$58-BW$57) -> 665213.42 | CD9: =B9 -> ACTIONNIRE8
A10: =epargne_mensuelle!A10 -> 9 | B10: =epargne_mensuelle!B10 -> ACTIONNIRE9 | C10: =SUM(epargne_mensuelle!C10:E10) -> 539026.95 | D10: =(C10/C$48)*C$53 -> 68133.086 | E10: =epargne_mensuelle!F10 -> 0 | F10: =C10-(C10/C$48)*C$52+(C10/C$48)*C$53+E10+(C10/C$48)*C$54 -> 80698.507 | G10: =(F10/F$48)*E$53 -> 0 | H10: =epargne_mensuelle!G10 -> 0 | I10: =IF(F$48=0,F10+H10+((C10+E10)/(C$48+E$48))*E$54,F10-((F10/F$48)*E$52)+(F10/F$48)*E$53+H10+((C10+E10)/(C$48+E$48))*E$54) -> 91942.546 | J10: =(I10/I$48)*H$53 -> 8735.732 | K10: =epargne_mensuelle!H10 -> 0 | L10: =IF(I$48=0,I10+K10+((C10+E10+H10)/(C$48+E$48+H$48))*H$54,I10-((I10/I$48)*H$52)+(I10/I$48)*H$53+K10+((C10+E10+H10)/(C$48+E$48+H$48))*H$54) -> 78242.687 | M10: =(L10/L$48)*K$53 -> 3027.7483 | N10: =epargne_mensuelle!I10 -> 0 | O10: =IF(L$48=0,L10+N10+((C10+E10+H10+K10)/(C$48+E$48+H$48+K$48))*K$54,L10-((L10/L$48)*K$52)+(L10/L$48)*K$53+N10+((C10+E10+H10+K10)/(C$48+E$48+H$48+K$48))*K$54) -> 68560.17 | P10: =(O10/O$48)*N$53 -> 1083.989 | Q10: =epargne_mensuelle!J10 -> 0 | R10: =IF(O$48=0,O10+Q10+((C10+E10+H10+K10+N10)/(C$48+E$48+H$48+K$48+N$48))*N$54,O10-((O10/O$48)*N$52)+(O10/O$48)*N$53+Q10+((C10+E10+H10+K10+N10)/(C$48+E$48+H$48+K$48+N$48))*N$54) -> 106110.49 | S10: =(R10/R$48)*Q$53 -> 8817.7383 | T10: =epargne_mensuelle!K10 -> 0 | U10: =IF(R$48=0,R10+T10+((C10+E10+H10+K10+N10+Q10)/(C$48+E$48+H$48+K$48+N$48+Q$48))*Q$54,R10-((R10/R$48)*Q$52)+(R10/R$48)*Q$53+T10+((C10+E10+H10+K10+N10+Q10)/(C$48+E$48+H$48+K$48+N$48+Q$48))*Q$54) -> 137782.57 | V10: =(U10/U$48)*T$53 -> 0 | W10: =epargne_mensuelle!L10 -> 0 | X10: =IF(U$48=0,U10+W10+((C10+E10+H10+K10+N10+Q10+T10)/(C$48+E$48+H$48+K$48+N$48+Q$48+T$48))*T$54,U10-((U10/U$48)*T$52)+(U10/U$48)*T$53+W10+((C10+E10+H10+K10+N10+Q10+T10)/(C$48+E$48+H$48+K$48+N$48+Q$48+T$48))*T$54) -> 137782.57 | Y10: =(X10/X$48)*W$53 -> 0 | Z10: =epargne_mensuelle!M10 -> 0 | AA10: =IF(X$48=0,X10+Z10+((C10+E10+H10+K10+N10+Q10+T10+W10)/(C$48+E$48+H$48+K$48+N$48+Q$48+T$48+W$48))*W$54,X10-((X10/X$48)*W$52)+(X10/X$48)*W$53+Z10+((C10+E10+H10+K10+N10+Q10+T10+W10)/(C$48+E$48+H$48+K$48+N$48+Q$48+T$48+W$48))*W$54) -> 137782.57 | AB10: =(AA10/AA$48)*Z$53 -> 0 | AC10: =epargne_mensuelle!N10 -> 0 | AD10: =IF(AA$48=0,AA10+AC10+((C10+E10+H10+K10+N10+Q10+T10+W10+Z10)/(C$48+E$48+H$48+K$48+N$48+Q$48+T$48+W$48+Z$48))*Z$54,AA10-((AA10/AA$48)*Z$52)+(AA10/AA$48)*Z$53+AC10+((C10+E10+H10+K10+N10+Q10+T10+W10+Z10)/(C$48+E$48+H$48+K$48+N$48+Q$48+T$48+W$48+Z$48))*Z$54) -> 137782.57 | AE10: =(AD10/AD$48)*AC$53 -> 0 | AF10: =epargne_mensuelle!O10 -> 0 | AG10: =IF(AD$48=0,AD10+AF10+((C10+E10+H10+K10+N10+Q10+T10+W10+Z10+AC10)/(C$48+E$48+H$48+K$48+N$48+Q$48+T$48+W$48+Z$48+AC$48))*AC$54,AD10-((AD10/AD$48)*AC$52)+(AD10/AD$48)*AC$53+AF10+((C10+E10+H10+K10+N10+Q10+T10+W10+Z10+AC10)/(C$48+E$48+H$48+K$48+N$48+Q$48+T$48+W$48+Z$48+AC$48))*AC$54) -> 137782.57 | AH10: =(AG10/AG$48)*AF$53 -> 0 | AI10: =epargne_mensuelle!P10 -> 0 | AJ10: =IF(AG$48=0,AG10+AI10+((C10+E10+H10+K10+N10+Q10+T10+W10+Z10+AC10+AF10)/(C$48+E$48+H$48+K$48+N$48+Q$48+T$48+W$48+Z$48+AC$48+AF$48))*AF$54,AG10-((AG10/AG$48)*AF$52)+(AG10/AG$48)*AF$53+AI10+((C10+E10+H10+K10+N10+Q10+T10+W10+Z10+AC10+AF10)/(C$48+E$48+H$48+K$48+N$48+Q$48+T$48+W$48+Z$48+AC$48+AF$48))*AF$54) -> 137782.57 | AK10: =(AJ10/AJ$48)*AI$53 -> 0 | AL10: =epargne_mensuelle!Q10 -> 0 | AM10: =IF(AJ$48=0,AJ10+AL10+((C10+E10+H10+K10+N10+Q10+T10+W10+Z10+AC10+AF10+AI10)/(C$48+E$48+H$48+K$48+N$48+Q$48+T$48+W$48+Z$48+AC$48+AF$48+AI$48))*AI$54,AJ10-((AJ10/AJ$48)*AI$52)+(AJ10/AJ$48)*AI$53+AL10+((C10+E10+H10+K10+N10+Q10+T10+W10+Z10+AC10+AF10+AI10)/(C$48+E$48+H$48+K$48+N$48+Q$48+T$48+W$48+Z$48+AC$48+AF$48+AI$48))*AI$54) -> 137782.57 | AN10: =(AM10/AM$48)*AL$53 -> 0 | AO10: =epargne_mensuelle!R10 -> 0 | AP10: =IF(AM$48=0,AM10+AO10+((C10+E10+H10+K10+N10+Q10+T10+W10+Z10+AC10+AF10+AI10+AL10)/(C$48+E$48+H$48+K$48+N$48+Q$48+T$48+W$48+Z$48+AC$48+AF$48+AI$48+AL$48))*AL$54,AM10-((AM10/AM$48)*AL$52)+(AM10/AM$48)*AL$53+AO10+((C10+E10+H10+K10+N10+Q10+T10+W10+Z10+AC10+AF10+AI10+AL10)/(C$48+E$48+H$48+K$48+N$48+Q$48+T$48+W$48+Z$48+AC$48+AF$48+AI$48+AL$48))*AL$54) -> 137782.57 | AQ10: =(AP10/AP$48)*AO$53 -> 0 | AR10: =epargne_mensuelle!S10 -> 0 | AS10: =IF(AP$48=0,AP10+AR10+((C10+E10+H10+K10+N10+Q10+T10+W10+Z10+AC10+AF10+AI10+AL10+AO10)/(C$48+E$48+H$48+K$48+N$48+Q$48+T$48+W$48+Z$48+AC$48+AF$48+AI$48+AL$48+AO$48))*AO$54,AP10-((AP10/AP$48)*AO$52)+(AP10/AP$48)*AO$53+AR10+((C10+E10+H10+K10+N10+Q10+T10+W10+Z10+AC10+AF10+AI10+AL10+AO10)/(C$48+E$48+H$48+K$48+N$48+Q$48+T$48+W$48+Z$48+AC$48+AF$48+AI$48+AL$48+AO$48))*AO$54) -> 137782.57 | AT10: =(AS10/AS$48)*AR$53 -> 0 | AU10: =epargne_mensuelle!T10 -> 0 | AV10: =IF(AS$48=0,AS10+AU10+((C10+E10+H10+K10+N10+Q10+T10+W10+Z10+AC10+AF10+AI10+AL10+AO10+AR10)/(C$48+E$48+H$48+K$48+N$48+Q$48+T$48+W$48+Z$48+AC$48+AF$48+AI$48+AL$48+AO$48+AR$48))*AR$54,AS10-((AS10/AS$48)*AR$52)+(AS10/AS$48)*AR$53+AU10+((C10+E10+H10+K10+N10+Q10+T10+W10+Z10+AC10+AF10+AI10+AL10+AO10+AR10)/(C$48+E$48+H$48+K$48+N$48+Q$48+T$48+W$48+Z$48+AC$48+AF$48+AI$48+AL$48+AO$48+AR$48))*AR$54) -> 137782.57 | AW10: =(AV10/AV$48)*AU$53 -> 0 | AX10: =epargne_mensuelle!U10 -> 0 | AY10: =IF(AV$48=0,AV10+AX10+((C10+E10+H10+K10+N10+Q10+T10+W10+Z10+AC10+AF10+AI10+AL10+AO10+AR10+AU10)/(C$48+E$48+H$48+K$48+N$48+Q$48+T$48+W$48+Z$48+AC$48+AF$48+AI$48+AL$48+AO$48+AR$48+AU$48))*AU$54,AV10-((AV10/AV$48)*AU$52)+(AV10/AV$48)*AU$53+AX10+((C10+E10+H10+K10+N10+Q10+T10+W10+Z10+AC10+AF10+AI10+AL10+AO10+AR10+AU10)/(C$48+E$48+H$48+K$48+N$48+Q$48+T$48+W$48+Z$48+AC$48+AF$48+AI$48+AL$48+AO$48+AR$48+AU$48))*AU$54) -> 137782.57 | AZ10: =(AY10/AY$48)*AX$53 -> 0 | BA10: =epargne_mensuelle!V10 -> 0 | BB10: =IF(AY$48=0,AY10+BA10+((C10+E10+H10+K10+N10+Q10+T10+W10+Z10+AC10+AF10+AI10+AL10+AO10+AR10+AU10+AX10)/(C$48+E$48+H$48+K$48+N$48+Q$48+T$48+W$48+Z$48+AC$48+AF$48+AI$48+AL$48+AO$48+AR$48+AU$48+AX$48))*AX$54,AY10-((AY10/AY$48)*AX$52)+(AY10/AY$48)*AX$53+BA10+((C10+E10+H10+K10+N10+Q10+T10+W10+Z10+AC10+AF10+AI10+AL10+AO10+AR10+AU10+AX10)/(C$48+E$48+H$48+K$48+N$48+Q$48+T$48+W$48+Z$48+AC$48+AF$48+AI$48+AL$48+AO$48+AR$48+AU$48+AX$48))*AX$54) -> 137782.57 | BC10: =(BB10/BB$48)*BA$53 -> 0 | BD10: =epargne_mensuelle!W10 -> 0 | BE10: =IF(BB$48=0,BB10+BD10+((C10+E10+H10+K10+N10+Q10+T10+W10+Z10+AC10+AF10+AI10+AL10+AO10+AR10+AU10+AX10+BA10)/(C$48+E$48+H$48+K$48+N$48+Q$48+T$48+W$48+Z$48+AC$48+AF$48+AI$48+AL$48+AO$48+AR$48+AU$48+AX$48+BA$48))*BA$54,BB10-((BB10/BB$48)*BA$52)+(BB10/BB$48)*BA$53+BD10+((C10+E10+H10+K10+N10+Q10+T10+W10+Z10+AC10+AF10+AI10+AL10+AO10+AR10+AU10+AX10+BA10)/(C$48+E$48+H$48+K$48+N$48+Q$48+T$48+W$48+Z$48+AC$48+AF$48+AI$48+AL$48+AO$48+AR$48+AU$48+AX$48+BA$48))*BA$54) -> 137782.57 | BF10: =(BE10/BE$48)*BD$53 -> 0 | BG10: =epargne_mensuelle!X10 -> 0 | BH10: =IF(BE$48=0,BE10+BG10+((C10+E10+H10+K10+N10+Q10+T10+W10+Z10+AC10+AF10+AI10+AL10+AO10+AR10+AU10+AX10+BA10+BD10)/(C$48+E$48+H$48+K$48+N$48+Q$48+T$48+W$48+Z$48+AC$48+AF$48+AI$48+AL$48+AO$48+AR$48+AU$48+AX$48+BA$48+BD$48))*BD$54,BE10-((BE10/BE$48)*BD$52)+(BE10/BE$48)*BD$53+BG10+((C10+E10+H10+K10+N10+Q10+T10+W10+Z10+AC10+AF10+AI10+AL10+AO10+AR10+AU10+AX10+BA10+BD10)/(C$48+E$48+H$48+K$48+N$48+Q$48+T$48+W$48+Z$48+AC$48+AF$48+AI$48+AL$48+AO$48+AR$48+AU$48+AX$48+BA$48+BD$48))*BD$54) -> 137782.57 | BI10: =(BH10/BH$48)*BG$53 -> 0 | BJ10: =epargne_mensuelle!Y10 -> 0 | BK10: =IF(BH$48=0,BH10+BJ10+((C10+E10+H10+K10+N10+Q10+T10+W10+Z10+AC10+AF10+AI10+AL10+AO10+AR10+AU10+AX10+BA10+BD10+BG10)/(C$48+E$48+H$48+K$48+N$48+Q$48+T$48+W$48+Z$48+AC$48+AF$48+AI$48+AL$48+AO$48+AR$48+AU$48+AX$48+BA$48+BD$48+BG$48))*BG$54,BH10-((BH10/BH$48)*BG$52)+(BH10/BH$48)*BG$53+BJ10+((C10+E10+H10+K10+N10+Q10+T10+W10+Z10+AC10+AF10+AI10+AL10+AO10+AR10+AU10+AX10+BA10+BD10+BG10)/(C$48+E$48+H$48+K$48+N$48+Q$48+T$48+W$48+Z$48+AC$48+AF$48+AI$48+AL$48+AO$48+AR$48+AU$48+AX$48+BA$48+BD$48+BG$48))*BG$54) -> 137782.57 | BL10: =(BK10/BK$48)*BJ$53 -> 0 | BM10: =epargne_mensuelle!Z10 -> 0 | BN10: =IF(BK$48=0,BK10+BM10+((C10+E10+H10+K10+N10+Q10+T10+W10+Z10+AC10+AF10+AI10+AL10+AO10+AR10+AU10+AX10+BA10+BD10+BG10+BJ10)/(C$48+E$48+H$48+K$48+N$48+Q$48+T$48+W$48+Z$48+AC$48+AF$48+AI$48+AL$48+AO$48+AR$48+AU$48+AX$48+BA$48+BD$48+BG$48+BJ$48))*BJ$54,BK10-((BK10/BK$48)*BJ$52)+(BK10/BK$48)*BJ$53+BM10+((C10+E10+H10+K10+N10+Q10+T10+W10+Z10+AC10+AF10+AI10+AL10+AO10+AR10+AU10+AX10+BA10+BD10+BG10+BJ10)/(C$48+E$48+H$48+K$48+N$48+Q$48+T$48+W$48+Z$48+AC$48+AF$48+AI$48+AL$48+AO$48+AR$48+AU$48+AX$48+BA$48+BD$48+BG$48+BJ$48))*BJ$54) -> 137782.57 | BO10: =(BN10/BN$48)*BM$53 -> 0 | BP10: =epargne_mensuelle!AA10 -> 0 | BQ10: =IF(BN$48=0,BN10+BP10+((F10+H10+K10+N10+Q10+T10+W10+Z10+AC10+AF10+AI10+AL10+AO10+AR10+AU10+AX10+BA10+BD10+BG10+BJ10+BM10)/(F$48+H$48+K$48+N$48+Q$48+T$48+W$48+Z$48+AC$48+AF$48+AI$48+AL$48+AO$48+AR$48+AU$48+AX$48+BA$48+BD$48+BG$48+BJ$48+BM$48))*BM$54,BN10-((BN10/BN$48)*BM$52)+(BN10/BN$48)*BM$53+BP10+((F10+H10+K10+N10+Q10+T10+W10+Z10+AC10+AF10+AI10+AL10+AO10+AR10+AU10+AX10+BA10+BD10+BG10+BJ10+BM10)/(F$48+H$48+K$48+N$48+Q$48+T$48+W$48+Z$48+AC$48+AF$48+AI$48+AL$48+AO$48+AR$48+AU$48+AX$48+BA$48+BD$48+BG$48+BJ$48+BM$48))*BM$54) -> 137782.57 | BR10: =(BQ10/BQ$48)*BP$53 -> 0 | BS10: =epargne_mensuelle!AB10 -> 0 | BT10: =IF(BQ$48=0,BQ10+BS10+((I10+K10+N10+Q10+T10+W10+Z10+AC10+AF10+AI10+AL10+AO10+AR10+AU10+AX10+BA10+BD10+BG10+BJ10+BM10+BP10)/(I$48+K$48+N$48+Q$48+T$48+W$48+Z$48+AC$48+AF$48+AI$48+AL$48+AO$48+AR$48+AU$48+AX$48+BA$48+BD$48+BG$48+BJ$48+BM$48+BP$48))*BP$54,BQ10-((BQ10/BQ$48)*BP$52)+(BQ10/BQ$48)*BP$53+BS10+((I10+K10+N10+Q10+T10+W10+Z10+AC10+AF10+AI10+AL10+AO10+AR10+AU10+AX10+BA10+BD10+BG10+BJ10+BM10+BP10)/(I$48+K$48+N$48+Q$48+T$48+W$48+Z$48+AC$48+AF$48+AI$48+AL$48+AO$48+AR$48+AU$48+AX$48+BA$48+BD$48+BG$48+BJ$48+BM$48+BP$48))*BP$54) -> 137782.57 | BU10: =(BT10/BT$48)*BS$53 -> 0 | BV10: =cumul_epargne!C10 -> 539026.95 | BW10: =D10+G10+J10+M10+P10+S10+V10+Y10+AB10+AE10+AH10+AK10+AN10+AQ10+AT10+AW10+AZ10+BC10+BF10+BI10+BL10+BO10+BR10+BU10 -> 89798.294 | BX10: =IF(BV10="",BW10,BV10+BW10) -> 628825.25 | BZ10: =BX10+BY10 -> 628825.25 | CA10: =IF(BV10="","",BW10/BV10) -> 0.16659333 | CB10: =BZ10/BZ$48 -> 0.013860912 | CC10: =CB10*(C$50-BW$58-BW$57) -> 60001.156 | CD10: =B10 -> ACTIONNIRE9
A11: =epargne_mensuelle!A11 -> 10 | B11: =epargne_mensuelle!B11 -> ACTIONNIRE10 | C11: =SUM(epargne_mensuelle!C11:E11) -> 477772.09 | D11: =(C11/C$48)*C$53 -> 60390.463 | E11: =epargne_mensuelle!F11 -> 25000 | F11: =C11-(C11/C$48)*C$52+(C11/C$48)*C$53+E11+(C11/C$48)*C$54 -> 96527.953 | G11: =(F11/F$48)*E$53 -> 0 | H11: =epargne_mensuelle!G11 -> 0 | I11: =IF(F$48=0,F11+H11+((C11+E11)/(C$48+E$48))*E$54,F11-((F11/F$48)*E$52)+(F11/F$48)*E$53+H11+((C11+E11)/(C$48+E$48))*E$54) -> 107015.72 | J11: =(I11/I$48)*H$53 -> 10167.879 | K11: =epargne_mensuelle!H11 -> 0 | L11: =IF(I$48=0,I11+K11+((C11+E11+H11)/(C$48+E$48+H$48))*H$54,I11-((I11/I$48)*H$52)+(I11/I$48)*H$53+K11+((C11+E11+H11)/(C$48+E$48+H$48))*H$54) -> 80247.121 | M11: =(L11/L$48)*K$53 -> 3105.3137 | N11: =epargne_mensuelle!I11 -> 0 | O11: =IF(L$48=0,L11+N11+((C11+E11+H11+K11)/(C$48+E$48+H$48+K$48))*K$54,L11-((L11/L$48)*K$52)+(L11/L$48)*K$53+N11+((C11+E11+H11+K11)/(C$48+E$48+H$48+K$48))*K$54) -> 66900.146 | P11: =(O11/O$48)*N$53 -> 1057.7428 | Q11: =epargne_mensuelle!J11 -> 0 | R11: =IF(O$48=0,O11+Q11+((C11+E11+H11+K11+N11)/(C$48+E$48+H$48+K$48+N$48))*N$54,O11-((O11/O$48)*N$52)+(O11/O$48)*N$53+Q11+((C11+E11+H11+K11+N11)/(C$48+E$48+H$48+K$48+N$48))*N$54) -> 100804.94 | S11: =(R11/R$48)*Q$53 -> 8376.8487 | T11: =epargne_mensuelle!K11 -> 0 | U11: =IF(R$48=0,R11+T11+((C11+E11+H11+K11+N11+Q11)/(C$48+E$48+H$48+K$48+N$48+Q$48))*Q$54,R11-((R11/R$48)*Q$52)+(R11/R$48)*Q$53+T11+((C11+E11+H11+K11+N11+Q11)/(C$48+E$48+H$48+K$48+N$48+Q$48))*Q$54) -> 129864.82 | V11: =(U11/U$48)*T$53 -> 0 | W11: =epargne_mensuelle!L11 -> 0 | X11: =IF(U$48=0,U11+W11+((C11+E11+H11+K11+N11+Q11+T11)/(C$48+E$48+H$48+K$48+N$48+Q$48+T$48))*T$54,U11-((U11/U$48)*T$52)+(U11/U$48)*T$53+W11+((C11+E11+H11+K11+N11+Q11+T11)/(C$48+E$48+H$48+K$48+N$48+Q$48+T$48))*T$54) -> 129864.82 | Y11: =(X11/X$48)*W$53 -> 0 | Z11: =epargne_mensuelle!M11 -> 0 | AA11: =IF(X$48=0,X11+Z11+((C11+E11+H11+K11+N11+Q11+T11+W11)/(C$48+E$48+H$48+K$48+N$48+Q$48+T$48+W$48))*W$54,X11-((X11/X$48)*W$52)+(X11/X$48)*W$53+Z11+((C11+E11+H11+K11+N11+Q11+T11+W11)/(C$48+E$48+H$48+K$48+N$48+Q$48+T$48+W$48))*W$54) -> 129864.82 | AB11: =(AA11/AA$48)*Z$53 -> 0 | AC11: =epargne_mensuelle!N11 -> 0 | AD11: =IF(AA$48=0,AA11+AC11+((C11+E11+H11+K11+N11+Q11+T11+W11+Z11)/(C$48+E$48+H$48+K$48+N$48+Q$48+T$48+W$48+Z$48))*Z$54,AA11-((AA11/AA$48)*Z$52)+(AA11/AA$48)*Z$53+AC11+((C11+E11+H11+K11+N11+Q11+T11+W11+Z11)/(C$48+E$48+H$48+K$48+N$48+Q$48+T$48+W$48+Z$48))*Z$54) -> 129864.82 | AE11: =(AD11/AD$48)*AC$53 -> 0 | AF11: =epargne_mensuelle!O11 -> 0 | AG11: =IF(AD$48=0,AD11+AF11+((C11+E11+H11+K11+N11+Q11+T11+W11+Z11+AC11)/(C$48+E$48+H$48+K$48+N$48+Q$48+T$48+W$48+Z$48+AC$48))*AC$54,AD11-((AD11/AD$48)*AC$52)+(AD11/AD$48)*AC$53+AF11+((C11+E11+H11+K11+N11+Q11+T11+W11+Z11+AC11)/(C$48+E$48+H$48+K$48+N$48+Q$48+T$48+W$48+Z$48+AC$48))*AC$54) -> 129864.82 | AH11: =(AG11/AG$48)*AF$53 -> 0 | AI11: =epargne_mensuelle!P11 -> 0 | AJ11: =IF(AG$48=0,AG11+AI11+((C11+E11+H11+K11+N11+Q11+T11+W11+Z11+AC11+AF11)/(C$48+E$48+H$48+K$48+N$48+Q$48+T$48+W$48+Z$48+AC$48+AF$48))*AF$54,AG11-((AG11/AG$48)*AF$52)+(AG11/AG$48)*AF$53+AI11+((C11+E11+H11+K11+N11+Q11+T11+W11+Z11+AC11+AF11)/(C$48+E$48+H$48+K$48+N$48+Q$48+T$48+W$48+Z$48+AC$48+AF$48))*AF$54) -> 129864.82 | AK11: =(AJ11/AJ$48)*AI$53 -> 0 | AL11: =epargne_mensuelle!Q11 -> 0 | AM11: =IF(AJ$48=0,AJ11+AL11+((C11+E11+H11+K11+N11+Q11+T11+W11+Z11+AC11+AF11+AI11)/(C$48+E$48+H$48+K$48+N$48+Q$48+T$48+W$48+Z$48+AC$48+AF$48+AI$48))*AI$54,AJ11-((AJ11/AJ$48)*AI$52)+(AJ11/AJ$48)*AI$53+AL11+((C11+E11+H11+K11+N11+Q11+T11+W11+Z11+AC11+AF11+AI11)/(C$48+E$48+H$48+K$48+N$48+Q$48+T$48+W$48+Z$48+AC$48+AF$48+AI$48))*AI$54) -> 129864.82 | AN11: =(AM11/AM$48)*AL$53 -> 0 | AO11: =epargne_mensuelle!R11 -> 0 | AP11: =IF(AM$48=0,AM11+AO11+((C11+E11+H11+K11+N11+Q11+T11+W11+Z11+AC11+AF11+AI11+AL11)/(C$48+E$48+H$48+K$48+N$48+Q$48+T$48+W$48+Z$48+AC$48+AF$48+AI$48+AL$48))*AL$54,AM11-((AM11/AM$48)*AL$52)+(AM11/AM$48)*AL$53+AO11+((C11+E11+H11+K11+N11+Q11+T11+W11+Z11+AC11+AF11+AI11+AL11)/(C$48+E$48+H$48+K$48+N$48+Q$48+T$48+W$48+Z$48+AC$48+AF$48+AI$48+AL$48))*AL$54) -> 129864.82 | AQ11: =(AP11/AP$48)*AO$53 -> 0 | AR11: =epargne_mensuelle!S11 -> 0 | AS11: =IF(AP$48=0,AP11+AR11+((C11+E11+H11+K11+N11+Q11+T11+W11+Z11+AC11+AF11+AI11+AL11+AO11)/(C$48+E$48+H$48+K$48+N$48+Q$48+T$48+W$48+Z$48+AC$48+AF$48+AI$48+AL$48+AO$48))*AO$54,AP11-((AP11/AP$48)*AO$52)+(AP11/AP$48)*AO$53+AR11+((C11+E11+H11+K11+N11+Q11+T11+W11+Z11+AC11+AF11+AI11+AL11+AO11)/(C$48+E$48+H$48+K$48+N$48+Q$48+T$48+W$48+Z$48+AC$48+AF$48+AI$48+AL$48+AO$48))*AO$54) -> 129864.82 | AT11: =(AS11/AS$48)*AR$53 -> 0 | AU11: =epargne_mensuelle!T11 -> 0 | AV11: =IF(AS$48=0,AS11+AU11+((C11+E11+H11+K11+N11+Q11+T11+W11+Z11+AC11+AF11+AI11+AL11+AO11+AR11)/(C$48+E$48+H$48+K$48+N$48+Q$48+T$48+W$48+Z$48+AC$48+AF$48+AI$48+AL$48+AO$48+AR$48))*AR$54,AS11-((AS11/AS$48)*AR$52)+(AS11/AS$48)*AR$53+AU11+((C11+E11+H11+K11+N11+Q11+T11+W11+Z11+AC11+AF11+AI11+AL11+AO11+AR11)/(C$48+E$48+H$48+K$48+N$48+Q$48+T$48+W$48+Z$48+AC$48+AF$48+AI$48+AL$48+AO$48+AR$48))*AR$54) -> 129864.82 | AW11: =(AV11/AV$48)*AU$53 -> 0 | AX11: =epargne_mensuelle!U11 -> 0 | AY11: =IF(AV$48=0,AV11+AX11+((C11+E11+H11+K11+N11+Q11+T11+W11+Z11+AC11+AF11+AI11+AL11+AO11+AR11+AU11)/(C$48+E$48+H$48+K$48+N$48+Q$48+T$48+W$48+Z$48+AC$48+AF$48+AI$48+AL$48+AO$48+AR$48+AU$48))*AU$54,AV11-((AV11/AV$48)*AU$52)+(AV11/AV$48)*AU$53+AX11+((C11+E11+H11+K11+N11+Q11+T11+W11+Z11+AC11+AF11+AI11+AL11+AO11+AR11+AU11)/(C$48+E$48+H$48+K$48+N$48+Q$48+T$48+W$48+Z$48+AC$48+AF$48+AI$48+AL$48+AO$48+AR$48+AU$48))*AU$54) -> 129864.82 | AZ11: =(AY11/AY$48)*AX$53 -> 0 | BA11: =epargne_mensuelle!V11 -> 0 | BB11: =IF(AY$48=0,AY11+BA11+((C11+E11+H11+K11+N11+Q11+T11+W11+Z11+AC11+AF11+AI11+AL11+AO11+AR11+AU11+AX11)/(C$48+E$48+H$48+K$48+N$48+Q$48+T$48+W$48+Z$48+AC$48+AF$48+AI$48+AL$48+AO$48+AR$48+AU$48+AX$48))*AX$54,AY11-((AY11/AY$48)*AX$52)+(AY11/AY$48)*AX$53+BA11+((C11+E11+H11+K11+N11+Q11+T11+W11+Z11+AC11+AF11+AI11+AL11+AO11+AR11+AU11+AX11)/(C$48+E$48+H$48+K$48+N$48+Q$48+T$48+W$48+Z$48+AC$48+AF$48+AI$48+AL$48+AO$48+AR$48+AU$48+AX$48))*AX$54) -> 129864.82 | BC11: =(BB11/BB$48)*BA$53 -> 0 | BD11: =epargne_mensuelle!W11 -> 0 | BE11: =IF(BB$48=0,BB11+BD11+((C11+E11+H11+K11+N11+Q11+T11+W11+Z11+AC11+AF11+AI11+AL11+AO11+AR11+AU11+AX11+BA11)/(C$48+E$48+H$48+K$48+N$48+Q$48+T$48+W$48+Z$48+AC$48+AF$48+AI$48+AL$48+AO$48+AR$48+AU$48+AX$48+BA$48))*BA$54,BB11-((BB11/BB$48)*BA$52)+(BB11/BB$48)*BA$53+BD11+((C11+E11+H11+K11+N11+Q11+T11+W11+Z11+AC11+AF11+AI11+AL11+AO11+AR11+AU11+AX11+BA11)/(C$48+E$48+H$48+K$48+N$48+Q$48+T$48+W$48+Z$48+AC$48+AF$48+AI$48+AL$48+AO$48+AR$48+AU$48+AX$48+BA$48))*BA$54) -> 129864.82 | BF11: =(BE11/BE$48)*BD$53 -> 0 | BG11: =epargne_mensuelle!X11 -> 0 | BH11: =IF(BE$48=0,BE11+BG11+((C11+E11+H11+K11+N11+Q11+T11+W11+Z11+AC11+AF11+AI11+AL11+AO11+AR11+AU11+AX11+BA11+BD11)/(C$48+E$48+H$48+K$48+N$48+Q$48+T$48+W$48+Z$48+AC$48+AF$48+AI$48+AL$48+AO$48+AR$48+AU$48+AX$48+BA$48+BD$48))*BD$54,BE11-((BE11/BE$48)*BD$52)+(BE11/BE$48)*BD$53+BG11+((C11+E11+H11+K11+N11+Q11+T11+W11+Z11+AC11+AF11+AI11+AL11+AO11+AR11+AU11+AX11+BA11+BD11)/(C$48+E$48+H$48+K$48+N$48+Q$48+T$48+W$48+Z$48+AC$48+AF$48+AI$48+AL$48+AO$48+AR$48+AU$48+AX$48+BA$48+BD$48))*BD$54) -> 129864.82 | BI11: =(BH11/BH$48)*BG$53 -> 0 | BJ11: =epargne_mensuelle!Y11 -> 0 | BK11: =IF(BH$48=0,BH11+BJ11+((C11+E11+H11+K11+N11+Q11+T11+W11+Z11+AC11+AF11+AI11+AL11+AO11+AR11+AU11+AX11+BA11+BD11+BG11)/(C$48+E$48+H$48+K$48+N$48+Q$48+T$48+W$48+Z$48+AC$48+AF$48+AI$48+AL$48+AO$48+AR$48+AU$48+AX$48+BA$48+BD$48+BG$48))*BG$54,BH11-((BH11/BH$48)*BG$52)+(BH11/BH$48)*BG$53+BJ11+((C11+E11+H11+K11+N11+Q11+T11+W11+Z11+AC11+AF11+AI11+AL11+AO11+AR11+AU11+AX11+BA11+BD11+BG11)/(C$48+E$48+H$48+K$48+N$48+Q$48+T$48+W$48+Z$48+AC$48+AF$48+AI$48+AL$48+AO$48+AR$48+AU$48+AX$48+BA$48+BD$48+BG$48))*BG$54) -> 129864.82 | BL11: =(BK11/BK$48)*BJ$53 -> 0 | BM11: =epargne_mensuelle!Z11 -> 0 | BN11: =IF(BK$48=0,BK11+BM11+((C11+E11+H11+K11+N11+Q11+T11+W11+Z11+AC11+AF11+AI11+AL11+AO11+AR11+AU11+AX11+BA11+BD11+BG11+BJ11)/(C$48+E$48+H$48+K$48+N$48+Q$48+T$48+W$48+Z$48+AC$48+AF$48+AI$48+AL$48+AO$48+AR$48+AU$48+AX$48+BA$48+BD$48+BG$48+BJ$48))*BJ$54,BK11-((BK11/BK$48)*BJ$52)+(BK11/BK$48)*BJ$53+BM11+((C11+E11+H11+K11+N11+Q11+T11+W11+Z11+AC11+AF11+AI11+AL11+AO11+AR11+AU11+AX11+BA11+BD11+BG11+BJ11)/(C$48+E$48+H$48+K$48+N$48+Q$48+T$48+W$48+Z$48+AC$48+AF$48+AI$48+AL$48+AO$48+AR$48+AU$48+AX$48+BA$48+BD$48+BG$48+BJ$48))*BJ$54) -> 129864.82 | BO11: =(BN11/BN$48)*BM$53 -> 0 | BP11: =epargne_mensuelle!AA11 -> 0 | BQ11: =IF(BN$48=0,BN11+BP11+((F11+H11+K11+N11+Q11+T11+W11+Z11+AC11+AF11+AI11+AL11+AO11+AR11+AU11+AX11+BA11+BD11+BG11+BJ11+BM11)/(F$48+H$48+K$48+N$48+Q$48+T$48+W$48+Z$48+AC$48+AF$48+AI$48+AL$48+AO$48+AR$48+AU$48+AX$48+BA$48+BD$48+BG$48+BJ$48+BM$48))*BM$54,BN11-((BN11/BN$48)*BM$52)+(BN11/BN$48)*BM$53+BP11+((F11+H11+K11+N11+Q11+T11+W11+Z11+AC11+AF11+AI11+AL11+AO11+AR11+AU11+AX11+BA11+BD11+BG11+BJ11+BM11)/(F$48+H$48+K$48+N$48+Q$48+T$48+W$48+Z$48+AC$48+AF$48+AI$48+AL$48+AO$48+AR$48+AU$48+AX$48+BA$48+BD$48+BG$48+BJ$48+BM$48))*BM$54) -> 129864.82 | BR11: =(BQ11/BQ$48)*BP$53 -> 0 | BS11: =epargne_mensuelle!AB11 -> 0 | BT11: =IF(BQ$48=0,BQ11+BS11+((I11+K11+N11+Q11+T11+W11+Z11+AC11+AF11+AI11+AL11+AO11+AR11+AU11+AX11+BA11+BD11+BG11+BJ11+BM11+BP11)/(I$48+K$48+N$48+Q$48+T$48+W$48+Z$48+AC$48+AF$48+AI$48+AL$48+AO$48+AR$48+AU$48+AX$48+BA$48+BD$48+BG$48+BJ$48+BM$48+BP$48))*BP$54,BQ11-((BQ11/BQ$48)*BP$52)+(BQ11/BQ$48)*BP$53+BS11+((I11+K11+N11+Q11+T11+W11+Z11+AC11+AF11+AI11+AL11+AO11+AR11+AU11+AX11+BA11+BD11+BG11+BJ11+BM11+BP11)/(I$48+K$48+N$48+Q$48+T$48+W$48+Z$48+AC$48+AF$48+AI$48+AL$48+AO$48+AR$48+AU$48+AX$48+BA$48+BD$48+BG$48+BJ$48+BM$48+BP$48))*BP$54) -> 129864.82 | BU11: =(BT11/BT$48)*BS$53 -> 0 | BV11: =cumul_epargne!C11 -> 502772.09 | BW11: =D11+G11+J11+M11+P11+S11+V11+Y11+AB11+AE11+AH11+AK11+AN11+AQ11+AT11+AW11+AZ11+BC11+BF11+BI11+BL11+BO11+BR11+BU11 -> 83098.247 | BX11: =IF(BV11="",BW11,BV11+BW11) -> 585870.34 | BZ11: =BX11+BY11 -> 585870.34 | CA11: =IF(BV11="","",BW11/BV11) -> 0.16528015 | CB11: =BZ11/BZ$48 -> 0.012914076 | CC11: =CB11*(C$50-BW$58-BW$57) -> 55902.49 | CD11: =B11 -> ACTIONNIRE10
A12: =epargne_mensuelle!A12 -> 11 | B12: =epargne_mensuelle!B12 -> ACTIONNIRE11 | C12: =SUM(epargne_mensuelle!C12:E12) -> 1066673.4 | D12: =(C12/C$48)*C$53 -> 134827.68 | E12: =epargne_mensuelle!F12 -> 20000 | F12: =C12-(C12/C$48)*C$52+(C12/C$48)*C$53+E12+(C12/C$48)*C$54 -> 179693.23 | G12: =(F12/F$48)*E$53 -> 0 | H12: =epargne_mensuelle!G12 -> 0 | I12: =IF(F$48=0,F12+H12+((C12+E12)/(C$48+E$48))*E$54,F12-((F12/F$48)*E$52)+(F12/F$48)*E$53+H12+((C12+E12)/(C$48+E$48))*E$54) -> 202361.11 | J12: =(I12/I$48)*H$53 -> 19226.925 | K12: =epargne_mensuelle!H12 -> 0 | L12: =IF(I$48=0,I12+K12+((C12+E12+H12)/(C$48+E$48+H$48))*H$54,I12-((I12/I$48)*H$52)+(I12/I$48)*H$53+K12+((C12+E12+H12)/(C$48+E$48+H$48))*H$54) -> 163550.17 | M12: =(L12/L$48)*K$53 -> 6328.8821 | N12: =epargne_mensuelle!I12 -> 0 | O12: =IF(L$48=0,L12+N12+((C12+E12+H12+K12)/(C$48+E$48+H$48+K$48))*K$54,L12-((L12/L$48)*K$52)+(L12/L$48)*K$53+N12+((C12+E12+H12+K12)/(C$48+E$48+H$48+K$48))*K$54) -> 140577.74 | P12: =(O12/O$48)*N$53 -> 2222.6422 | Q12: =epargne_mensuelle!J12 -> 0 | R12: =IF(O$48=0,O12+Q12+((C12+E12+H12+K12+N12)/(C$48+E$48+H$48+K$48+N$48))*N$54,O12-((O12/O$48)*N$52)+(O12/O$48)*N$53+Q12+((C12+E12+H12+K12+N12)/(C$48+E$48+H$48+K$48+N$48))*N$54) -> 215382.93 | S12: =(R12/R$48)*Q$53 -> 17898.232 | T12: =epargne_mensuelle!K12 -> 0 | U12: =IF(R$48=0,R12+T12+((C12+E12+H12+K12+N12+Q12)/(C$48+E$48+H$48+K$48+N$48+Q$48))*Q$54,R12-((R12/R$48)*Q$52)+(R12/R$48)*Q$53+T12+((C12+E12+H12+K12+N12+Q12)/(C$48+E$48+H$48+K$48+N$48+Q$48))*Q$54) -> 278847.99 | V12: =(U12/U$48)*T$53 -> 0 | W12: =epargne_mensuelle!L12 -> 0 | X12: =IF(U$48=0,U12+W12+((C12+E12+H12+K12+N12+Q12+T12)/(C$48+E$48+H$48+K$48+N$48+Q$48+T$48))*T$54,U12-((U12/U$48)*T$52)+(U12/U$48)*T$53+W12+((C12+E12+H12+K12+N12+Q12+T12)/(C$48+E$48+H$48+K$48+N$48+Q$48+T$48))*T$54) -> 278847.99 | Y12: =(X12/X$48)*W$53 -> 0 | Z12: =epargne_mensuelle!M12 -> 0 | AA12: =IF(X$48=0,X12+Z12+((C12+E12+H12+K12+N12+Q12+T12+W12)/(C$48+E$48+H$48+K$48+N$48+Q$48+T$48+W$48))*W$54,X12-((X12/X$48)*W$52)+(X12/X$48)*W$53+Z12+((C12+E12+H12+K12+N12+Q12+T12+W12)/(C$48+E$48+H$48+K$48+N$48+Q$48+T$48+W$48))*W$54) -> 278847.99 | AB12: =(AA12/AA$48)*Z$53 -> 0 | AC12: =epargne_mensuelle!N12 -> 0 | AD12: =IF(AA$48=0,AA12+AC12+((C12+E12+H12+K12+N12+Q12+T12+W12+Z12)/(C$48+E$48+H$48+K$48+N$48+Q$48+T$48+W$48+Z$48))*Z$54,AA12-((AA12/AA$48)*Z$52)+(AA12/AA$48)*Z$53+AC12+((C12+E12+H12+K12+N12+Q12+T12+W12+Z12)/(C$48+E$48+H$48+K$48+N$48+Q$48+T$48+W$48+Z$48))*Z$54) -> 278847.99 | AE12: =(AD12/AD$48)*AC$53 -> 0 | AF12: =epargne_mensuelle!O12 -> 0 | AG12: =IF(AD$48=0,AD12+AF12+((C12+E12+H12+K12+N12+Q12+T12+W12+Z12+AC12)/(C$48+E$48+H$48+K$48+N$48+Q$48+T$48+W$48+Z$48+AC$48))*AC$54,AD12-((AD12/AD$48)*AC$52)+(AD12/AD$48)*AC$53+AF12+((C12+E12+H12+K12+N12+Q12+T12+W12+Z12+AC12)/(C$48+E$48+H$48+K$48+N$48+Q$48+T$48+W$48+Z$48+AC$48))*AC$54) -> 278847.99 | AH12: =(AG12/AG$48)*AF$53 -> 0 | AI12: =epargne_mensuelle!P12 -> 0 | AJ12: =IF(AG$48=0,AG12+AI12+((C12+E12+H12+K12+N12+Q12+T12+W12+Z12+AC12+AF12)/(C$48+E$48+H$48+K$48+N$48+Q$48+T$48+W$48+Z$48+AC$48+AF$48))*AF$54,AG12-((AG12/AG$48)*AF$52)+(AG12/AG$48)*AF$53+AI12+((C12+E12+H12+K12+N12+Q12+T12+W12+Z12+AC12+AF12)/(C$48+E$48+H$48+K$48+N$48+Q$48+T$48+W$48+Z$48+AC$48+AF$48))*AF$54) -> 278847.99 | AK12: =(AJ12/AJ$48)*AI$53 -> 0 | AL12: =epargne_mensuelle!Q12 -> 0 | AM12: =IF(AJ$48=0,AJ12+AL12+((C12+E12+H12+K12+N12+Q12+T12+W12+Z12+AC12+AF12+AI12)/(C$48+E$48+H$48+K$48+N$48+Q$48+T$48+W$48+Z$48+AC$48+AF$48+AI$48))*AI$54,AJ12-((AJ12/AJ$48)*AI$52)+(AJ12/AJ$48)*AI$53+AL12+((C12+E12+H12+K12+N12+Q12+T12+W12+Z12+AC12+AF12+AI12)/(C$48+E$48+H$48+K$48+N$48+Q$48+T$48+W$48+Z$48+AC$48+AF$48+AI$48))*AI$54) -> 278847.99 | AN12: =(AM12/AM$48)*AL$53 -> 0 | AO12: =epargne_mensuelle!R12 -> 0 | AP12: =IF(AM$48=0,AM12+AO12+((C12+E12+H12+K12+N12+Q12+T12+W12+Z12+AC12+AF12+AI12+AL12)/(C$48+E$48+H$48+K$48+N$48+Q$48+T$48+W$48+Z$48+AC$48+AF$48+AI$48+AL$48))*AL$54,AM12-((AM12/AM$48)*AL$52)+(AM12/AM$48)*AL$53+AO12+((C12+E12+H12+K12+N12+Q12+T12+W12+Z12+AC12+AF12+AI12+AL12)/(C$48+E$48+H$48+K$48+N$48+Q$48+T$48+W$48+Z$48+AC$48+AF$48+AI$48+AL$48))*AL$54) -> 278847.99 | AQ12: =(AP12/AP$48)*AO$53 -> 0 | AR12: =epargne_mensuelle!S12 -> 0 | AS12: =IF(AP$48=0,AP12+AR12+((C12+E12+H12+K12+N12+Q12+T12+W12+Z12+AC12+AF12+AI12+AL12+AO12)/(C$48+E$48+H$48+K$48+N$48+Q$48+T$48+W$48+Z$48+AC$48+AF$48+AI$48+AL$48+AO$48))*AO$54,AP12-((AP12/AP$48)*AO$52)+(AP12/AP$48)*AO$53+AR12+((C12+E12+H12+K12+N12+Q12+T12+W12+Z12+AC12+AF12+AI12+AL12+AO12)/(C$48+E$48+H$48+K$48+N$48+Q$48+T$48+W$48+Z$48+AC$48+AF$48+AI$48+AL$48+AO$48))*AO$54) -> 278847.99 | AT12: =(AS12/AS$48)*AR$53 -> 0 | AU12: =epargne_mensuelle!T12 -> 0 | AV12: =IF(AS$48=0,AS12+AU12+((C12+E12+H12+K12+N12+Q12+T12+W12+Z12+AC12+AF12+AI12+AL12+AO12+AR12)/(C$48+E$48+H$48+K$48+N$48+Q$48+T$48+W$48+Z$48+AC$48+AF$48+AI$48+AL$48+AO$48+AR$48))*AR$54,AS12-((AS12/AS$48)*AR$52)+(AS12/AS$48)*AR$53+AU12+((C12+E12+H12+K12+N12+Q12+T12+W12+Z12+AC12+AF12+AI12+AL12+AO12+AR12)/(C$48+E$48+H$48+K$48+N$48+Q$48+T$48+W$48+Z$48+AC$48+AF$48+AI$48+AL$48+AO$48+AR$48))*AR$54) -> 278847.99 | AW12: =(AV12/AV$48)*AU$53 -> 0 | AX12: =epargne_mensuelle!U12 -> 0 | AY12: =IF(AV$48=0,AV12+AX12+((C12+E12+H12+K12+N12+Q12+T12+W12+Z12+AC12+AF12+AI12+AL12+AO12+AR12+AU12)/(C$48+E$48+H$48+K$48+N$48+Q$48+T$48+W$48+Z$48+AC$48+AF$48+AI$48+AL$48+AO$48+AR$48+AU$48))*AU$54,AV12-((AV12/AV$48)*AU$52)+(AV12/AV$48)*AU$53+AX12+((C12+E12+H12+K12+N12+Q12+T12+W12+Z12+AC12+AF12+AI12+AL12+AO12+AR12+AU12)/(C$48+E$48+H$48+K$48+N$48+Q$48+T$48+W$48+Z$48+AC$48+AF$48+AI$48+AL$48+AO$48+AR$48+AU$48))*AU$54) -> 278847.99 | AZ12: =(AY12/AY$48)*AX$53 -> 0 | BA12: =epargne_mensuelle!V12 -> 0 | BB12: =IF(AY$48=0,AY12+BA12+((C12+E12+H12+K12+N12+Q12+T12+W12+Z12+AC12+AF12+AI12+AL12+AO12+AR12+AU12+AX12)/(C$48+E$48+H$48+K$48+N$48+Q$48+T$48+W$48+Z$48+AC$48+AF$48+AI$48+AL$48+AO$48+AR$48+AU$48+AX$48))*AX$54,AY12-((AY12/AY$48)*AX$52)+(AY12/AY$48)*AX$53+BA12+((C12+E12+H12+K12+N12+Q12+T12+W12+Z12+AC12+AF12+AI12+AL12+AO12+AR12+AU12+AX12)/(C$48+E$48+H$48+K$48+N$48+Q$48+T$48+W$48+Z$48+AC$48+AF$48+AI$48+AL$48+AO$48+AR$48+AU$48+AX$48))*AX$54) -> 278847.99 | BC12: =(BB12/BB$48)*BA$53 -> 0 | BD12: =epargne_mensuelle!W12 -> 0 | BE12: =IF(BB$48=0,BB12+BD12+((C12+E12+H12+K12+N12+Q12+T12+W12+Z12+AC12+AF12+AI12+AL12+AO12+AR12+AU12+AX12+BA12)/(C$48+E$48+H$48+K$48+N$48+Q$48+T$48+W$48+Z$48+AC$48+AF$48+AI$48+AL$48+AO$48+AR$48+AU$48+AX$48+BA$48))*BA$54,BB12-((BB12/BB$48)*BA$52)+(BB12/BB$48)*BA$53+BD12+((C12+E12+H12+K12+N12+Q12+T12+W12+Z12+AC12+AF12+AI12+AL12+AO12+AR12+AU12+AX12+BA12)/(C$48+E$48+H$48+K$48+N$48+Q$48+T$48+W$48+Z$48+AC$48+AF$48+AI$48+AL$48+AO$48+AR$48+AU$48+AX$48+BA$48))*BA$54) -> 278847.99 | BF12: =(BE12/BE$48)*BD$53 -> 0 | BG12: =epargne_mensuelle!X12 -> 0 | BH12: =IF(BE$48=0,BE12+BG12+((C12+E12+H12+K12+N12+Q12+T12+W12+Z12+AC12+AF12+AI12+AL12+AO12+AR12+AU12+AX12+BA12+BD12)/(C$48+E$48+H$48+K$48+N$48+Q$48+T$48+W$48+Z$48+AC$48+AF$48+AI$48+AL$48+AO$48+AR$48+AU$48+AX$48+BA$48+BD$48))*BD$54,BE12-((BE12/BE$48)*BD$52)+(BE12/BE$48)*BD$53+BG12+((C12+E12+H12+K12+N12+Q12+T12+W12+Z12+AC12+AF12+AI12+AL12+AO12+AR12+AU12+AX12+BA12+BD12)/(C$48+E$48+H$48+K$48+N$48+Q$48+T$48+W$48+Z$48+AC$48+AF$48+AI$48+AL$48+AO$48+AR$48+AU$48+AX$48+BA$48+BD$48))*BD$54) -> 278847.99 | BI12: =(BH12/BH$48)*BG$53 -> 0 | BJ12: =epargne_mensuelle!Y12 -> 0 | BK12: =IF(BH$48=0,BH12+BJ12+((C12+E12+H12+K12+N12+Q12+T12+W12+Z12+AC12+AF12+AI12+AL12+AO12+AR12+AU12+AX12+BA12+BD12+BG12)/(C$48+E$48+H$48+K$48+N$48+Q$48+T$48+W$48+Z$48+AC$48+AF$48+AI$48+AL$48+AO$48+AR$48+AU$48+AX$48+BA$48+BD$48+BG$48))*BG$54,BH12-((BH12/BH$48)*BG$52)+(BH12/BH$48)*BG$53+BJ12+((C12+E12+H12+K12+N12+Q12+T12+W12+Z12+AC12+AF12+AI12+AL12+AO12+AR12+AU12+AX12+BA12+BD12+BG12)/(C$48+E$48+H$48+K$48+N$48+Q$48+T$48+W$48+Z$48+AC$48+AF$48+AI$48+AL$48+AO$48+AR$48+AU$48+AX$48+BA$48+BD$48+BG$48))*BG$54) -> 278847.99 | BL12: =(BK12/BK$48)*BJ$53 -> 0 | BM12: =epargne_mensuelle!Z12 -> 0 | BN12: =IF(BK$48=0,BK12+BM12+((C12+E12+H12+K12+N12+Q12+T12+W12+Z12+AC12+AF12+AI12+AL12+AO12+AR12+AU12+AX12+BA12+BD12+BG12+BJ12)/(C$48+E$48+H$48+K$48+N$48+Q$48+T$48+W$48+Z$48+AC$48+AF$48+AI$48+AL$48+AO$48+AR$48+AU$48+AX$48+BA$48+BD$48+BG$48+BJ$48))*BJ$54,BK12-((BK12/BK$48)*BJ$52)+(BK12/BK$48)*BJ$53+BM12+((C12+E12+H12+K12+N12+Q12+T12+W12+Z12+AC12+AF12+AI12+AL12+AO12+AR12+AU12+AX12+BA12+BD12+BG12+BJ12)/(C$48+E$48+H$48+K$48+N$48+Q$48+T$48+W$48+Z$48+AC$48+AF$48+AI$48+AL$48+AO$48+AR$48+AU$48+AX$48+BA$48+BD$48+BG$48+BJ$48))*BJ$54) -> 278847.99 | BO12: =(BN12/BN$48)*BM$53 -> 0 | BP12: =epargne_mensuelle!AA12 -> 0 | BQ12: =IF(BN$48=0,BN12+BP12+((F12+H12+K12+N12+Q12+T12+W12+Z12+AC12+AF12+AI12+AL12+AO12+AR12+AU12+AX12+BA12+BD12+BG12+BJ12+BM12)/(F$48+H$48+K$48+N$48+Q$48+T$48+W$48+Z$48+AC$48+AF$48+AI$48+AL$48+AO$48+AR$48+AU$48+AX$48+BA$48+BD$48+BG$48+BJ$48+BM$48))*BM$54,BN12-((BN12/BN$48)*BM$52)+(BN12/BN$48)*BM$53+BP12+((F12+H12+K12+N12+Q12+T12+W12+Z12+AC12+AF12+AI12+AL12+AO12+AR12+AU12+AX12+BA12+BD12+BG12+BJ12+BM12)/(F$48+H$48+K$48+N$48+Q$48+T$48+W$48+Z$48+AC$48+AF$48+AI$48+AL$48+AO$48+AR$48+AU$48+AX$48+BA$48+BD$48+BG$48+BJ$48+BM$48))*BM$54) -> 278847.99 | BR12: =(BQ12/BQ$48)*BP$53 -> 0 | BS12: =epargne_mensuelle!AB12 -> 0 | BT12: =IF(BQ$48=0,BQ12+BS12+((I12+K12+N12+Q12+T12+W12+Z12+AC12+AF12+AI12+AL12+AO12+AR12+AU12+AX12+BA12+BD12+BG12+BJ12+BM12+BP12)/(I$48+K$48+N$48+Q$48+T$48+W$48+Z$48+AC$48+AF$48+AI$48+AL$48+AO$48+AR$48+AU$48+AX$48+BA$48+BD$48+BG$48+BJ$48+BM$48+BP$48))*BP$54,BQ12-((BQ12/BQ$48)*BP$52)+(BQ12/BQ$48)*BP$53+BS12+((I12+K12+N12+Q12+T12+W12+Z12+AC12+AF12+AI12+AL12+AO12+AR12+AU12+AX12+BA12+BD12+BG12+BJ12+BM12+BP12)/(I$48+K$48+N$48+Q$48+T$48+W$48+Z$48+AC$48+AF$48+AI$48+AL$48+AO$48+AR$48+AU$48+AX$48+BA$48+BD$48+BG$48+BJ$48+BM$48+BP$48))*BP$54) -> 278847.99 | BU12: =(BT12/BT$48)*BS$53 -> 0 | BV12: =cumul_epargne!C12 -> 1086673.4 | BW12: =D12+G12+J12+M12+P12+S12+V12+Y12+AB12+AE12+AH12+AK12+AN12+AQ12+AT12+AW12+AZ12+BC12+BF12+BI12+BL12+BO12+BR12+BU12 -> 180504.36 | BX12: =IF(BV12="",BW12,BV12+BW12) -> 1267177.8 | BZ12: =BX12+BY12 -> 1267177.8 | CA12: =IF(BV12="","",BW12/BV12) -> 0.16610727 | CB12: =BZ12/BZ$48 -> 0.027931829 | CC12: =CB12*(C$50-BW$58-BW$57) -> 120911.39 | CD12: =B12 -> ACTIONNIRE11
A13: =epargne_mensuelle!A13 -> 12 | B13: =epargne_mensuelle!B13 -> ACTIONNIRE12 | C13: =SUM(epargne_mensuelle!C13:E13) -> 472273.11 | D13: =(C13/C$48)*C$53 -> 59695.391 | E13: =epargne_mensuelle!F13 -> 0 | F13: =C13-(C13/C$48)*C$52+(C13/C$48)*C$53+E13+(C13/C$48)*C$54 -> 70704.693 | G13: =(F13/F$48)*E$53 -> 0 | H13: =epargne_mensuelle!G13 -> 0 | I13: =IF(F$48=0,F13+H13+((C13+E13)/(C$48+E$48))*E$54,F13-((F13/F$48)*E$52)+(F13/F$48)*E$53+H13+((C13+E13)/(C$48+E$48))*E$54) -> 80556.254 | J13: =(I13/I$48)*H$53 -> 7653.8869 | K13: =epargne_mensuelle!H13 -> 0 | L13: =IF(I$48=0,I13+K13+((C13+E13+H13)/(C$48+E$48+H$48))*H$54,I13-((I13/I$48)*H$52)+(I13/I$48)*H$53+K13+((C13+E13+H13)/(C$48+E$48+H$48))*H$54) -> 68553.005 | M13: =(L13/L$48)*K$53 -> 2652.7878 | N13: =epargne_mensuelle!I13 -> 0 | O13: =IF(L$48=0,L13+N13+((C13+E13+H13+K13)/(C$48+E$48+H$48+K$48))*K$54,L13-((L13/L$48)*K$52)+(L13/L$48)*K$53+N13+((C13+E13+H13+K13)/(C$48+E$48+H$48+K$48))*K$54) -> 60069.584 | P13: =(O13/O$48)*N$53 -> 949.74633 | Q13: =epargne_mensuelle!J13 -> 0 | R13: =IF(O$48=0,O13+Q13+((C13+E13+H13+K13+N13)/(C$48+E$48+H$48+K$48+N$48))*N$54,O13-((O13/O$48)*N$52)+(O13/O$48)*N$53+Q13+((C13+E13+H13+K13+N13)/(C$48+E$48+H$48+K$48+N$48))*N$54) -> 92969.624 | S13: =(R13/R$48)*Q$53 -> 7725.7374 | T13: =epargne_mensuelle!K13 -> 0 | U13: =IF(R$48=0,R13+T13+((C13+E13+H13+K13+N13+Q13)/(C$48+E$48+H$48+K$48+N$48+Q$48))*Q$54,R13-((R13/R$48)*Q$52)+(R13/R$48)*Q$53+T13+((C13+E13+H13+K13+N13+Q13)/(C$48+E$48+H$48+K$48+N$48+Q$48))*Q$54) -> 120719.38 | V13: =(U13/U$48)*T$53 -> 0 | W13: =epargne_mensuelle!L13 -> 0 | X13: =IF(U$48=0,U13+W13+((C13+E13+H13+K13+N13+Q13+T13)/(C$48+E$48+H$48+K$48+N$48+Q$48+T$48))*T$54,U13-((U13/U$48)*T$52)+(U13/U$48)*T$53+W13+((C13+E13+H13+K13+N13+Q13+T13)/(C$48+E$48+H$48+K$48+N$48+Q$48+T$48))*T$54) -> 120719.38 | Y13: =(X13/X$48)*W$53 -> 0 | Z13: =epargne_mensuelle!M13 -> 0 | AA13: =IF(X$48=0,X13+Z13+((C13+E13+H13+K13+N13+Q13+T13+W13)/(C$48+E$48+H$48+K$48+N$48+Q$48+T$48+W$48))*W$54,X13-((X13/X$48)*W$52)+(X13/X$48)*W$53+Z13+((C13+E13+H13+K13+N13+Q13+T13+W13)/(C$48+E$48+H$48+K$48+N$48+Q$48+T$48+W$48))*W$54) -> 120719.38 | AB13: =(AA13/AA$48)*Z$53 -> 0 | AC13: =epargne_mensuelle!N13 -> 0 | AD13: =IF(AA$48=0,AA13+AC13+((C13+E13+H13+K13+N13+Q13+T13+W13+Z13)/(C$48+E$48+H$48+K$48+N$48+Q$48+T$48+W$48+Z$48))*Z$54,AA13-((AA13/AA$48)*Z$52)+(AA13/AA$48)*Z$53+AC13+((C13+E13+H13+K13+N13+Q13+T13+W13+Z13)/(C$48+E$48+H$48+K$48+N$48+Q$48+T$48+W$48+Z$48))*Z$54) -> 120719.38 | AE13: =(AD13/AD$48)*AC$53 -> 0 | AF13: =epargne_mensuelle!O13 -> 0 | AG13: =IF(AD$48=0,AD13+AF13+((C13+E13+H13+K13+N13+Q13+T13+W13+Z13+AC13)/(C$48+E$48+H$48+K$48+N$48+Q$48+T$48+W$48+Z$48+AC$48))*AC$54,AD13-((AD13/AD$48)*AC$52)+(AD13/AD$48)*AC$53+AF13+((C13+E13+H13+K13+N13+Q13+T13+W13+Z13+AC13)/(C$48+E$48+H$48+K$48+N$48+Q$48+T$48+W$48+Z$48+AC$48))*AC$54) -> 120719.38 | AH13: =(AG13/AG$48)*AF$53 -> 0 | AI13: =epargne_mensuelle!P13 -> 0 | AJ13: =IF(AG$48=0,AG13+AI13+((C13+E13+H13+K13+N13+Q13+T13+W13+Z13+AC13+AF13)/(C$48+E$48+H$48+K$48+N$48+Q$48+T$48+W$48+Z$48+AC$48+AF$48))*AF$54,AG13-((AG13/AG$48)*AF$52)+(AG13/AG$48)*AF$53+AI13+((C13+E13+H13+K13+N13+Q13+T13+W13+Z13+AC13+AF13)/(C$48+E$48+H$48+K$48+N$48+Q$48+T$48+W$48+Z$48+AC$48+AF$48))*AF$54) -> 120719.38 | AK13: =(AJ13/AJ$48)*AI$53 -> 0 | AL13: =epargne_mensuelle!Q13 -> 0 | AM13: =IF(AJ$48=0,AJ13+AL13+((C13+E13+H13+K13+N13+Q13+T13+W13+Z13+AC13+AF13+AI13)/(C$48+E$48+H$48+K$48+N$48+Q$48+T$48+W$48+Z$48+AC$48+AF$48+AI$48))*AI$54,AJ13-((AJ13/AJ$48)*AI$52)+(AJ13/AJ$48)*AI$53+AL13+((C13+E13+H13+K13+N13+Q13+T13+W13+Z13+AC13+AF13+AI13)/(C$48+E$48+H$48+K$48+N$48+Q$48+T$48+W$48+Z$48+AC$48+AF$48+AI$48))*AI$54) -> 120719.38 | AN13: =(AM13/AM$48)*AL$53 -> 0 | AO13: =epargne_mensuelle!R13 -> 0 | AP13: =IF(AM$48=0,AM13+AO13+((C13+E13+H13+K13+N13+Q13+T13+W13+Z13+AC13+AF13+AI13+AL13)/(C$48+E$48+H$48+K$48+N$48+Q$48+T$48+W$48+Z$48+AC$48+AF$48+AI$48+AL$48))*AL$54,AM13-((AM13/AM$48)*AL$52)+(AM13/AM$48)*AL$53+AO13+((C13+E13+H13+K13+N13+Q13+T13+W13+Z13+AC13+AF13+AI13+AL13)/(C$48+E$48+H$48+K$48+N$48+Q$48+T$48+W$48+Z$48+AC$48+AF$48+AI$48+AL$48))*AL$54) -> 120719.38 | AQ13: =(AP13/AP$48)*AO$53 -> 0 | AR13: =epargne_mensuelle!S13 -> 0 | AS13: =IF(AP$48=0,AP13+AR13+((C13+E13+H13+K13+N13+Q13+T13+W13+Z13+AC13+AF13+AI13+AL13+AO13)/(C$48+E$48+H$48+K$48+N$48+Q$48+T$48+W$48+Z$48+AC$48+AF$48+AI$48+AL$48+AO$48))*AO$54,AP13-((AP13/AP$48)*AO$52)+(AP13/AP$48)*AO$53+AR13+((C13+E13+H13+K13+N13+Q13+T13+W13+Z13+AC13+AF13+AI13+AL13+AO13)/(C$48+E$48+H$48+K$48+N$48+Q$48+T$48+W$48+Z$48+AC$48+AF$48+AI$48+AL$48+AO$48))*AO$54) -> 120719.38 | AT13: =(AS13/AS$48)*AR$53 -> 0 | AU13: =epargne_mensuelle!T13 -> 0 | AV13: =IF(AS$48=0,AS13+AU13+((C13+E13+H13+K13+N13+Q13+T13+W13+Z13+AC13+AF13+AI13+AL13+AO13+AR13)/(C$48+E$48+H$48+K$48+N$48+Q$48+T$48+W$48+Z$48+AC$48+AF$48+AI$48+AL$48+AO$48+AR$48))*AR$54,AS13-((AS13/AS$48)*AR$52)+(AS13/AS$48)*AR$53+AU13+((C13+E13+H13+K13+N13+Q13+T13+W13+Z13+AC13+AF13+AI13+AL13+AO13+AR13)/(C$48+E$48+H$48+K$48+N$48+Q$48+T$48+W$48+Z$48+AC$48+AF$48+AI$48+AL$48+AO$48+AR$48))*AR$54) -> 120719.38 | AW13: =(AV13/AV$48)*AU$53 -> 0 | AX13: =epargne_mensuelle!U13 -> 0 | AY13: =IF(AV$48=0,AV13+AX13+((C13+E13+H13+K13+N13+Q13+T13+W13+Z13+AC13+AF13+AI13+AL13+AO13+AR13+AU13)/(C$48+E$48+H$48+K$48+N$48+Q$48+T$48+W$48+Z$48+AC$48+AF$48+AI$48+AL$48+AO$48+AR$48+AU$48))*AU$54,AV13-((AV13/AV$48)*AU$52)+(AV13/AV$48)*AU$53+AX13+((C13+E13+H13+K13+N13+Q13+T13+W13+Z13+AC13+AF13+AI13+AL13+AO13+AR13+AU13)/(C$48+E$48+H$48+K$48+N$48+Q$48+T$48+W$48+Z$48+AC$48+AF$48+AI$48+AL$48+AO$48+AR$48+AU$48))*AU$54) -> 120719.38 | AZ13: =(AY13/AY$48)*AX$53 -> 0 | BA13: =epargne_mensuelle!V13 -> 0 | BB13: =IF(AY$48=0,AY13+BA13+((C13+E13+H13+K13+N13+Q13+T13+W13+Z13+AC13+AF13+AI13+AL13+AO13+AR13+AU13+AX13)/(C$48+E$48+H$48+K$48+N$48+Q$48+T$48+W$48+Z$48+AC$48+AF$48+AI$48+AL$48+AO$48+AR$48+AU$48+AX$48))*AX$54,AY13-((AY13/AY$48)*AX$52)+(AY13/AY$48)*AX$53+BA13+((C13+E13+H13+K13+N13+Q13+T13+W13+Z13+AC13+AF13+AI13+AL13+AO13+AR13+AU13+AX13)/(C$48+E$48+H$48+K$48+N$48+Q$48+T$48+W$48+Z$48+AC$48+AF$48+AI$48+AL$48+AO$48+AR$48+AU$48+AX$48))*AX$54) -> 120719.38 | BC13: =(BB13/BB$48)*BA$53 -> 0 | BD13: =epargne_mensuelle!W13 -> 0 | BE13: =IF(BB$48=0,BB13+BD13+((C13+E13+H13+K13+N13+Q13+T13+W13+Z13+AC13+AF13+AI13+AL13+AO13+AR13+AU13+AX13+BA13)/(C$48+E$48+H$48+K$48+N$48+Q$48+T$48+W$48+Z$48+AC$48+AF$48+AI$48+AL$48+AO$48+AR$48+AU$48+AX$48+BA$48))*BA$54,BB13-((BB13/BB$48)*BA$52)+(BB13/BB$48)*BA$53+BD13+((C13+E13+H13+K13+N13+Q13+T13+W13+Z13+AC13+AF13+AI13+AL13+AO13+AR13+AU13+AX13+BA13)/(C$48+E$48+H$48+K$48+N$48+Q$48+T$48+W$48+Z$48+AC$48+AF$48+AI$48+AL$48+AO$48+AR$48+AU$48+AX$48+BA$48))*BA$54) -> 120719.38 | BF13: =(BE13/BE$48)*BD$53 -> 0 | BG13: =epargne_mensuelle!X13 -> 0 | BH13: =IF(BE$48=0,BE13+BG13+((C13+E13+H13+K13+N13+Q13+T13+W13+Z13+AC13+AF13+AI13+AL13+AO13+AR13+AU13+AX13+BA13+BD13)/(C$48+E$48+H$48+K$48+N$48+Q$48+T$48+W$48+Z$48+AC$48+AF$48+AI$48+AL$48+AO$48+AR$48+AU$48+AX$48+BA$48+BD$48))*BD$54,BE13-((BE13/BE$48)*BD$52)+(BE13/BE$48)*BD$53+BG13+((C13+E13+H13+K13+N13+Q13+T13+W13+Z13+AC13+AF13+AI13+AL13+AO13+AR13+AU13+AX13+BA13+BD13)/(C$48+E$48+H$48+K$48+N$48+Q$48+T$48+W$48+Z$48+AC$48+AF$48+AI$48+AL$48+AO$48+AR$48+AU$48+AX$48+BA$48+BD$48))*BD$54) -> 120719.38 | BI13: =(BH13/BH$48)*BG$53 -> 0 | BJ13: =epargne_mensuelle!Y13 -> 0 | BK13: =IF(BH$48=0,BH13+BJ13+((C13+E13+H13+K13+N13+Q13+T13+W13+Z13+AC13+AF13+AI13+AL13+AO13+AR13+AU13+AX13+BA13+BD13+BG13)/(C$48+E$48+H$48+K$48+N$48+Q$48+T$48+W$48+Z$48+AC$48+AF$48+AI$48+AL$48+AO$48+AR$48+AU$48+AX$48+BA$48+BD$48+BG$48))*BG$54,BH13-((BH13/BH$48)*BG$52)+(BH13/BH$48)*BG$53+BJ13+((C13+E13+H13+K13+N13+Q13+T13+W13+Z13+AC13+AF13+AI13+AL13+AO13+AR13+AU13+AX13+BA13+BD13+BG13)/(C$48+E$48+H$48+K$48+N$48+Q$48+T$48+W$48+Z$48+AC$48+AF$48+AI$48+AL$48+AO$48+AR$48+AU$48+AX$48+BA$48+BD$48+BG$48))*BG$54) -> 120719.38 | BL13: =(BK13/BK$48)*BJ$53 -> 0 | BM13: =epargne_mensuelle!Z13 -> 0 | BN13: =IF(BK$48=0,BK13+BM13+((C13+E13+H13+K13+N13+Q13+T13+W13+Z13+AC13+AF13+AI13+AL13+AO13+AR13+AU13+AX13+BA13+BD13+BG13+BJ13)/(C$48+E$48+H$48+K$48+N$48+Q$48+T$48+W$48+Z$48+AC$48+AF$48+AI$48+AL$48+AO$48+AR$48+AU$48+AX$48+BA$48+BD$48+BG$48+BJ$48))*BJ$54,BK13-((BK13/BK$48)*BJ$52)+(BK13/BK$48)*BJ$53+BM13+((C13+E13+H13+K13+N13+Q13+T13+W13+Z13+AC13+AF13+AI13+AL13+AO13+AR13+AU13+AX13+BA13+BD13+BG13+BJ13)/(C$48+E$48+H$48+K$48+N$48+Q$48+T$48+W$48+Z$48+AC$48+AF$48+AI$48+AL$48+AO$48+AR$48+AU$48+AX$48+BA$48+BD$48+BG$48+BJ$48))*BJ$54) -> 120719.38 | BO13: =(BN13/BN$48)*BM$53 -> 0 | BP13: =epargne_mensuelle!AA13 -> 0 | BQ13: =IF(BN$48=0,BN13+BP13+((F13+H13+K13+N13+Q13+T13+W13+Z13+AC13+AF13+AI13+AL13+AO13+AR13+AU13+AX13+BA13+BD13+BG13+BJ13+BM13)/(F$48+H$48+K$48+N$48+Q$48+T$48+W$48+Z$48+AC$48+AF$48+AI$48+AL$48+AO$48+AR$48+AU$48+AX$48+BA$48+BD$48+BG$48+BJ$48+BM$48))*BM$54,BN13-((BN13/BN$48)*BM$52)+(BN13/BN$48)*BM$53+BP13+((F13+H13+K13+N13+Q13+T13+W13+Z13+AC13+AF13+AI13+AL13+AO13+AR13+AU13+AX13+BA13+BD13+BG13+BJ13+BM13)/(F$48+H$48+K$48+N$48+Q$48+T$48+W$48+Z$48+AC$48+AF$48+AI$48+AL$48+AO$48+AR$48+AU$48+AX$48+BA$48+BD$48+BG$48+BJ$48+BM$48))*BM$54) -> 120719.38 | BR13: =(BQ13/BQ$48)*BP$53 -> 0 | BS13: =epargne_mensuelle!AB13 -> 0 | BT13: =IF(BQ$48=0,BQ13+BS13+((I13+K13+N13+Q13+T13+W13+Z13+AC13+AF13+AI13+AL13+AO13+AR13+AU13+AX13+BA13+BD13+BG13+BJ13+BM13+BP13)/(I$48+K$48+N$48+Q$48+T$48+W$48+Z$48+AC$48+AF$48+AI$48+AL$48+AO$48+AR$48+AU$48+AX$48+BA$48+BD$48+BG$48+BJ$48+BM$48+BP$48))*BP$54,BQ13-((BQ13/BQ$48)*BP$52)+(BQ13/BQ$48)*BP$53+BS13+((I13+K13+N13+Q13+T13+W13+Z13+AC13+AF13+AI13+AL13+AO13+AR13+AU13+AX13+BA13+BD13+BG13+BJ13+BM13+BP13)/(I$48+K$48+N$48+Q$48+T$48+W$48+Z$48+AC$48+AF$48+AI$48+AL$48+AO$48+AR$48+AU$48+AX$48+BA$48+BD$48+BG$48+BJ$48+BM$48+BP$48))*BP$54) -> 120719.38 | BU13: =(BT13/BT$48)*BS$53 -> 0 | BV13: =cumul_epargne!C13 -> 472273.11 | BW13: =D13+G13+J13+M13+P13+S13+V13+Y13+AB13+AE13+AH13+AK13+AN13+AQ13+AT13+AW13+AZ13+BC13+BF13+BI13+BL13+BO13+BR13+BU13 -> 78677.549 | BX13: =IF(BV13="",BW13,BV13+BW13) -> 550950.66 | BZ13: =BX13+BY13 -> 550950.66 | CA13: =IF(BV13="","",BW13/BV13) -> 0.16659333 | CB13: =BZ13/BZ$48 -> 0.012144357 | CC13: =CB13*(C$50-BW$58-BW$57) -> 52570.53 | CD13: =B13 -> ACTIONNIRE12
... A47: =epargne_mensuelle!A47 -> 0 | B47: =epargne_mensuelle!B47 -> 0 | C47: =SUM(epargne_mensuelle!C47:E47) -> 0 | D47: =(C47/C$48)*C$53 -> 0 | E47: =epargne_mensuelle!F47 -> 0 | F47: =C47-(C47/C$48)*C$52+(C47/C$48)*C$53+E47+(C47/C$48)*C$54 -> 0 | G47: =(F47/F$48)*E$53 -> 0 | H47: =epargne_mensuelle!G47 -> 0 | I47: =IF(F$48=0,F47+H47+((C47+E47)/(C$48+E$48))*E$54,F47-((F47/F$48)*E$52)+(F47/F$48)*E$53+H47+((C47+E47)/(C$48+E$48))*E$54) -> 0 | J47: =(I47/I$48)*H$53 -> 0 | K47: =epargne_mensuelle!H47 -> 0 | L47: =IF(I$48=0,I47+K47+((C47+E47+H47)/(C$48+E$48+H$48))*H$54,I47-((I47/I$48)*H$52)+(I47/I$48)*H$53+K47+((C47+E47+H47)/(C$48+E$48+H$48))*H$54) -> 0 | M47: =(L47/L$48)*K$53 -> 0 | N47: =epargne_mensuelle!I47 -> 0 | O47: =IF(L$48=0,L47+N47+((C47+E47+H47+K47)/(C$48+E$48+H$48+K$48))*K$54,L47-((L47/L$48)*K$52)+(L47/L$48)*K$53+N47+((C47+E47+H47+K47)/(C$48+E$48+H$48+K$48))*K$54) -> 0 | P47: =(O47/O$48)*N$53 -> 0 | Q47: =epargne_mensuelle!J47 -> 0 | R47: =IF(O$48=0,O47+Q47+((C47+E47+H47+K47+N47)/(C$48+E$48+H$48+K$48+N$48))*N$54,O47-((O47/O$48)*N$52)+(O47/O$48)*N$53+Q47+((C47+E47+H47+K47+N47)/(C$48+E$48+H$48+K$48+N$48))*N$54) -> 0 | S47: =(R47/R$48)*Q$53 -> 0 | T47: =epargne_mensuelle!K47 -> 0 | U47: =IF(R$48=0,R47+T47+((C47+E47+H47+K47+N47+Q47)/(C$48+E$48+H$48+K$48+N$48+Q$48))*Q$54,R47-((R47/R$48)*Q$52)+(R47/R$48)*Q$53+T47+((C47+E47+H47+K47+N47+Q47)/(C$48+E$48+H$48+K$48+N$48+Q$48))*Q$54) -> 0 | V47: =(U47/U$48)*T$53 -> 0 | W47: =epargne_mensuelle!L47 -> 0 | X47: =IF(U$48=0,U47+W47+((C47+E47+H47+K47+N47+Q47+T47)/(C$48+E$48+H$48+K$48+N$48+Q$48+T$48))*T$54,U47-((U47/U$48)*T$52)+(U47/U$48)*T$53+W47+((C47+E47+H47+K47+N47+Q47+T47)/(C$48+E$48+H$48+K$48+N$48+Q$48+T$48))*T$54) -> 0 | Y47: =(X47/X$48)*W$53 -> 0 | Z47: =epargne_mensuelle!M47 -> 0 | AA47: =IF(X$48=0,X47+Z47+((C47+E47+H47+K47+N47+Q47+T47+W47)/(C$48+E$48+H$48+K$48+N$48+Q$48+T$48+W$48))*W$54,X47-((X47/X$48)*W$52)+(X47/X$48)*W$53+Z47+((C47+E47+H47+K47+N47+Q47+T47+W47)/(C$48+E$48+H$48+K$48+N$48+Q$48+T$48+W$48))*W$54) -> 0 | AB47: =(AA47/AA$48)*Z$53 -> 0 | AC47: =epargne_mensuelle!N47 -> 0 | AD47: =IF(AA$48=0,AA47+AC47+((C47+E47+H47+K47+N47+Q47+T47+W47+Z47)/(C$48+E$48+H$48+K$48+N$48+Q$48+T$48+W$48+Z$48))*Z$54,AA47-((AA47/AA$48)*Z$52)+(AA47/AA$48)*Z$53+AC47+((C47+E47+H47+K47+N47+Q47+T47+W47+Z47)/(C$48+E$48+H$48+K$48+N$48+Q$48+T$48+W$48+Z$48))*Z$54) -> 0 | AE47: =(AD47/AD$48)*AC$53 -> 0 | AF47: =epargne_mensuelle!O47 -> 0 | AG47: =IF(AD$48=0,AD47+AF47+((C47+E47+H47+K47+N47+Q47+T47+W47+Z47+AC47)/(C$48+E$48+H$48+K$48+N$48+Q$48+T$48+W$48+Z$48+AC$48))*AC$54,AD47-((AD47/AD$48)*AC$52)+(AD47/AD$48)*AC$53+AF47+((C47+E47+H47+K47+N47+Q47+T47+W47+Z47+AC47)/(C$48+E$48+H$48+K$48+N$48+Q$48+T$48+W$48+Z$48+AC$48))*AC$54) -> 0 | AH47: =(AG47/AG$48)*AF$53 -> 0 | AI47: =epargne_mensuelle!P47 -> 0 | AJ47: =IF(AG$48=0,AG47+AI47+((C47+E47+H47+K47+N47+Q47+T47+W47+Z47+AC47+AF47)/(C$48+E$48+H$48+K$48+N$48+Q$48+T$48+W$48+Z$48+AC$48+AF$48))*AF$54,AG47-((AG47/AG$48)*AF$52)+(AG47/AG$48)*AF$53+AI47+((C47+E47+H47+K47+N47+Q47+T47+W47+Z47+AC47+AF47)/(C$48+E$48+H$48+K$48+N$48+Q$48+T$48+W$48+Z$48+AC$48+AF$48))*AF$54) -> 0 | AK47: =(AJ47/AJ$48)*AI$53 -> 0 | AL47: =epargne_mensuelle!Q47 -> 0 | AM47: =IF(AJ$48=0,AJ47+AL47+((C47+E47+H47+K47+N47+Q47+T47+W47+Z47+AC47+AF47+AI47)/(C$48+E$48+H$48+K$48+N$48+Q$48+T$48+W$48+Z$48+AC$48+AF$48+AI$48))*AI$54,AJ47-((AJ47/AJ$48)*AI$52)+(AJ47/AJ$48)*AI$53+AL47+((C47+E47+H47+K47+N47+Q47+T47+W47+Z47+AC47+AF47+AI47)/(C$48+E$48+H$48+K$48+N$48+Q$48+T$48+W$48+Z$48+AC$48+AF$48+AI$48))*AI$54) -> 0 | AN47: =(AM47/AM$48)*AL$53 -> 0 | AO47: =epargne_mensuelle!R47 -> 0 | AP47: =IF(AM$48=0,AM47+AO47+((C47+E47+H47+K47+N47+Q47+T47+W47+Z47+AC47+AF47+AI47+AL47)/(C$48+E$48+H$48+K$48+N$48+Q$48+T$48+W$48+Z$48+AC$48+AF$48+AI$48+AL$48))*AL$54,AM47-((AM47/AM$48)*AL$52)+(AM47/AM$48)*AL$53+AO47+((C47+E47+H47+K47+N47+Q47+T47+W47+Z47+AC47+AF47+AI47+AL47)/(C$48+E$48+H$48+K$48+N$48+Q$48+T$48+W$48+Z$48+AC$48+AF$48+AI$48+AL$48))*AL$54) -> 0 | AQ47: =(AP47/AP$48)*AO$53 -> 0 | AR47: =epargne_mensuelle!S47 -> 0 | AS47: =IF(AP$48=0,AP47+AR47+((C47+E47+H47+K47+N47+Q47+T47+W47+Z47+AC47+AF47+AI47+AL47+AO47)/(C$48+E$48+H$48+K$48+N$48+Q$48+T$48+W$48+Z$48+AC$48+AF$48+AI$48+AL$48+AO$48))*AO$54,AP47-((AP47/AP$48)*AO$52)+(AP47/AP$48)*AO$53+AR47+((C47+E47+H47+K47+N47+Q47+T47+W47+Z47+AC47+AF47+AI47+AL47+AO47)/(C$48+E$48+H$48+K$48+N$48+Q$48+T$48+W$48+Z$48+AC$48+AF$48+AI$48+AL$48+AO$48))*AO$54) -> 0 | AT47: =(AS47/AS$48)*AR$53 -> 0 | AU47: =epargne_mensuelle!T47 -> 0 | AV47: =IF(AS$48=0,AS47+AU47+((C47+E47+H47+K47+N47+Q47+T47+W47+Z47+AC47+AF47+AI47+AL47+AO47+AR47)/(C$48+E$48+H$48+K$48+N$48+Q$48+T$48+W$48+Z$48+AC$48+AF$48+AI$48+AL$48+AO$48+AR$48))*AR$54,AS47-((AS47/AS$48)*AR$52)+(AS47/AS$48)*AR$53+AU47+((C47+E47+H47+K47+N47+Q47+T47+W47+Z47+AC47+AF47+AI47+AL47+AO47+AR47)/(C$48+E$48+H$48+K$48+N$48+Q$48+T$48+W$48+Z$48+AC$48+AF$48+AI$48+AL$48+AO$48+AR$48))*AR$54) -> 0 | AW47: =(AV47/AV$48)*AU$53 -> 0 | AX47: =epargne_mensuelle!U47 -> 0 | AY47: =IF(AV$48=0,AV47+AX47+((C47+E47+H47+K47+N47+Q47+T47+W47+Z47+AC47+AF47+AI47+AL47+AO47+AR47+AU47)/(C$48+E$48+H$48+K$48+N$48+Q$48+T$48+W$48+Z$48+AC$48+AF$48+AI$48+AL$48+AO$48+AR$48+AU$48))*AU$54,AV47-((AV47/AV$48)*AU$52)+(AV47/AV$48)*AU$53+AX47+((C47+E47+H47+K47+N47+Q47+T47+W47+Z47+AC47+AF47+AI47+AL47+AO47+AR47+AU47)/(C$48+E$48+H$48+K$48+N$48+Q$48+T$48+W$48+Z$48+AC$48+AF$48+AI$48+AL$48+AO$48+AR$48+AU$48))*AU$54) -> 0 | AZ47: =(AY47/AY$48)*AX$53 -> 0 | BA47: =epargne_mensuelle!V47 -> 0 | BB47: =IF(AY$48=0,AY47+BA47+((C47+E47+H47+K47+N47+Q47+T47+W47+Z47+AC47+AF47+AI47+AL47+AO47+AR47+AU47+AX47)/(C$48+E$48+H$48+K$48+N$48+Q$48+T$48+W$48+Z$48+AC$48+AF$48+AI$48+AL$48+AO$48+AR$48+AU$48+AX$48))*AX$54,AY47-((AY47/AY$48)*AX$52)+(AY47/AY$48)*AX$53+BA47+((C47+E47+H47+K47+N47+Q47+T47+W47+Z47+AC47+AF47+AI47+AL47+AO47+AR47+AU47+AX47)/(C$48+E$48+H$48+K$48+N$48+Q$48+T$48+W$48+Z$48+AC$48+AF$48+AI$48+AL$48+AO$48+AR$48+AU$48+AX$48))*AX$54) -> 0 | BC47: =(BB47/BB$48)*BA$53 -> 0 | BD47: =epargne_mensuelle!W47 -> 0 | BE47: =IF(BB$48=0,BB47+BD47+((C47+E47+H47+K47+N47+Q47+T47+W47+Z47+AC47+AF47+AI47+AL47+AO47+AR47+AU47+AX47+BA47)/(C$48+E$48+H$48+K$48+N$48+Q$48+T$48+W$48+Z$48+AC$48+AF$48+AI$48+AL$48+AO$48+AR$48+AU$48+AX$48+BA$48))*BA$54,BB47-((BB47/BB$48)*BA$52)+(BB47/BB$48)*BA$53+BD47+((C47+E47+H47+K47+N47+Q47+T47+W47+Z47+AC47+AF47+AI47+AL47+AO47+AR47+AU47+AX47+BA47)/(C$48+E$48+H$48+K$48+N$48+Q$48+T$48+W$48+Z$48+AC$48+AF$48+AI$48+AL$48+AO$48+AR$48+AU$48+AX$48+BA$48))*BA$54) -> 0 | BF47: =(BE47/BE$48)*BD$53 -> 0 | BG47: =epargne_mensuelle!X47 -> 0 | BH47: =IF(BE$48=0,BE47+BG47+((C47+E47+H47+K47+N47+Q47+T47+W47+Z47+AC47+AF47+AI47+AL47+AO47+AR47+AU47+AX47+BA47+BD47)/(C$48+E$48+H$48+K$48+N$48+Q$48+T$48+W$48+Z$48+AC$48+AF$48+AI$48+AL$48+AO$48+AR$48+AU$48+AX$48+BA$48+BD$48))*BD$54,BE47-((BE47/BE$48)*BD$52)+(BE47/BE$48)*BD$53+BG47+((C47+E47+H47+K47+N47+Q47+T47+W47+Z47+AC47+AF47+AI47+AL47+AO47+AR47+AU47+AX47+BA47+BD47)/(C$48+E$48+H$48+K$48+N$48+Q$48+T$48+W$48+Z$48+AC$48+AF$48+AI$48+AL$48+AO$48+AR$48+AU$48+AX$48+BA$48+BD$48))*BD$54) -> 0 | BI47: =(BH47/BH$48)*BG$53 -> 0 | BJ47: =epargne_mensuelle!Y47 -> 0 | BK47: =IF(BH$48=0,BH47+BJ47+((C47+E47+H47+K47+N47+Q47+T47+W47+Z47+AC47+AF47+AI47+AL47+AO47+AR47+AU47+AX47+BA47+BD47+BG47)/(C$48+E$48+H$48+K$48+N$48+Q$48+T$48+W$48+Z$48+AC$48+AF$48+AI$48+AL$48+AO$48+AR$48+AU$48+AX$48+BA$48+BD$48+BG$48))*BG$54,BH47-((BH47/BH$48)*BG$52)+(BH47/BH$48)*BG$53+BJ47+((C47+E47+H47+K47+N47+Q47+T47+W47+Z47+AC47+AF47+AI47+AL47+AO47+AR47+AU47+AX47+BA47+BD47+BG47)/(C$48+E$48+H$48+K$48+N$48+Q$48+T$48+W$48+Z$48+AC$48+AF$48+AI$48+AL$48+AO$48+AR$48+AU$48+AX$48+BA$48+BD$48+BG$48))*BG$54) -> 0 | BL47: =(BK47/BK$48)*BJ$53 -> 0 | BM47: =epargne_mensuelle!Z47 -> 0 | BN47: =IF(BK$48=0,BK47+BM47+((C47+E47+H47+K47+N47+Q47+T47+W47+Z47+AC47+AF47+AI47+AL47+AO47+AR47+AU47+AX47+BA47+BD47+BG47+BJ47)/(C$48+E$48+H$48+K$48+N$48+Q$48+T$48+W$48+Z$48+AC$48+AF$48+AI$48+AL$48+AO$48+AR$48+AU$48+AX$48+BA$48+BD$48+BG$48+BJ$48))*BJ$54,BK47-((BK47/BK$48)*BJ$52)+(BK47/BK$48)*BJ$53+BM47+((C47+E47+H47+K47+N47+Q47+T47+W47+Z47+AC47+AF47+AI47+AL47+AO47+AR47+AU47+AX47+BA47+BD47+BG47+BJ47)/(C$48+E$48+H$48+K$48+N$48+Q$48+T$48+W$48+Z$48+AC$48+AF$48+AI$48+AL$48+AO$48+AR$48+AU$48+AX$48+BA$48+BD$48+BG$48+BJ$48))*BJ$54) -> 0 | BO47: =(BN47/BN$48)*BM$53 -> 0 | BP47: =epargne_mensuelle!AA47 -> 0 | BQ47: =IF(BN$48=0,BN47+BP47+((F47+H47+K47+N47+Q47+T47+W47+Z47+AC47+AF47+AI47+AL47+AO47+AR47+AU47+AX47+BA47+BD47+BG47+BJ47+BM47)/(F$48+H$48+K$48+N$48+Q$48+T$48+W$48+Z$48+AC$48+AF$48+AI$48+AL$48+AO$48+AR$48+AU$48+AX$48+BA$48+BD$48+BG$48+BJ$48+BM$48))*BM$54,BN47-((BN47/BN$48)*BM$52)+(BN47/BN$48)*BM$53+BP47+((F47+H47+K47+N47+Q47+T47+W47+Z47+AC47+AF47+AI47+AL47+AO47+AR47+AU47+AX47+BA47+BD47+BG47+BJ47+BM47)/(F$48+H$48+K$48+N$48+Q$48+T$48+W$48+Z$48+AC$48+AF$48+AI$48+AL$48+AO$48+AR$48+AU$48+AX$48+BA$48+BD$48+BG$48+BJ$48+BM$48))*BM$54) -> 0 | BR47: =(BQ47/BQ$48)*BP$53 -> 0 | BS47: =epargne_mensuelle!AB47 -> 0 | BT47: =IF(BQ$48=0,BQ47+BS47+((I47+K47+N47+Q47+T47+W47+Z47+AC47+AF47+AI47+AL47+AO47+AR47+AU47+AX47+BA47+BD47+BG47+BJ47+BM47+BP47)/(I$48+K$48+N$48+Q$48+T$48+W$48+Z$48+AC$48+AF$48+AI$48+AL$48+AO$48+AR$48+AU$48+AX$48+BA$48+BD$48+BG$48+BJ$48+BM$48+BP$48))*BP$54,BQ47-((BQ47/BQ$48)*BP$52)+(BQ47/BQ$48)*BP$53+BS47+((I47+K47+N47+Q47+T47+W47+Z47+AC47+AF47+AI47+AL47+AO47+AR47+AU47+AX47+BA47+BD47+BG47+BJ47+BM47+BP47)/(I$48+K$48+N$48+Q$48+T$48+W$48+Z$48+AC$48+AF$48+AI$48+AL$48+AO$48+AR$48+AU$48+AX$48+BA$48+BD$48+BG$48+BJ$48+BM$48+BP$48))*BP$54) -> 0 | BU47: =(BT47/BT$48)*BS$53 -> 0 | BV47: =cumul_epargne!C47 | BW47: =D47+G47+J47+M47+P47+S47+V47+Y47+AB47+AE47+AH47+AK47+AN47+AQ47+AT47+AW47+AZ47+BC47+BF47+BI47+BL47+BO47+BR47+BU47 -> 0 | BX47: =IF(BV47="",BW47,BV47+BW47) -> 0 | BZ47: =BX47+BY47 -> 0 | CA47: =IF(BV47="","",BW47/BV47) | CB47: =BZ47/BZ$48 -> 0 | CC47: =CB47*(C$50-BW$58-BW$57) -> 0 | CD47: =B47 -> 0
A48: Total | C48: =SUM(C2:C47) -> 34335403 | D48: =SUM(D2:D47) -> 4340000 | E48: =SUM(E2:E47) -> 660000 | F48: =SUM(F2:F47) -> 5800403 | G48: =SUM(G2:G47) -> 0 | H48: =SUM(H2:H47) -> 2100000 | I48: =SUM(I2:I47) -> 8630403 | J48: =SUM(J2:J47) -> 820000 | ... BZ48: =SUM(BZ2:BZ47) -> 45366803 | CA48: =IF(BV48="","",BW48/BV48) -> 0.16011598 | CB48: =BZ48/BZ$48 -> 1 | CC48: =CB48*(C$50-BW$58-BW$57) -> 4328803 | CD48: =B48 -> 0
BV49: Prêts en cours: | BX49: =recap_prêt!J45+SUM(recap_prêt!J7:J8)-113030 -> 42292370
B50: Solde en caisse: | C50: =recap_prêt!$C$1 -> 4328803 | BT50: Solde en caisse: | BW50: =recap_prêt!$C$1 -> 4328803 | BX50: =BW50+BX49 -> 46621173
BX51: =BX48-BX50 -> -1254370
B52: Prêt | C52: =pret!J40 -> 35400000 | E52: =pret!K40 -> 0 | H52: =pret!L40 -> 6500000 | K52: =pret!M40 -> 4600000 | N52: =pret!N40 -> 2500000 | Q52: =pret!O40 -> 3000000 | T52: =pret!P40 -> 0 | W52: =pret!Q40 -> 0 | Z52: =pret!R40 -> 0 | AC52: =pret!S40 -> 0 | AF52: =pret!T40 -> 0 | AI52: =pret!U40 -> 0 | AL52: =pret!V40 -> 0 | AO52: =pret!W40 -> 0 | AR52: =pret!X40 -> 0 | AU52: =pret!Y40 -> 0 | AX52: =pret!Z40 -> 0 | BA52: =pret!AA40 -> 0 | BD52: =pret!AB40 -> 0 | BG52: =pret!AC40 -> 0 | BJ52: =pret!AD40 -> 0 | BM52: =pret!AE40 -> 0 | BP52: =pret!AF40 -> 0 | BS52: =pret!AG40 -> 0 | BW52: =SUM(A52:BS52) -> 52000000
B53: Intérêt | C53: =_interet!J42 -> 4340000 | E53: =_interet!K42 -> 0 | H53: =_interet!L42 -> 820000 | K53: =_interet!M42 -> 281400 | N53: =_interet!N42 -> 100000 | Q53: =_interet!O42 -> 720000 | T53: =_interet!P42 -> 0 | W53: =_interet!Q42 -> 0 | Z53: =_interet!R42 -> 0 | AC53: =_interet!S42 -> 0 | AF53: =_interet!T42 -> 0 | AI53: =_interet!U42 -> 0 | AL53: =_interet!V42 -> 0 | AO53: =_interet!W42 -> 0 | AR53: =_interet!X42 -> 0 | AU53: =_interet!Y42 -> 0 | AX53: =_interet!Z42 -> 0 | BA53: =_interet!AA42 -> 0 | BD53: =_interet!AB42 -> 0 | BG53: =_interet!AC42 -> 0 | BJ53: =_interet!AD42 -> 0 | BM53: =_interet!AE42 -> 0 | BP53: =_interet!AF42 -> 0 | BS53: =_interet!AG42 -> 0 | BW53: =SUM(A53:BS53) -> 6261400
B54: remboursement | C54: =C55 -> 1865000 | E54: =E55 -> 730000 | H54: =H55 -> 3221500 | K54: =K55 -> 2606500 | N54: =N55 -> 4594500 | Q54: =Q55 -> 4323500 | T54: =T55 -> 0 | W54: =W55 -> 0 | Z54: =Z55 -> 0 | AC54: =AC55 -> 0 | AF54: =AF55 -> 0 | AI54: =AI55 -> 0 | AL54: =AL55 -> 0 | AO54: =AO55 -> 0 | AR54: =AR55 -> 0 | AU54: =AU55 -> 0 | AX54: =AX55 -> 0 | BA54: =BA55 -> 0 | BD54: =BD55 -> 0 | BG54: =BG55 -> 0 | BJ54: =BJ55 -> 0 | BM54: =BM55 -> 0 | BP54: =BP55 -> 0 | BS54: =BS55 -> 0 | BW54: =SUM(A54:BS54) -> 17341000
C55: =recouvrement_dette!J40 -> 1865000 | E55: =recouvrement_dette!K40 -> 730000 | H55: =recouvrement_dette!L40 -> 3221500 | K55: =recouvrement_dette!M40 -> 2606500 | N55: =recouvrement_dette!N40 -> 4594500 | Q55: =recouvrement_dette!O40 -> 4323500 | T55: =recouvrement_dette!P40 -> 0 | W55: =recouvrement_dette!Q40 -> 0 | Z55: =recouvrement_dette!R40 -> 0 | AC55: =recouvrement_dette!S40 -> 0 | AF55: =recouvrement_dette!T40 -> 0 | AI55: =recouvrement_dette!U40 -> 0 | AL55: =recouvrement_dette!V40 -> 0 | AO55: =recouvrement_dette!W40 -> 0 | AR55: =recouvrement_dette!X40 -> 0 | AU55: =recouvrement_dette!Y40 -> 0 | AX55: =recouvrement_dette!Z40 -> 0 | BA55: =recouvrement_dette!AA40 -> 0 | BD55: =recouvrement_dette!AB40 -> 0 | BG55: =recouvrement_dette!AC40 -> 0 | BJ55: =recouvrement_dette!AD40 -> 0 | BM55: =recouvrement_dette!AE40 -> 0 | BP55: =recouvrement_dette!AF40 -> 0 | BS55: =recouvrement_dette!AG40 -> 0 | BW55: =SUM(A55:BS55) -> 17341000
B57: Pénalités | C57: =recouvrement_dette!J42 -> 0 | E57: =recouvrement_dette!K42 -> 0 | H57: =recouvrement_dette!L42 -> 0 | K57: =recouvrement_dette!M42 -> 0 | N57: =recouvrement_dette!N42 -> 0 | Q57: =recouvrement_dette!O42 -> 0 | T57: =recouvrement_dette!P42 -> 0 | W57: =recouvrement_dette!Q42 -> 0 | Z57: =recouvrement_dette!R42 -> 0 | AC57: =recouvrement_dette!S42 -> 0 | AF57: =recouvrement_dette!T42 -> 0 | AI57: =recouvrement_dette!U42 -> 0 | AL57: =recouvrement_dette!V42 -> 0 | AO57: =recouvrement_dette!W42 -> 0 | AR57: =recouvrement_dette!X42 -> 0 | AU57: =recouvrement_dette!Y42 -> 0 | AX57: =recouvrement_dette!Z42 -> 0 | BA57: =recouvrement_dette!AA42 -> 0 | BD57: =recouvrement_dette!AB42 -> 0 | BG57: =recouvrement_dette!AC42 -> 0 | BJ57: =recouvrement_dette!AD42 -> 0 | BM57: =recouvrement_dette!AE42 -> 0 | BP57: =recouvrement_dette!AF42 -> 0 | BS57: =recouvrement_dette!AG42 -> 0 | BW57: =SUM(A57:BS57) -> 0
B58: Prime Comité gestion | C58: =C53*$B$59 -> 0 | E58: =E53*$B$59 -> 0 | H58: =H53*$B$59 -> 0 | K58: =K53*$B$59 -> 0 | N58: =N53*$B$59 -> 0 | Q58: =Q53*$B$59 -> 0 | T58: =T53*$B$59 -> 0 | W58: =W53*$B$59 -> 0 | Z58: =Z53*$B$59 -> 0 | AC58: =AC53*$B$59 -> 0 | AF58: =AF53*$B$59 -> 0 | AI58: =AI53*$B$59 -> 0 | AL58: =AL53*$B$59 -> 0 | AO58: =AO53*$B$59 -> 0 | AR58: =AR53*$B$59 -> 0 | AU58: =AU53*$B$59 -> 0 | AX58: =AX53*$B$59 -> 0 | BA58: =BA53*$B$59 -> 0 | BD58: =BD53*$B$59 -> 0 | BG58: =BG53*$B$59 -> 0 | BJ58: =BJ53*$B$59 -> 0 | BM58: =BM53*$B$59 -> 0 | BP58: =BP53*$B$59 -> 0 | BS58: =BS53*$B$59 -> 0 | BW58: =SUM(A58:BS58) -> 0
B59: 0

Sheet Feuil5

Sheet epargne_mensuelle
A1: N° | B1: Nom épargnant | C1: Repport cassation N-1 | D1: Paiement Cassation | E1: 45870 | F1: 45901 | G1: 45931 | H1: 45962 | I1: 45992 | J1: 46023 | K1: 46054 | L1: 46082 | M1: 46113 | N1: 46143 | O1: 46174 | P1: 46204 | Q1: 46235 | R1: 46266 | S1: 46296 | T1: 46327 | U1: 46357 | V1: 46388 | W1: 46419 | X1: 46447 | Y1: 46478 | Z1: 46508 | AA1: 46539 | AB1: 46569
A2: 1 | B2: ACTIONNIRE1 | C2: 1956801.8 | D2: -1000000 | J2: 25000
A3: 2 | B3: ACTIONNIRE2 | C3: 270897.47 | G3: 300000
A4: 3 | B4: ACTIONNIRE3 | C4: 3308079.8 | E4: 700000
A5: 4 | B5: ACTIONNIRE4 | C5: 372369.77
A6: 5 | B6: ACTIONNIRE5 | C6: 1393753.8
A7: 6 | B7: ACTIONNIRE6 | C7: 829601.83
A8: 7 | B8: ACTIONNIRE7 | C8: 840018.32
A9: 8 | B9: ACTIONNIRE8 | C9: 5000758.2 | G9: 1000000
A10: 9 | B10: ACTIONNIRE9 | C10: 769026.95 | D10: -230000
A11: 10 | B11: ACTIONNIRE10 | C11: 477772.09 | F11: 25000
A12: 11 | B12: ACTIONNIRE11 | C12: 1066673.4 | F12: 20000
A13: 12 | B13: ACTIONNIRE12 | C13: 472273.11
A14: 13 | B14: ACTIONNIRE13 | C14: 1208778.2 | E14: 1000000 | G14: 300000
A15: 14 | B15: ACTIONNIRE14 | C15: 514154.36
A16: 15 | B16: ACTIONNIRE15 | C16: 747258.38 | E16: 370000
A17: 16 | B17: ACTIONNIRE16 | C17: 99669.598
A18: 17 | B18: ACTIONNIRE17 | C18: 1118757.7
A19: 18 | B19: ACTIONNIRE18 | C19: 299377.18 | H19: 400000
A20: 19 | B20: ACTIONNIRE19 | C20: 159938.43 | F20: 500000
A21: 20 | B21: ACTIONNIRE20 | C21: 218369.91
A22: 21 | B22: ACTIONNIRE21 | C22: 304027.69
A23: 22 | B23: ACTIONNIRE22 | C23: 907686.43
A24: 23 | B24: ACTIONNIRE23 | C24: 54646.514
A25: 24 | B25: ACTIONNIRE24 | C25: 162676.97
A26: 25 | B26: ACTIONNIRE25 | C26: 696021.67
A27: 26 | B27: ACTIONNIRE26 | C27: 290762.86
A28: 27 | B28: ACTIONNIRE27 | C28: 29035.526 | I28: 25000
A29: 28 | B29: ACTIONNIRE28 | C29: 147241.09 | E29: 20000
A30: 29 | B30: ACTIONNIRE29 | C30: 2585156.5 | D30: -1000000 | I30: 440000
A31: 30 | B31: ACTIONNIRE30 | C31: 1028984.1
A32: 31 | B32: ACTIONNIRE31 | C32: 1236027.4
A33: 32 | B33: ACTIONNIRE32 | C33: 260099.7
A34: 33 | B34: ACTIONNIRE33 | C34: 87809.36
A35: 34 | B35: ACTIONNIRE34 | C35: 2514536 | G35: 500000 | H35: 700000 | I35: 300000
A36: 35 | B36: ACTIONNIRE35 | C36: 121360.81 | E36: 380000
A37: 36 | B37: ACTIONNIRE36 | E37: 2040000
A38: 37 | B38: ACTIONNIRE37 | E38: 20000 | F38: 115000
A39: 38 | B39: ACTIONNIRE38 | E39: 5000
A40: 39 | B40: ACTIONNIRE39 | E40: 360000
A41: 40 | B41: ACTIONNIRE40 | E41: 120000
A42: 41 | B42: ACTIONNIRE41 | J42: 120000
A48: Total | C48: =SUM(C2:C47) -> 31550403 | D48: =SUM(D2:D47) -> -2230000 | E48: =SUM(E2:E47) -> 5015000 | F48: =SUM(F2:F47) -> 660000 | G48: =SUM(G2:G47) -> 2100000 | H48: =SUM(H2:H47) -> 1100000 | I48: =SUM(I2:I47) -> 765000 | J48: =SUM(J2:J47) -> 145000 | ... AB48: =SUM(AB2:AB47) -> 0

Sheet cumul_epargne
A1: N° | B1: Nom épargnant | C1: Cumul épargne
A2: =IF(epargne_mensuelle!A2="","",epargne_mensuelle!A2) -> 1 | B2: =IF(epargne_mensuelle!B2="","",epargne_mensuelle!B2) -> ACTIONNIRE1 | C2: =IF(A2="","",SUM(epargne_mensuelle!C2:AB2)) -> 981801.77
A3: =IF(epargne_mensuelle!A3="","",epargne_mensuelle!A3) -> 2 | B3: =IF(epargne_mensuelle!B3="","",epargne_mensuelle!B3) -> ACTIONNIRE2 | C3: =IF(A3="","",SUM(epargne_mensuelle!C3:AB3)) -> 570897.47
A4: =IF(epargne_mensuelle!A4="","",epargne_mensuelle!A4) -> 3 | B4: =IF(epargne_mensuelle!B4="","",epargne_mensuelle!B4) -> ACTIONNIRE3 | C4: =IF(A4="","",SUM(epargne_mensuelle!C4:AB4)) -> 4008079.8
A5: =IF(epargne_mensuelle!A5="","",epargne_mensuelle!A5) -> 4 | B5: =IF(epargne_mensuelle!B5="","",epargne_mensuelle!B5) -> ACTIONNIRE4 | C5: =IF(A5="","",SUM(epargne_mensuelle!C5:AB5)) -> 372369.77
A6: =IF(epargne_mensuelle!A6="","",epargne_mensuelle!A6) -> 5 | B6: =IF(epargne_mensuelle!B6="","",epargne_mensuelle!B6) -> ACTIONNIRE5 | C6: =IF(A6="","",SUM(epargne_mensuelle!C6:AB6)) -> 1393753.8
A7: =IF(epargne_mensuelle!A7="","",epargne_mensuelle!A7) -> 6 | B7: =IF(epargne_mensuelle!B7="","",epargne_mensuelle!B7) -> ACTIONNIRE6 | C7: =IF(A7="","",SUM(epargne_mensuelle!C7:AB7)) -> 829601.83
A8: =IF(epargne_mensuelle!A8="","",epargne_mensuelle!A8) -> 7 | B8: =IF(epargne_mensuelle!B8="","",epargne_mensuelle!B8) -> ACTIONNIRE7 | C8: =IF(A8="","",SUM(epargne_mensuelle!C8:AB8)) -> 840018.32
A9: =IF(epargne_mensuelle!A9="","",epargne_mensuelle!A9) -> 8 | B9: =IF(epargne_mensuelle!B9="","",epargne_mensuelle!B9) -> ACTIONNIRE8 | C9: =IF(A9="","",SUM(epargne_mensuelle!C9:AB9)) -> 6000758.2
A10: =IF(epargne_mensuelle!A10="","",epargne_mensuelle!A10) -> 9 | B10: =IF(epargne_mensuelle!B10="","",epargne_mensuelle!B10) -> ACTIONNIRE9 | C10: =IF(A10="","",SUM(epargne_mensuelle!C10:AB10)) -> 539026.95
A11: =IF(epargne_mensuelle!A11="","",epargne_mensuelle!A11) -> 10 | B11: =IF(epargne_mensuelle!B11="","",epargne_mensuelle!B11) -> ACTIONNIRE10 | C11: =IF(A11="","",SUM(epargne_mensuelle!C11:AB11)) -> 502772.09
A12: =IF(epargne_mensuelle!A12="","",epargne_mensuelle!A12) -> 11 | B12: =IF(epargne_mensuelle!B12="","",epargne_mensuelle!B12) -> ACTIONNIRE11 | C12: =IF(A12="","",SUM(epargne_mensuelle!C12:AB12)) -> 1086673.4
A13: =IF(epargne_mensuelle!A13="","",epargne_mensuelle!A13) -> 12 | B13: =IF(epargne_mensuelle!B13="","",epargne_mensuelle!B13) -> ACTIONNIRE12 | C13: =IF(A13="","",SUM(epargne_mensuelle!C13:AB13)) -> 472273.11
... A47: =IF(epargne_mensuelle!A47="","",epargne_mensuelle!A47) | B47: =IF(epargne_mensuelle!B47="","",epargne_mensuelle!B47) | C47: =IF(A47="","",SUM(epargne_mensuelle!C47:AB47))
A48: Total épargne | C48: =SUM(C2:C47) -> 39105403

Sheet recouvrement_dette
A1: N° | B1: Nom épargnant | C1: Date dette | D1: Échéance dette | E1: Montant dette | F1: Durée dette (en mois) | G1: Taux intérêt | H1: Intérêt | I1: 45839 | J1: 45870 | K1: 45901 | L1: 45931 | M1: 45962 | N1: 45992 | O1: 46023 | P1: 46054 | Q1: 46082 | R1: 46113 | S1: 46143 | T1: 46174 | U1: 46204 | V1: 46235 | W1: 46266 | X1: 46296 | Y1: 46327 | Z1: 46357 | AA1: 46388 | AB1: 46419 | AC1: 46447 | AD1: 46478 | AE1: 46508 | AF1: 46539 | AG1: 46569
A2: 1 | B2: action1 | E2: 75000 | J2: 25000
A3: 2 | B3: action2 | C3: Fev. 2025 | D3: 10 Oct. 2026 | E3: 2400000 | F3: 20 | G3: =IF(E3<1000000,F3*1.5%,F3*1%) -> 0.2 | H3: =G3*E3 -> 480000 | J3: 840000 | K3: 150000 | L3: 130000 | M3: 140000 | N3: 140000 | O3: 140000
A4: 3 | B4: action3 | C4: Août 2025 | D4: 10 Juil. 2026 | E4: 5500000 | F4: 10 | G4: =IF(E4<1000000,F4*1.5%,F4*1%) -> 0.1 | H4: =G4*E4 -> 550000 | K4: 580000 | L4: 830000 | M4: 380000 | N4: 480000 | O4: 400000
A5: 4 | B5: action4 | C5: Août 2025 | D5: 10 Sept. 2026 | E5: 300000 | F5: 12 | G5: =IF(E5<1000000,F5*1.5%,F5*1%) -> 0.18 | H5: =G5*E5 -> 54000 | L5: 29500 | M5: 29500 | N5: 29500 | O5: 29500
A6: 5 | B6: action5 | C6: Août 2025 | D6: 10 Sept. 2027 | E6: 1850000 | F6: 24 | G6: =IF(E6<1000000,F6*1.5%,F6*1%) -> 0.24 | H6: =G6*E6 -> 444000 | L6: 100000 | M6: 100000 | N6: 100000 | O6: 100000
A7: 6 | B7: action6 | C7: Août 2025 | D7: 10 Sept. 2026 | E7: 3700000 | F7: 12 | G7: =IF(E7<1000000,F7*1.5%,F7*1%) -> 0.12 | H7: =G7*E7 -> 444000 | L7: 345334 | M7: 345334 | N7: 328333 | O7: 345333
A8: 7 | B8: action7 | C8: Août 2025 | D8: 10 Sept. 2026 | E8: 4000000 | F8: 12 | G8: =IF(E8<1000000,F8*1.5%,F8*1%) -> 0.12 | H8: =G8*E8 -> 480000 | L8: 373333 | M8: 373333 | N8: 373334 | O8: 373333
A9: 8 | B9: action8 | C9: Août 2025 | D9: 10 Juil. 2026 | E9: 4000000 | F9: 10 | G9: =IF(E9<1000000,F9*1.5%,F9*1%) -> 0.1 | H9: =G9*E9 -> 400000 | J9: 1000000 | N9: 300000 | O9: 300000
A10: 9 | B10: action9 | C10: Août 2025 | D10: 10 Sept. 2026 | E10: 1150000 | F10: 12 | G10: =IF(E10<1000000,F10*1.5%,F10*1%) -> 0.12 | H10: =G10*E10 -> 138000 | L10: 110000 | M10: 100000 | N10: 100000
A11: 10 | B11: action10 | C11: Août 2025 | D11: 10 Juin. 2026 | E11: 4000000 | F11: 9 | G11: =IF(E11<1000000,F11*1.5%,F11*1%) -> 0.09 | H11: =G11*E11 -> 360000 | L11: 485000 | M11: 485000 | N11: 485000 | O11: 485000
A12: 11 | B12: action11 | C12: Août 2025 | D12: 10 Sept. 2026 | E12: 4000000 | F12: 12 | G12: =IF(E12<1000000,F12*1.5%,F12*1%) -> 0.12 | H12: =G12*E12 -> 480000 | L12: 373333 | M12: 373333 | N12: 373333 | O12: 373334
A13: 12 | B13: action12 | C13: Août 2025 | D13: 10 Juil. 2026 | E13: 1500000 | F13: 10 | G13: =IF(E13<1000000,F13*1.5%,F13*1%) -> 0.1 | H13: =G13*E13 -> 150000 | L13: 165000 | N13: 330000
A14: 13 | B14: action13 | C14: Août 2025 | D14: 10 Sept. 2026 | E14: 3000000 | F14: 12 | G14: =IF(E14<1000000,F14*1.5%,F14*1%) -> 0.12 | H14: =G14*E14 -> 360000 | L14: 280000 | M14: 280000 | N14: 280000
A15: 14 | B15: action14 | C15: Octobre 2025 | D15: 10 Mai. 2027 | E15: 3000000 | F15: 18 | G15: =IF(E15<1000000,F15*1.5%,F15*1%) -> 0.18 | H15: =G15*E15 -> 540000 | O15: 425000
A16: 14 | B16: action15 | C16: Octobre 2025 | D16: 10 Sept. 2026 | E16: 2500000 | F16: 10 | G16: =IF(E16<1000000,F16*1.5%,F16*1%) -> 0.1 | H16: =G16*E16 -> 250000 | N16: 275000 | O16: 275000
A17: 15 | B17: action16 | C17: Octobre 2025 | D17: 10 Fév. 2026 | E17: 1000000 | F17: 3 | G17: =IF(E17<1000000,F17*1.5%,F17*1%) -> 0.03 | H17: =G17*E17 -> 30000 | N17: 1000000 | O17: 30000
A18: 15 | B18: action17 | C18: Novemvre 2025 | D18: 10 Déc. 2026 | E18: 1570000 | F18: 12 | G18: =IF(E18<1000000,F18*1.5%,F18*1%) -> 0.12 | H18: =G18*E18 -> 188400 | O18: 147000
A19: 15 | B19: action18 | C19: Novemvre 2025 | D19: 10 Mars. 2026 | E19: 3100000 | F19: 3 | G19: =IF(E19<1000000,F19*1.5%,F19*1%) -> 0.03 | H19: =G19*E19 -> 93000 | O19: 900000
A20: 15 | B20: action19 | C20: Decembre 2025 | D20: 10 Mai 2026 | E20: 2500000 | F20: 4 | G20: =IF(E20<1000000,F20*1.5%,F20*1%) -> 0.04 | H20: =G20*E20 -> 100000
A21: 15 | B21: action20 | C21: Janvier 2026 | D21: 10 Fév 2028 | E21: 3000000 | F21: 24 | G21: =IF(E21<1000000,F21*1.5%,F21*1%) -> 0.24 | H21: =G21*E21 -> 720000
A22: 14
A23: 14
A24: 14
A25: 15
A26: 15
A27: 15
A28: 7
A29: 10
A30: 15
A31: 14
A33: 15
A40: Total | C40: =SUM(C2:C4) -> 0 | D40: =SUM(D2:D4) -> 0 | E40: =SUM(E2:E39) -> 52145000 | H40: =SUM(H2:H39) -> 6261400 | I40: =SUM(I2:I39) -> 0 | J40: =SUM(J2:J38) -> 1865000 | K40: =SUM(K2:K38) -> 730000 | L40: =SUM(L2:L38) -> 3221500 | M40: =SUM(M2:M38) -> 2606500 | N40: =SUM(N2:N38) -> 4594500 | O40: =SUM(O2:O38) -> 4323500 | P40: =SUM(P2:P38) -> 0 | Q40: =SUM(Q2:Q38) -> 0 | ... AF40: =SUM(AF2:AF38) -> 0 | AG40: =SUM(AG2:AG39) -> 0
B42: Pénalités
B43: Autres dépenses | J43: 47600

Sheet recap_prêt
B1: SOLDE EN CAISSE | C1: =cumul_epargne!C48-recap_prêt!B45+recap_prêt!H45-SUM(recouvrement_dette!I43:AG43)+SUM(recouvrement_dette!I42:AG42) -> 4328803
A2: RECAPITULATIF DES DETTES DANS LA MICROFINANCE CAMDVI
L4: Janvier. 2026
A6: NOMS | B6: Montant prêt | C6: Mois du prêt | D6: Durée du prêt (en mois) | E6: Taux intérêt cumulé | F6: Montant intérêt | G6: Montant global à rembourser | H6: Montant déjà remboursé | I6: Taux de recouv. | J6: Reste à rembourser | K6: Échéance du prêt | L6: Commentaire
A7: =recouvrement_dette!B2 -> action1 | B7: =recouvrement_dette!E2 -> 75000 | E7: =recouvrement_dette!G2 -> 0 | F7: =E7*B7 -> 0 | G7: 75000 | H7: =SUM(recouvrement_dette!I2:AG2) -> 25000 | I7: =H7/G7 -> 0.33333333 | J7: =G7-H7 -> 50000 | K7: 10 oct. 2025 | L7: Prêt antérieur à la microfinance
A8: =recouvrement_dette!B3 -> action2 | B8: =recouvrement_dette!E3 -> 2400000 | C8: =recouvrement_dette!C3 -> Fev. 2025 | D8: =recouvrement_dette!F3 -> 20 | E8: =recouvrement_dette!G3 -> 0.2 | F8: =E8*B8 -> 480000 | G8: =B8+F8 -> 2880000 | H8: =SUM(recouvrement_dette!I3:AG3) -> 1540000 | I8: =H8/G8 -> 0.53472222 | J8: =G8-H8 -> 1340000 | K8: =recouvrement_dette!D3 -> 10 Oct. 2026 | L8: Prêt microfinance
A9: =recouvrement_dette!B4 -> action3 | B9: =recouvrement_dette!E4 -> 5500000 | C9: =recouvrement_dette!C4 -> Août 2025 | D9: =recouvrement_dette!F4 -> 10 | E9: =recouvrement_dette!G4 -> 0.1 | F9: =E9*B9 -> 550000 | G9: =B9+F9 -> 6050000 | H9: =SUM(recouvrement_dette!I4:AG4) -> 2670000 | I9: =H9/G9 -> 0.44132231 | J9: =G9-H9 -> 3380000 | K9: =recouvrement_dette!D4 -> 10 Juil. 2026 | L9: Prêt microfinance
A10: =recouvrement_dette!B5 -> action4 | B10: =recouvrement_dette!E5 -> 300000 | C10: =recouvrement_dette!C5 -> Août 2025 | D10: =recouvrement_dette!F5 -> 12 | E10: =recouvrement_dette!G5 -> 0.18 | F10: =E10*B10 -> 54000 | G10: =B10+F10 -> 354000 | H10: =SUM(recouvrement_dette!I5:AG5) -> 118000 | I10: =H10/G10 -> 0.33333333 | J10: =G10-H10 -> 236000 | K10: =recouvrement_dette!D5 -> 10 Sept. 2026 | L10: Prêt remboursé
A11: =recouvrement_dette!B6 -> action5 | B11: =recouvrement_dette!E6 -> 1850000 | C11: =recouvrement_dette!C6 -> Août 2025 | D11: =recouvrement_dette!F6 -> 24 | E11: =recouvrement_dette!G6 -> 0.24 | F11: =E11*B11 -> 444000 | G11: =B11+F11 -> 2294000 | H11: =SUM(recouvrement_dette!I6:AG6) -> 400000 | I11: =H11/G11 -> 0.17436792 | J11: =G11-H11 -> 1894000 | K11: =recouvrement_dette!D6 -> 10 Sept. 2027 | L11: Prêt remboursé
A12: =recouvrement_dette!B7 -> action6 | B12: =recouvrement_dette!E7 -> 3700000 | C12: =recouvrement_dette!C7 -> Août 2025 | D12: =recouvrement_dette!F7 -> 12 | E12: =recouvrement_dette!G7 -> 0.12 | F12: =E12*B12 -> 444000 | G12: =B12+F12 -> 4144000 | H12: =SUM(recouvrement_dette!I7:AG7) -> 1364334 | I12: =H12/G12 -> 0.32923118 | J12: =G12-H12 -> 2779666 | K12: =recouvrement_dette!D7 -> 10 Sept. 2026 | L12: Prêt remboursé
A13: =recouvrement_dette!B8 -> action7 | B13: =recouvrement_dette!E8 -> 4000000 | C13: =recouvrement_dette!C8 -> Août 2025 | D13: =recouvrement_dette!F8 -> 12 | E13: =recouvrement_dette!G8 -> 0.12 | F13: =E13*B13 -> 480000 | G13: =B13+F13 -> 4480000 | H13: =SUM(recouvrement_dette!I8:AG8) -> 1493333 | I13: =H13/G13 -> 0.33333326 | J13: =G13-H13 -> 2986667 | K13: =recouvrement_dette!D8 -> 10 Sept. 2026 | L13: Prêt microfinance
A14: =recouvrement_dette!B9 -> action8 | B14: =recouvrement_dette!E9 -> 4000000 | C14: =recouvrement_dette!C9 -> Août 2025 | D14: =recouvrement_dette!F9 -> 10 | E14: =recouvrement_dette!G9 -> 0.1 | F14: =E14*B14 -> 400000 | G14: =B14+F14 -> 4400000 | H14: =SUM(recouvrement_dette!I9:AG9) -> 1600000 | I14: =H14/G14 -> 0.36363636 | J14: =G14-H14 -> 2800000 | K14: =recouvrement_dette!D9 -> 10 Juil. 2026 | L14: Prêt microfinance
A15: =recouvrement_dette!B10 -> action9 | B15: =recouvrement_dette!E10 -> 1150000 | C15: =recouvrement_dette!C10 -> Août 2025 | D15: =recouvrement_dette!F10 -> 12 | E15: =recouvrement_dette!G10 -> 0.12 | F15: =E15*B15 -> 138000 | G15: =B15+F15 -> 1288000 | H15: =SUM(recouvrement_dette!I10:AG10) -> 310000 | I15: =H15/G15 -> 0.24068323 | J15: =G15-H15 -> 978000 | K15: =recouvrement_dette!D10 -> 10 Sept. 2026 | L15: Prêt remboursé
A16: =recouvrement_dette!B11 -> action10 | B16: =recouvrement_dette!E11 -> 4000000 | C16: =recouvrement_dette!C11 -> Août 2025 | D16: =recouvrement_dette!F11 -> 9 | E16: =recouvrement_dette!G11 -> 0.09 | F16: =E16*B16 -> 360000 | G16: =B16+F16 -> 4360000 | H16: =SUM(recouvrement_dette!I11:AG11) -> 1940000 | I16: =H16/G16 -> 0.44495413 | J16: =G16-H16 -> 2420000 | K16: =recouvrement_dette!D11 -> 10 Juin. 2026 | L16: Prêt remboursé
A17: =recouvrement_dette!B12 -> action11 | B17: =recouvrement_dette!E12 -> 4000000 | C17: =recouvrement_dette!C12 -> Août 2025 | D17: =recouvrement_dette!F12 -> 12 | E17: =recouvrement_dette!G12 -> 0.12 | F17: =E17*B17 -> 480000 | G17: =B17+F17 -> 4480000 | H17: =SUM(recouvrement_dette!I12:AG12) -> 1493333 | I17: =H17/G17 -> 0.33333326 | J17: =G17-H17 -> 2986667 | K17: =recouvrement_dette!D12 -> 10 Sept. 2026 | L17: Prêt remboursé
A18: =recouvrement_dette!B13 -> action12 | B18: =recouvrement_dette!E13 -> 1500000 | C18: =recouvrement_dette!C13 -> Août 2025 | D18: =recouvrement_dette!F13 -> 10 | E18: =recouvrement_dette!G13 -> 0.1 | F18: =E18*B18 -> 150000 | G18: =B18+F18 -> 1650000 | H18: =SUM(recouvrement_dette!I13:AG13) -> 495000 | I18: =H18/G18 -> 0.3 | J18: =G18-H18 -> 1155000 | K18: =recouvrement_dette!D13 -> 10 Juil. 2026 | L18: Prêt remboursé
A19: =recouvrement_dette!B14 -> action13 | B19: =recouvrement_dette!E14 -> 3000000 | C19: =recouvrement_dette!C14 -> Août 2025 | D19: =recouvrement_dette!F14 -> 12 | E19: =recouvrement_dette!G14 -> 0.12 | F19: =E19*B19 -> 360000 | G19: =B19+F19 -> 3360000 | H19: =SUM(recouvrement_dette!I14:AG14) -> 840000 | I19: =H19/G19 -> 0.25 | J19: =G19-H19 -> 2520000 | K19: =recouvrement_dette!D14 -> 10 Sept. 2026 | L19: Prêt remboursé
... A44: =recouvrement_dette!B39 -> 0 | B44: =recouvrement_dette!E39 -> 0 | C44: =recouvrement_dette!C39 -> 0 | D44: =recouvrement_dette!F39 -> 0 | E44: =recouvrement_dette!G39 -> 0 | F44: =E44*B44 -> 0 | G44: =B44+F44 -> 0 | H44: =SUM(recouvrement_dette!I39:AG39) -> 0 | I44: =H44/G44 -> #DIV/0! | J44: =G44-H44 -> 0 | K44: =recouvrement_dette!D39 -> 0 | L44: Prêt microfinance
A45: Total | B45: =SUM(B8:B44) -> 52070000 | F45: =SUM(F8:F44) -> 6261400 | G45: =SUM(G8:G44) -> 58331400 | H45: =SUM(H7:H44) -> 17341000 | I45: =H45/G45 -> 0.29728414 | J45: =SUM(J8:J44) -> 41015400
A46: *En texte rouge, les personnes n'ayant pas encore soldé leurs dettes à l'échéance
A49: * En fond vert, les personnes ayant soldé leurs dettes

Sheet Synthese_cassation
I1: =recap_prêt!L4 -> Janvier. 2026
A3: N° | B3: Nom épargnant | C3: Total épargne | D3: Total intérêt | E3: Total théorique à percevoir | F3: Bonus/Malus apuration anciennes dettes | G3: Total théorique +Bonus-Malus | H3: Intérêt relatif | I3: Part relative | J3: Total net à percevoir
A4: =IF(apport_mensuel_calcul!A2=0,"",apport_mensuel_calcul!A2) -> 1 | B4: =IF(apport_mensuel_calcul!B2=0,"",apport_mensuel_calcul!B2) -> ACTIONNIRE1 | C4: =IF(apport_mensuel_calcul!BV2=0,"",apport_mensuel_calcul!BV2) -> 981801.77 | D4: =IF(apport_mensuel_calcul!BW2=0,"",apport_mensuel_calcul!BW2) -> 161474.28 | E4: =IF(apport_mensuel_calcul!BX2=0,"",apport_mensuel_calcul!BX2) -> 1143276.1 | F4: =IF(apport_mensuel_calcul!BY2=0,"",apport_mensuel_calcul!BY2) | G4: =IF(apport_mensuel_calcul!BZ2=0,"",apport_mensuel_calcul!BZ2) -> 1143276.1 | H4: =IF(apport_mensuel_calcul!CA2=0,"",apport_mensuel_calcul!CA2) -> 0.16446729 | I4: =IF(apport_mensuel_calcul!CB2=0,"",apport_mensuel_calcul!CB2) -> 0.025200719 | J4: =IF(apport_mensuel_calcul!CC2=0,"",apport_mensuel_calcul!CC2) -> 109088.95
A5: =IF(apport_mensuel_calcul!A3=0,"",apport_mensuel_calcul!A3) -> 2 | B5: =IF(apport_mensuel_calcul!B3=0,"",apport_mensuel_calcul!B3) -> ACTIONNIRE2 | C5: =IF(apport_mensuel_calcul!BV3=0,"",apport_mensuel_calcul!BV3) -> 570897.47 | D5: =IF(apport_mensuel_calcul!BW3=0,"",apport_mensuel_calcul!BW3) -> 86449.043 | E5: =IF(apport_mensuel_calcul!BX3=0,"",apport_mensuel_calcul!BX3) -> 657346.51 | F5: =IF(apport_mensuel_calcul!BY3=0,"",apport_mensuel_calcul!BY3) | G5: =IF(apport_mensuel_calcul!BZ3=0,"",apport_mensuel_calcul!BZ3) -> 657346.51 | H5: =IF(apport_mensuel_calcul!CA3=0,"",apport_mensuel_calcul!CA3) -> 0.15142657 | I5: =IF(apport_mensuel_calcul!CB3=0,"",apport_mensuel_calcul!CB3) -> 0.014489593 | J5: =IF(apport_mensuel_calcul!CC3=0,"",apport_mensuel_calcul!CC3) -> 62722.594
A6: =IF(apport_mensuel_calcul!A4=0,"",apport_mensuel_calcul!A4) -> 3 | B6: =IF(apport_mensuel_calcul!B4=0,"",apport_mensuel_calcul!B4) -> ACTIONNIRE3 | C6: =IF(apport_mensuel_calcul!BV4=0,"",apport_mensuel_calcul!BV4) -> 4008079.8 | D6: =IF(apport_mensuel_calcul!BW4=0,"",apport_mensuel_calcul!BW4) -> 667719.35 | E6: =IF(apport_mensuel_calcul!BX4=0,"",apport_mensuel_calcul!BX4) -> 4675799.1 | F6: =IF(apport_mensuel_calcul!BY4=0,"",apport_mensuel_calcul!BY4) | G6: =IF(apport_mensuel_calcul!BZ4=0,"",apport_mensuel_calcul!BZ4) -> 4675799.1 | H6: =IF(apport_mensuel_calcul!CA4=0,"",apport_mensuel_calcul!CA4) -> 0.16659333 | I6: =IF(apport_mensuel_calcul!CB4=0,"",apport_mensuel_calcul!CB4) -> 0.10306653 | J6: =IF(apport_mensuel_calcul!CC4=0,"",apport_mensuel_calcul!CC4) -> 446154.72
A7: =IF(apport_mensuel_calcul!A5=0,"",apport_mensuel_calcul!A5) -> 4 | B7: =IF(apport_mensuel_calcul!B5=0,"",apport_mensuel_calcul!B5) -> ACTIONNIRE4 | C7: =IF(apport_mensuel_calcul!BV5=0,"",apport_mensuel_calcul!BV5) -> 372369.77 | D7: =IF(apport_mensuel_calcul!BW5=0,"",apport_mensuel_calcul!BW5) -> 62034.319 | E7: =IF(apport_mensuel_calcul!BX5=0,"",apport_mensuel_calcul!BX5) -> 434404.08 | F7: =IF(apport_mensuel_calcul!BY5=0,"",apport_mensuel_calcul!BY5) | G7: =IF(apport_mensuel_calcul!BZ5=0,"",apport_mensuel_calcul!BZ5) -> 434404.08 | H7: =IF(apport_mensuel_calcul!CA5=0,"",apport_mensuel_calcul!CA5) -> 0.16659333 | I7: =IF(apport_mensuel_calcul!CB5=0,"",apport_mensuel_calcul!CB5) -> 0.0095753735 | J7: =IF(apport_mensuel_calcul!CC5=0,"",apport_mensuel_calcul!CC5) -> 41449.905
A8: =IF(apport_mensuel_calcul!A6=0,"",apport_mensuel_calcul!A6) -> 5 | B8: =IF(apport_mensuel_calcul!B6=0,"",apport_mensuel_calcul!B6) -> ACTIONNIRE5 | C8: =IF(apport_mensuel_calcul!BV6=0,"",apport_mensuel_calcul!BV6) -> 1393753.8 | D8: =IF(apport_mensuel_calcul!BW6=0,"",apport_mensuel_calcul!BW6) -> 232190.09 | E8: =IF(apport_mensuel_calcul!BX6=0,"",apport_mensuel_calcul!BX6) -> 1625943.9 | F8: =IF(apport_mensuel_calcul!BY6=0,"",apport_mensuel_calcul!BY6) | G8: =IF(apport_mensuel_calcul!BZ6=0,"",apport_mensuel_calcul!BZ6) -> 1625943.9 | H8: =IF(apport_mensuel_calcul!CA6=0,"",apport_mensuel_calcul!CA6) -> 0.16659333 | I8: =IF(apport_mensuel_calcul!CB6=0,"",apport_mensuel_calcul!CB6) -> 0.035839949 | J8: =IF(apport_mensuel_calcul!CC6=0,"",apport_mensuel_calcul!CC6) -> 155144.08
A9: =IF(apport_mensuel_calcul!A7=0,"",apport_mensuel_calcul!A7) -> 6 | B9: =IF(apport_mensuel_calcul!B7=0,"",apport_mensuel_calcul!B7) -> ACTIONNIRE6 | C9: =IF(apport_mensuel_calcul!BV7=0,"",apport_mensuel_calcul!BV7) -> 829601.83 | D9: =IF(apport_mensuel_calcul!BW7=0,"",apport_mensuel_calcul!BW7) -> 138206.13 | E9: =IF(apport_mensuel_calcul!BX7=0,"",apport_mensuel_calcul!BX7) -> 967807.96 | F9: =IF(apport_mensuel_calcul!BY7=0,"",apport_mensuel_calcul!BY7) | G9: =IF(apport_mensuel_calcul!BZ7=0,"",apport_mensuel_calcul!BZ7) -> 967807.96 | H9: =IF(apport_mensuel_calcul!CA7=0,"",apport_mensuel_calcul!CA7) -> 0.16659333 | I9: =IF(apport_mensuel_calcul!CB7=0,"",apport_mensuel_calcul!CB7) -> 0.021332955 | J9: =IF(apport_mensuel_calcul!CC7=0,"",apport_mensuel_calcul!CC7) -> 92346.159
A10: =IF(apport_mensuel_calcul!A8=0,"",apport_mensuel_calcul!A8) -> 7 | B10: =IF(apport_mensuel_calcul!B8=0,"",apport_mensuel_calcul!B8) -> ACTIONNIRE7 | C10: =IF(apport_mensuel_calcul!BV8=0,"",apport_mensuel_calcul!BV8) -> 840018.32 | D10: =IF(apport_mensuel_calcul!BW8=0,"",apport_mensuel_calcul!BW8) -> 139941.45 | E10: =IF(apport_mensuel_calcul!BX8=0,"",apport_mensuel_calcul!BX8) -> 979959.77 | F10: =IF(apport_mensuel_calcul!BY8=0,"",apport_mensuel_calcul!BY8) | G10: =IF(apport_mensuel_calcul!BZ8=0,"",apport_mensuel_calcul!BZ8) -> 979959.77 | H10: =IF(apport_mensuel_calcul!CA8=0,"",apport_mensuel_calcul!CA8) -> 0.16659333 | I10: =IF(apport_mensuel_calcul!CB8=0,"",apport_mensuel_calcul!CB8) -> 0.021600812 | J10: =IF(apport_mensuel_calcul!CC8=0,"",apport_mensuel_calcul!CC8) -> 93505.658
A11: =IF(apport_mensuel_calcul!A9=0,"",apport_mensuel_calcul!A9) -> 8 | B11: =IF(apport_mensuel_calcul!B9=0,"",apport_mensuel_calcul!B9) -> ACTIONNIRE8 | C11: =IF(apport_mensuel_calcul!BV9=0,"",apport_mensuel_calcul!BV9) -> 6000758.2 | D11: =IF(apport_mensuel_calcul!BW9=0,"",apport_mensuel_calcul!BW9) -> 970824.06 | E11: =IF(apport_mensuel_calcul!BX9=0,"",apport_mensuel_calcul!BX9) -> 6971582.3 | F11: =IF(apport_mensuel_calcul!BY9=0,"",apport_mensuel_calcul!BY9) | G11: =IF(apport_mensuel_calcul!BZ9=0,"",apport_mensuel_calcul!BZ9) -> 6971582.3 | H11: =IF(apport_mensuel_calcul!CA9=0,"",apport_mensuel_calcul!CA9) -> 0.16178357 | I11: =IF(apport_mensuel_calcul!CB9=0,"",apport_mensuel_calcul!CB9) -> 0.15367145 | J11: =IF(apport_mensuel_calcul!CC9=0,"",apport_mensuel_calcul!CC9) -> 665213.42
A12: =IF(apport_mensuel_calcul!A10=0,"",apport_mensuel_calcul!A10) -> 9 | B12: =IF(apport_mensuel_calcul!B10=0,"",apport_mensuel_calcul!B10) -> ACTIONNIRE9 | C12: =IF(apport_mensuel_calcul!BV10=0,"",apport_mensuel_calcul!BV10) -> 539026.95 | D12: =IF(apport_mensuel_calcul!BW10=0,"",apport_mensuel_calcul!BW10) -> 89798.294 | E12: =IF(apport_mensuel_calcul!BX10=0,"",apport_mensuel_calcul!BX10) -> 628825.25 | F12: =IF(apport_mensuel_calcul!BY10=0,"",apport_mensuel_calcul!BY10) | G12: =IF(apport_mensuel_calcul!BZ10=0,"",apport_mensuel_calcul!BZ10) -> 628825.25 | H12: =IF(apport_mensuel_calcul!CA10=0,"",apport_mensuel_calcul!CA10) -> 0.16659333 | I12: =IF(apport_mensuel_calcul!CB10=0,"",apport_mensuel_calcul!CB10) -> 0.013860912 | J12: =IF(apport_mensuel_calcul!CC10=0,"",apport_mensuel_calcul!CC10) -> 60001.156
A13: =IF(apport_mensuel_calcul!A11=0,"",apport_mensuel_calcul!A11) -> 10 | B13: =IF(apport_mensuel_calcul!B11=0,"",apport_mensuel_calcul!B11) -> ACTIONNIRE10 | C13: =IF(apport_mensuel_calcul!BV11=0,"",apport_mensuel_calcul!BV11) -> 502772.09 | D13: =IF(apport_mensuel_calcul!BW11=0,"",apport_mensuel_calcul!BW11) -> 83098.247 | E13: =IF(apport_mensuel_calcul!BX11=0,"",apport_mensuel_calcul!BX11) -> 585870.34 | F13: =IF(apport_mensuel_calcul!BY11=0,"",apport_mensuel_calcul!BY11) | G13: =IF(apport_mensuel_calcul!BZ11=0,"",apport_mensuel_calcul!BZ11) -> 585870.34 | H13: =IF(apport_mensuel_calcul!CA11=0,"",apport_mensuel_calcul!CA11) -> 0.16528015 | I13: =IF(apport_mensuel_calcul!CB11=0,"",apport_mensuel_calcul!CB11) -> 0.012914076 | J13: =IF(apport_mensuel_calcul!CC11=0,"",apport_mensuel_calcul!CC11) -> 55902.49
A14: =IF(apport_mensuel_calcul!A12=0,"",apport_mensuel_calcul!A12) -> 11 | B14: =IF(apport_mensuel_calcul!B12=0,"",apport_mensuel_calcul!B12) -> ACTIONNIRE11 | C14: =IF(apport_mensuel_calcul!BV12=0,"",apport_mensuel_calcul!BV12) -> 1086673.4 | D14: =IF(apport_mensuel_calcul!BW12=0,"",apport_mensuel_calcul!BW12) -> 180504.36 | E14: =IF(apport_mensuel_calcul!BX12=0,"",apport_mensuel_calcul!BX12) -> 1267177.8 | F14: =IF(apport_mensuel_calcul!BY12=0,"",apport_mensuel_calcul!BY12) | G14: =IF(apport_mensuel_calcul!BZ12=0,"",apport_mensuel_calcul!BZ12) -> 1267177.8 | H14: =IF(apport_mensuel_calcul!CA12=0,"",apport_mensuel_calcul!CA12) -> 0.16610727 | I14: =IF(apport_mensuel_calcul!CB12=0,"",apport_mensuel_calcul!CB12) -> 0.027931829 | J14: =IF(apport_mensuel_calcul!CC12=0,"",apport_mensuel_calcul!CC12) -> 120911.39
A15: =IF(apport_mensuel_calcul!A13=0,"",apport_mensuel_calcul!A13) -> 12 | B15: =IF(apport_mensuel_calcul!B13=0,"",apport_mensuel_calcul!B13) -> ACTIONNIRE12 | C15: =IF(apport_mensuel_calcul!BV13=0,"",apport_mensuel_calcul!BV13) -> 472273.11 | D15: =IF(apport_mensuel_calcul!BW13=0,"",apport_mensuel_calcul!BW13) -> 78677.549 | E15: =IF(apport_mensuel_calcul!BX13=0,"",apport_mensuel_calcul!BX13) -> 550950.66 | F15: =IF(apport_mensuel_calcul!BY13=0,"",apport_mensuel_calcul!BY13) | G15: =IF(apport_mensuel_calcul!BZ13=0,"",apport_mensuel_calcul!BZ13) -> 550950.66 | H15: =IF(apport_mensuel_calcul!CA13=0,"",apport_mensuel_calcul!CA13) -> 0.16659333 | I15: =IF(apport_mensuel_calcul!CB13=0,"",apport_mensuel_calcul!CB13) -> 0.012144357 | J15: =IF(apport_mensuel_calcul!CC13=0,"",apport_mensuel_calcul!CC13) -> 52570.53
... A47: =IF(apport_mensuel_calcul!A45=0,"",apport_mensuel_calcul!A45) | B47: =IF(apport_mensuel_calcul!B45=0,"",apport_mensuel_calcul!B45) | C47: =IF(apport_mensuel_calcul!BV45=0,"",apport_mensuel_calcul!BV45) | D47: =IF(apport_mensuel_calcul!BW45=0,"",apport_mensuel_calcul!BW45) | E47: =IF(apport_mensuel_calcul!BX45=0,"",apport_mensuel_calcul!BX45) | F47: =IF(apport_mensuel_calcul!BY45=0,"",apport_mensuel_calcul!BY45) | G47: =IF(apport_mensuel_calcul!BZ45=0,"",apport_mensuel_calcul!BZ45) | H47: =IF(apport_mensuel_calcul!CA45=0,"",apport_mensuel_calcul!CA45) | I47: =IF(apport_mensuel_calcul!CB45=0,"",apport_mensuel_calcul!CB45) | J47: =IF(apport_mensuel_calcul!CC45=0,"",apport_mensuel_calcul!CC45)
A48: Total | C48: =apport_mensuel_calcul!BV48 -> 39105403 | D48: =apport_mensuel_calcul!BW48 -> 6261400 | E48: =apport_mensuel_calcul!BX48 -> 45366803 | F48: =apport_mensuel_calcul!BY48 -> 0 | G48: =apport_mensuel_calcul!BZ48 -> 45366803 | H48: =apport_mensuel_calcul!CA48 -> 0.16011598 | I48: =apport_mensuel_calcul!CB48 -> 1 | J48: =apport_mensuel_calcul!CC48 -> 4328803
C50: Prêts en cours: | E50: =apport_mensuel_calcul!BX49 -> 42292370
B51: Solde en caisse: | C51: =apport_mensuel_calcul!BW50 -> 4328803
A53: Total prêt nouveau tournoi: | C53: =apport_mensuel_calcul!BW52 -> 52000000
A54: Total intérêt nouveau tournoi: | C54: =apport_mensuel_calcul!BW53 -> 6261400
A55: Total remboursé nouveau tournoi: | C55: =apport_mensuel_calcul!BW54-SUM(recouvrement_dette!J2:N2) -> 17316000
B56: Taux remboursement: | C56: =C55/(C54+C53) -> 0.29721222
B58: Total pénalité: | C58: =apport_mensuel_calcul!BW57 -> 0

Sheet Feuil10
A1: Prêts en cours: | C1: 7463630
A2: 7886397 | C2: =A2+C1 -> 15350027
C3: =C2-apport_mensuel_calcul!BX48 -> -30016776

Sheet pret
A1: N° | B1: Nom épargnant | C1: Date dette | D1: Échéance dette | E1: Montant dette | F1: Durée dette (en mois) | G1: Taux intérêt | H1: Intérêt | I1: 45839 | J1: 45870 | K1: 45901 | L1: 45931 | M1: 45962 | N1: 45992 | O1: 46023 | P1: 46054 | Q1: 46082 | R1: 46113 | S1: 46143 | T1: 46174 | U1: 46204 | V1: 46235 | W1: 46266 | X1: 46296 | Y1: 46327 | Z1: 46357 | AA1: 46388 | AB1: 46419 | AC1: 46447 | AD1: 46478 | AE1: 46508 | AF1: 46539 | AG1: 46569
A2: 1 | B2: YIMKWAN Christel | E2: 75000 | G2: =H2/E2 -> 0
A3: 2 | B3: KUITCHE Chevalier | C3: Fev. 2025 | D3: 10 Oct. 2026 | E3: 2400000 | F3: 20 | G3: 0.2 | H3: =G3*E3 -> 480000 | J3: 2400000
A4: 5 | B4: =recouvrement_dette!B4 -> action3 | C4: Août 2025 | D4: 10 Juil. 2026 | E4: 5500000 | F4: 10 | G4: =IF(E4<1000000,F4*1.5%,F4*1%) -> 0.1 | H4: =G4*E4 -> 550000 | J4: 5500000
A5: 6 | B5: =recouvrement_dette!B5 -> action4 | C5: Août 2025 | D5: 10 Sept. 2026 | E5: 300000 | F5: 12 | G5: =IF(E5<1000000,F5*1.5%,F5*1%) -> 0.18 | H5: =G5*E5 -> 54000 | J5: 300000
A6: 7 | B6: =recouvrement_dette!B6 -> action5 | C6: Août 2025 | D6: 10 Sept. 2027 | E6: 1850000 | F6: 24 | G6: =IF(E6<1000000,F6*1.5%,F6*1%) -> 0.24 | H6: =G6*E6 -> 444000 | J6: 1850000
A7: 8 | B7: =recouvrement_dette!B7 -> action6 | C7: Août 2025 | D7: 10 Sept. 2026 | E7: 3700000 | F7: 12 | G7: =IF(E7<1000000,F7*1.5%,F7*1%) -> 0.12 | H7: =G7*E7 -> 444000 | J7: 3700000
A8: 9 | B8: =recouvrement_dette!B8 -> action7 | C8: Août 2025 | D8: 10 Sept. 2026 | E8: 4000000 | F8: 12 | G8: =IF(E8<1000000,F8*1.5%,F8*1%) -> 0.12 | H8: =G8*E8 -> 480000 | J8: 4000000
A9: 10 | B9: =recouvrement_dette!B9 -> action8 | C9: Août 2025 | D9: 10 Juil. 2026 | E9: 4000000 | F9: 10 | G9: =IF(E9<1000000,F9*1.5%,F9*1%) -> 0.1 | H9: =G9*E9 -> 400000 | J9: 4000000
A10: 11 | B10: =recouvrement_dette!B10 -> action9 | C10: Août 2025 | D10: 10 Sept. 2026 | E10: 1150000 | F10: 12 | G10: =IF(E10<1000000,F10*1.5%,F10*1%) -> 0.12 | H10: =G10*E10 -> 138000 | J10: 1150000
A11: 12 | B11: =recouvrement_dette!B11 -> action10 | C11: Août 2025 | D11: 10 Juin. 2026 | E11: 4000000 | F11: 9 | G11: =IF(E11<1000000,F11*1.5%,F11*1%) -> 0.09 | H11: =G11*E11 -> 360000 | J11: 4000000
A12: 13 | B12: =recouvrement_dette!B12 -> action11 | C12: Août 2025 | D12: 10 Sept. 2026 | E12: 4000000 | F12: 12 | G12: =IF(E12<1000000,F12*1.5%,F12*1%) -> 0.12 | H12: =G12*E12 -> 480000 | J12: 4000000
A13: 14 | B13: =recouvrement_dette!B13 -> action12 | C13: Août 2025 | D13: 10 Juil. 2026 | E13: 1500000 | F13: 10 | G13: =IF(E13<1000000,F13*1.5%,F13*1%) -> 0.1 | H13: =G13*E13 -> 150000 | J13: 1500000
A14: 14 | B14: =recouvrement_dette!B14 -> action13 | C14: Août 2025 | D14: 10 Sept. 2026 | E14: 3000000 | F14: 12 | G14: =IF(E14<1000000,F14*1.5%,F14*1%) -> 0.12 | H14: =G14*E14 -> 360000 | J14: 3000000
A15: 14 | B15: =recouvrement_dette!B15 -> action14 | C15: =recouvrement_dette!C15 -> Octobre 2025 | D15: =recouvrement_dette!D15 -> 10 Mai. 2027 | E15: =recouvrement_dette!E15 -> 3000000 | F15: =recouvrement_dette!F15 -> 18 | G15: =IF(E15<1000000,F15*1.5%,F15*1%) -> 0.18 | H15: =G15*E15 -> 540000 | L15: 3000000
A16: 14 | B16: =recouvrement_dette!B16 -> action15 | C16: =recouvrement_dette!C16 -> Octobre 2025 | D16: =recouvrement_dette!D16 -> 10 Sept. 2026 | E16: =recouvrement_dette!E16 -> 2500000 | F16: =recouvrement_dette!F16 -> 10 | G16: =IF(E16<1000000,F16*1.5%,F16*1%) -> 0.1 | H16: =G16*E16 -> 250000 | L16: 2500000
A17: 14 | B17: =recouvrement_dette!B17 -> action16 | C17: =recouvrement_dette!C17 -> Octobre 2025 | D17: =recouvrement_dette!D17 -> 10 Fév. 2026 | E17: =recouvrement_dette!E17 -> 1000000 | F17: =recouvrement_dette!F17 -> 3 | G17: =IF(E17<1000000,F17*1.5%,F17*1%) -> 0.03 | H17: =G17*E17 -> 30000 | L17: 1000000
A18: 14 | B18: =recouvrement_dette!B18 -> action17 | C18: Novemvre 2025 | D18: 10 Déc. 2026 | E18: 1570000 | F18: 12 | G18: =IF(E18<1000000,F18*1.5%,F18*1%) -> 0.12 | H18: =G18*E18 -> 188400 | M18: 1500000
A19: 14 | B19: =recouvrement_dette!B19 -> action18 | C19: Novemvre 2025 | D19: 10 Mars. 2026 | E19: 3100000 | F19: 3 | G19: =IF(E19<1000000,F19*1.5%,F19*1%) -> 0.03 | H19: =G19*E19 -> 93000 | M19: 3100000
A20: 14 | B20: =recouvrement_dette!B20 -> action19 | C20: Decembre 2025 | D20: 10 Mai 2025 | E20: 2500000 | F20: 4 | G20: =IF(E20<1000000,F20*1.5%,F20*1%) -> 0.04 | H20: =G20*E20 -> 100000 | N20: 2500000
A21: 14 | B21: =recouvrement_dette!B21 -> action20 | C21: Janvier 2026 | D21: 10 Fév. 2028 | E21: 3000000 | F21: 24 | G21: =IF(E21<1000000,F21*1.5%,F21*1%) -> 0.24 | H21: =G21*E21 -> 720000 | O21: 3000000
A22: 14 | B22: =recouvrement_dette!B22 -> 0 | G22: =IF(E22<1000000,F22*1.5%,F22*1%) -> 0 | H22: =G22*E22 -> 0
A23: 14 | B23: =recouvrement_dette!B23 -> 0 | G23: =IF(E23<1000000,F23*1.5%,F23*1%) -> 0 | H23: =G23*E23 -> 0
A24: 14 | B24: =recouvrement_dette!B24 -> 0 | G24: =IF(E24<1000000,F24*1.5%,F24*1%) -> 0 | H24: =G24*E24 -> 0
A25: 14 | B25: =recouvrement_dette!B25 -> 0 | G25: =IF(E25<1000000,F25*1.5%,F25*1%) -> 0 | H25: =G25*E25 -> 0
A26: 14 | B26: =recouvrement_dette!B26 -> 0 | G26: =IF(E26<1000000,F26*1.5%,F26*1%) -> 0 | H26: =G26*E26 -> 0
A27: 14 | B27: =recouvrement_dette!B27 -> 0 | G27: =IF(E27<1000000,F27*1.5%,F27*1%) -> 0 | H27: =G27*E27 -> 0
B28: =recouvrement_dette!B28 -> 0 | G28: =IF(E28<1000000,F28*1.5%,F28*1%) -> 0 | H28: =G28*E28 -> 0
A29: 9 | B29: =recouvrement_dette!B29 -> 0 | G29: =IF(E29<1000000,F29*1.5%,F29*1%) -> 0 | H29: =G29*E29 -> 0
A30: 14 | B30: =recouvrement_dette!B30 -> 0 | G30: =IF(E30<1000000,F30*1.5%,F30*1%) -> 0 | H30: =G30*E30 -> 0
A31: 14 | B31: =recouvrement_dette!B31 -> 0 | G31: =IF(E31<1000000,F31*1.5%,F31*1%) -> 0 | H31: =G31*E31 -> 0
A32: 14 | B32: =recouvrement_dette!B32 -> 0 | G32: =IF(E32<1000000,F32*1.5%,F32*1%) -> 0 | H32: =G32*E32 -> 0
A33: 14 | B33: =recouvrement_dette!B33 -> 0 | G33: =IF(E33<1000000,F33*1.5%,F33*1%) -> 0 | H33: =G33*E33 -> 0
A34: 14 | B34: =recouvrement_dette!B34 -> 0 | G34: =IF(E34<1000000,F34*1.5%,F34*1%) -> 0 | H34: =G34*E34 -> 0
A35: 14 | B35: =recouvrement_dette!B35 -> 0 | G35: =IF(E35<1000000,F35*1.5%,F35*1%) -> 0 | H35: =G35*E35 -> 0
A36: 14 | B36: =recouvrement_dette!B36 -> 0 | G36: =IF(E36<1000000,F36*1.5%,F36*1%) -> 0 | H36: =G36*E36 -> 0
A37: 14 | B37: =recouvrement_dette!B37 -> 0 | G37: =IF(E37<1000000,F37*1.5%,F37*1%) -> 0 | H37: =G37*E37 -> 0
A38: 14 | B38: =recouvrement_dette!B38 -> 0 | G38: =IF(E38<1000000,F38*1.5%,F38*1%) -> 0 | H38: =G38*E38 -> 0
A39: 14 | B39: =recouvrement_dette!B39 -> 0 | G39: =IF(E39<1000000,F39*1.5%,F39*1%) -> 0 | H39: =G39*E39 -> 0
A40: Total | C40: =SUM(C2:C4) -> 0 | D40: =SUM(D2:D4) -> 0 | I40: =SUM(I2:I39) -> 0 | J40: =SUM(J2:J39) -> 35400000 | K40: =SUM(K2:K39) -> 0 | L40: =SUM(L2:L39) -> 6500000 | M40: =SUM(M2:M39) -> 4600000 | N40: =SUM(N2:N39) -> 2500000 | O40: =SUM(O2:O39) -> 3000000 | P40: =SUM(P2:P39) -> 0 | ... AG40: =SUM(AG2:AG39) -> 0

Sheet _interet
A1: N° | B1: Nom épargnant | C1: Date dette | D1: Échéance dette | E1: Montant dette | F1: Durée dette (en mois) | G1: Taux intérêt | H1: Intérêt | I1: 45108 | J1: 45139 | K1: 45170 | L1: 45200 | M1: 45231 | N1: 45261 | O1: 45292 | P1: 45323 | Q1: 45352 | R1: 45383 | S1: 45413 | T1: 45444 | U1: 45474 | V1: 45505 | W1: 45536 | X1: 45566 | Y1: 45597 | Z1: 45627 | AA1: 45658 | AB1: 45689 | AC1: 45717 | AD1: 45748 | AE1: 45778 | AF1: 45809 | AG1: 45839
A2: 1 | B2: =+recouvrement_dette!B2 -> action1 | E2: 75000 | H2: 38030
A3: 2 | B3: =+recouvrement_dette!B3 -> action2 | C3: Fev. 2025 | D3: 10 Oct. 2026 | E3: 2400000 | F3: 20 | G3: =IF(E3<1000000,F3*1.5%,F3*1%) -> 0.2 | H3: =G3*E3 -> 480000 | J3: =$E3*$G3 -> 480000
A4: 3 | B4: =+recouvrement_dette!B4 -> action3 | C4: Août 2025 | D4: 10 Juil. 2026 | E4: 5500000 | F4: 10 | G4: =IF(E4<1000000,F4*1.5%,F4*1%) -> 0.1 | H4: =G4*E4 -> 550000 | J4: =$E4*$G4 -> 550000
A5: 4 | B5: =+recouvrement_dette!B5 -> action4 | C5: Août 2025 | D5: 10 Sept. 2026 | E5: 300000 | F5: 12 | G5: =IF(E5<1000000,F5*1.5%,F5*1%) -> 0.18 | H5: =G5*E5 -> 54000 | J5: =$E5*$G5 -> 54000
A6: 5 | B6: =+recouvrement_dette!B6 -> action5 | C6: Août 2025 | D6: 10 Sept. 2027 | E6: 1850000 | F6: 24 | G6: =IF(E6<1000000,F6*1.5%,F6*1%) -> 0.24 | H6: =G6*E6 -> 444000 | J6: =$E6*$G6 -> 444000
A7: 6 | B7: =+recouvrement_dette!B7 -> action6 | C7: Août 2025 | D7: 10 Sept. 2026 | E7: 3700000 | F7: 12 | G7: =IF(E7<1000000,F7*1.5%,F7*1%) -> 0.12 | H7: =G7*E7 -> 444000 | J7: =$E7*$G7 -> 444000
A8: 7 | B8: =+recouvrement_dette!B8 -> action7 | C8: Août 2025 | D8: 10 Sept. 2026 | E8: 4000000 | F8: 12 | G8: =IF(E8<1000000,F8*1.5%,F8*1%) -> 0.12 | H8: =G8*E8 -> 480000 | J8: =$E8*$G8 -> 480000
A9: 8 | B9: =+recouvrement_dette!B9 -> action8 | C9: Août 2025 | D9: 10 Juil. 2026 | E9: 4000000 | F9: 10 | G9: =IF(E9<1000000,F9*1.5%,F9*1%) -> 0.1 | H9: =G9*E9 -> 400000 | J9: =$E9*$G9 -> 400000
A10: 9 | B10: =+recouvrement_dette!B10 -> action9 | C10: Août 2025 | D10: 10 Sept. 2026 | E10: 1150000 | F10: 12 | G10: =IF(E10<1000000,F10*1.5%,F10*1%) -> 0.12 | H10: =G10*E10 -> 138000 | J10: =$E10*$G10 -> 138000
A11: 10 | B11: =+recouvrement_dette!B11 -> action10 | C11: Août 2025 | D11: 10 Juin. 2026 | E11: 4000000 | F11: 9 | G11: =IF(E11<1000000,F11*1.5%,F11*1%) -> 0.09 | H11: =G11*E11 -> 360000 | J11: =$E11*$G11 -> 360000
A12: 11 | B12: =+recouvrement_dette!B12 -> action11 | C12: Août 2025 | D12: 10 Sept. 2026 | E12: 4000000 | F12: 12 | G12: =IF(E12<1000000,F12*1.5%,F12*1%) -> 0.12 | H12: =G12*E12 -> 480000 | J12: =$E12*$G12 -> 480000
A13: 11 | B13: =+recouvrement_dette!B13 -> action12 | C13: Août 2025 | D13: 10 Juil. 2026 | E13: 1500000 | F13: 10 | G13: =IF(E13<1000000,F13*1.5%,F13*1%) -> 0.1 | H13: =G13*E13 -> 150000 | J13: =$E13*$G13 -> 150000
A14: 11 | B14: =+recouvrement_dette!B14 -> action13 | C14: Août 2025 | D14: 10 Sept. 2026 | E14: 3000000 | F14: 12 | G14: =IF(E14<1000000,F14*1.5%,F14*1%) -> 0.12 | H14: =G14*E14 -> 360000 | J14: =$E14*$G14 -> 360000
A15: 11 | B15: =+recouvrement_dette!B15 -> action14 | C15: =+recouvrement_dette!C15 -> Octobre 2025 | D15: =+recouvrement_dette!D15 -> 10 Mai. 2027 | E15: =+recouvrement_dette!E15 -> 3000000 | F15: =+recouvrement_dette!F15 -> 18 | G15: =+recouvrement_dette!G15 -> 0.18 | H15: =G15*E15 -> 540000 | L15: =$E15*$G15 -> 540000
A16: 11 | B16: =+recouvrement_dette!B16 -> action15 | C16: =+recouvrement_dette!C16 -> Octobre 2025 | D16: =+recouvrement_dette!D16 -> 10 Sept. 2026 | E16: =+recouvrement_dette!E16 -> 2500000 | F16: =+recouvrement_dette!F16 -> 10 | G16: =+recouvrement_dette!G16 -> 0.1 | H16: =G16*E16 -> 250000 | L16: =$E16*$G16 -> 250000
A17: 11 | B17: =+recouvrement_dette!B17 -> action16 | C17: =recouvrement_dette!C15 -> Octobre 2025 | D17: =recouvrement_dette!D15 -> 10 Mai. 2027 | E17: =+recouvrement_dette!E17 -> 1000000 | F17: =+recouvrement_dette!F17 -> 3 | G17: =+recouvrement_dette!G17 -> 0.03 | H17: =G17*E17 -> 30000 | L17: =$E17*$G17 -> 30000
A18: 11 | B18: =+recouvrement_dette!B18 -> action17 | C18: Novemvre 2025 | D18: 10 Déc. 2026 | E18: 1570000 | F18: 12 | G18: =recouvrement_dette!G18 -> 0.12 | H18: =G18*E18 -> 188400 | M18: =$E18*$G18 -> 188400
A19: 11 | B19: =+recouvrement_dette!B19 -> action18 | C19: Novemvre 2025 | D19: 10 Mars. 2026 | E19: 3100000 | F19: 3 | G19: =recouvrement_dette!G19 -> 0.03 | H19: =G19*E19 -> 93000 | M19: =$E19*$G19 -> 93000
A20: 11 | B20: =+recouvrement_dette!B20 -> action19 | C20: Décembre 2025 | D20: 10 Mai 2025 | E20: 2500000 | F20: 4 | G20: =recouvrement_dette!G20 -> 0.04 | H20: =G20*E20 -> 100000 | N20: =$E20*$G20 -> 100000
A21: 11 | B21: =+recouvrement_dette!B21 -> action20 | C21: Janvier 2026 | D21: 10 Fev. 2026 | E21: 3000000 | F21: 24 | G21: =recouvrement_dette!G21 -> 0.24 | H21: =G21*E21 -> 720000 | O21: =$E21*$G21 -> 720000
A22: 11 | B22: =+recouvrement_dette!B22 -> 0
A23: 11 | B23: =+recouvrement_dette!B23 -> 0
A24: 11 | B24: =+recouvrement_dette!B24 -> 0
A25: 11 | B25: =+recouvrement_dette!B25 -> 0
A26: 11 | B26: =+recouvrement_dette!B26 -> 0
A27: 11 | B27: =+recouvrement_dette!B27 -> 0
A28: 11 | B28: =+recouvrement_dette!B28 -> 0
A29: 11 | B29: =+recouvrement_dette!B29 -> 0
B30: =+recouvrement_dette!B30 -> 0
B31: =+recouvrement_dette!B31 -> 0
B32: =+recouvrement_dette!B32 -> 0
B33: =+recouvrement_dette!B33 -> 0
B34: =+recouvrement_dette!B34 -> 0
B35: =+recouvrement_dette!B35 -> 0
B36: =+recouvrement_dette!B36 -> 0
B37: =+recouvrement_dette!B37 -> 0
B38: =+recouvrement_dette!B38 -> 0
B39: =+recouvrement_dette!B39 -> 0
B40: =+recouvrement_dette!B40 -> 0
B41: =+recouvrement_dette!B41 -> 0
A42: Total | C42: =SUM(C2:C6) -> 0 | D42: =SUM(D2:D6) -> 0 | I42: =SUM(I2:I40) -> 0 | J42: =SUM(J2:J40) -> 4340000 | K42: =SUM(K2:K40) -> 0 | L42: =SUM(L2:L40) -> 820000 | M42: =SUM(M2:M40) -> 281400 | N42: =SUM(N2:N40) -> 100000 | O42: =SUM(O2:O40) -> 720000 | P42: =SUM(P2:P40) -> 0 | ... AG42: =SUM(AG2:AG40) -> 0

Sheet Feuil3
A1: NOMS | B1: Montant prêt | C1: Mois du prêt | D1: Durée du prêt (en mois) | E1: Taux intérêt cumulé | F1: Montant intérêt | G1: Montant déjà remboursé | H1: Taux de recouv. | I1: Reste à rembourser | J1: Échéance du prêt | K1: Commentaire
A2: YOUDOM Nadine | B2: 300000 | E2: 0.16 | F2: 48000 | G2: 348000 | H2: 1 | I2: 0 | J2: 05 Nov. 2021 | K2: Prêt remboursé
A3: TITNKHEU Moïse/DJEUKA | B3: 100000 | E3: 0 | F3: 0 | G3: 100000 | H3: 1 | I3: 0 | J3: 05 Déc. 2021 | K3: Prêt remboursé
A4: NOUTSA Eugène | B4: 92675 | E4: 0 | F4: 0 | G4: 92675 | H4: 1 | I4: 0 | J4: 05 Déc. 2021 | K4: Prêt remboursé
A5: SONGOU Sainclair | B5: 5000 | E5: 0 | F5: 0 | G5: 5000 | H5: 1 | I5: 0 | J5: 05 Déc. 2021 | K5: Prêt remboursé
A6: YIMKWAN Christel | B6: 75000 | E6: 0.50706667 | F6: 38030 | G6: 0 | H6: 0 | I6: 113030 | J6: 05 Déc. 2021 | K6: Prêt antérieur à la microfinance
A7: TAKOULEU Richardson | B7: 200000 | E7: 0.16 | F7: 32000 | G7: 232000 | H7: 1 | I7: 0 | J7: 05 Juin. 2022 | K7: Prêt remboursé
A8: WANGUN Parfait | B8: 264000 | E8: 0 | F8: 0 | G8: 240772.95 | H8: 0.91201875 | I8: 23227.05 | J8: 05 Déc. 2021 | K8: Régularisation trésorerie
A9: DOUNTSOP Jackson | B9: 1000000 | C9: Oct. 2021 | D9: 12 | E9: 0.2 | F9: 200000 | G9: 1200000 | H9: 1 | I9: 0 | J9: 10 Oct. 2022 | K9: Prêt microfinance
A10: LELE Hernandez | B10: 468000 | C10: Nov. 2021 | D10: 6 | E10: 0.1 | F10: 46800 | G10: 514800 | H10: 1 | I10: 0 | J10: 10 Mai. 2022 | K10: Prêt remboursé
A11: TCHIOFO Fidélia | B11: 164000 | C11: Nov. 2021 | D11: 3 | E11: 0.05 | F11: 8200 | G11: 172200 | H11: 1 | I11: 0 | J11: 10 Fev. 2022 | K11: Prêt remboursé
A12: TITNKHEU Moïse | B12: 600000 | C12: Janv. 2022 | D12: 9 | E12: 0.15 | F12: 90000 | G12: 690000 | H12: 1 | I12: 0 | J12: 10 Oct. 2022 | K12: Prêt remboursé
A13: SONGOU Sainclair | B13: 850000 | C13: Fév. 2022 | D13: 3 | E13: 0.05 | F13: 42500 | G13: 892500 | H13: 1 | I13: 0 | J13: 10 Mai. 2022 | K13: Prêt remboursé
A14: TCHIOFO Paulin | B14: 150000 | C14: Fév. 2022 | D14: 3 | E14: 0.05 | F14: 7500 | G14: 157500 | H14: 1 | I14: 0 | J14: 10 Mai. 2022 | K14: Prêt remboursé | M14: 895000 | N14: 400000
A15: KUITCHE Chevalier | B15: 325000 | C15: Avril. 2022 | D15: 6 | E15: 0.1 | F15: 32500 | G15: 357500 | H15: 1 | I15: 0 | J15: 10 Oct. 2022 | K15: Prêt remboursé | M15: 100000 | N15: 900000
A16: NOUTSA Eugène | B16: 1000000 | C16: Mai. 2022 | D16: 6 | E16: 0.1 | F16: 100000 | G16: 1100000 | H16: 1 | I16: 0 | J16: 10 Nov. 2022 | K16: Prêt remboursé | M16: 5000000 | N16: 1000000
A17: LELE Hernandez | B17: 1200000 | C17: Mai. 2022 | D17: 6 | E17: 0.1 | F17: 120000 | G17: 1320000 | H17: 1 | I17: 0 | J17: 10 Nov. 2022 | K17: Prêt remboursé | M17: 300000 | N17: 120000
A18: SONGOU Sainclair | B18: 900000 | C18: Juil. 2022 | D18: 9 | E18: 0.15 | F18: 135000 | G18: 1035000 | H18: 1 | I18: 0 | J18: 10 Avril. 2023 | K18: Prêt remboursé | M18: 100000
A19: DOUNTSOP Jackson | B19: 2000000 | C19: Août. 2022 | D19: 6 | E19: 0.1 | F19: 200000 | G19: 2200000 | H19: 1 | I19: 0 | J19: 10 Fév. 2023 | K19: Prêt remboursé | M19: 4500
A20: LELE Hernandez | B20: 2250000 | C20: Nov. 2022 | D20: 9 | E20: 0.15 | F20: 337500 | G20: 2587500 | H20: 1 | I20: 0 | J20: 10 Août. 2023 | K20: Prêt remboursé | N20: 666700
A21: DOUNTSOP Jackson | B21: 1320000 | C21: Janv. 2023 | D21: 9 | E21: 0.15 | F21: 198000 | G21: 1023000 | H21: 0.67391304 | I21: 495000 | J21: 10 Oct. 2023 | K21: Prêt microfinance | N21: 603300
A22: TCHOFO paulin | B22: 50000 | C22: Janv. 2023 | D22: 3 | E22: 0.05 | F22: 2500 | G22: 52500 | H22: 1 | I22: 0 | J22: 10 Avril. 2023 | K22: Prêt remboursé | N22: 70000
A23: TASSE Narcisse | B23: 2000000 | C23: Fév. 2023 | D23: 6 | E23: 0.1 | F23: 200000 | G23: 2200000 | H23: 1 | I23: 0 | J23: 10 Août. 2023 | K23: Prêt remboursé | N23: 30000
A24: SONGOU Sainclair | B24: 1300000 | C24: Mars. 2023 | D24: 3 | E24: 0.05 | F24: 65000 | G24: 1365000 | H24: 1 | I24: 0 | J24: 29 Juil. 2023 | K24: Prêt remboursé
A25: KUITCHE Chevalier | B25: 350000 | C25: Avril. 2023 | D25: 6 | E25: 0.1 | F25: 35000 | G25: 175000 | H25: 0.45454545 | I25: 210000 | J25: 10 Oct. 2023 | K25: Prêt microfinance | M25: =+SUM(M14:M22) -> 6399500 | N25: =+SUM(N14:N23) -> 3790000
A26: TCHOFO paulin | B26: 100000 | C26: Mai. 2023 | D26: 3 | E26: 0.05 | F26: 5000 | G26: 75000 | H26: 0.71428571 | I26: 30000 | J26: 10 Août. 2023 | K26: Prêt microfinance | N26: =+N25-M25 -> -2609500
A27: NOUTSA Eugène | B27: 2000000 | C27: Juin. 2023 | D27: 3 | E27: 0.05 | F27: 100000 | G27: 766700 | H27: 0.36509524 | I27: 1333300 | J27: 10 Sep. 2023 | K27: Prêt microfinance | M27: 9192191
A28: Total | B28: 19063675 | F28: 2043530 | G28: 18902648 | H28: 0.89555429 | I28: 2204557 | N28: =+M27+N26 -> 6582691

Sheet Feuil2
A1: 158000
A2: 0
A3: 0
A4: 0
A5: 113030
A6: 138900
A7: 225000

Sheet Tableau_amortissement_Franklin
A1: ECHOLENNEMENT D'UNE DETTE DANS LA MICROFINANCE CAMDVI
A5: *Bien vouloir renseigner uniquement les cases vertes
A7: Secteur du prêteur: | E7: Centre-Sud-Est | I7: Mois du prêt: | J7: Janv-2026
H9: Échéance du prêt | J9: 46793
A11: Nom du prêteur: | D11: MIAFO Franklin | I11: N° CNI:
A13: Montant prêt: | C13: 3000000 | D13: Durée du prêt: | F13: 24 | G13: mois | H13: Taux intérêt cumulé: | J13: =IF(C13<1000000,F13*1.5%,F13%) -> 0.24
H15: Intérêt sur prêt généré: | J15: =C13*J13 -> 720000
A17: Echolennement de la dette | G17: Montant global à rembourser: | J17: =C13+J15 -> 3720000
A19: Mois (Au plus tard le 10 de chaque mois) | C19: Montant à percevoir (1) | D19: Montant percu (2) | E19: (1)-(2)
A20: 46023 | E20: =C20-D20 -> 0
A21: 46054 | E21: =C21-D21 -> 0
A22: 46082 | C22: 155000 | E22: =C22-D22 -> 155000
A23: 46113 | C23: 155000 | E23: =C23-D23 -> 155000
A24: 46143 | C24: 155000 | E24: =C24-D24 -> 155000
A25: 46174 | C25: 155000 | E25: =C25-D25 -> 155000
A26: 46204 | C26: 155000 | E26: =C26-D26 -> 155000
A27: 46235 | C27: 155000 | E27: =C27-D27 -> 155000
A28: 46266 | C28: 155000 | E28: =C28-D28 -> 155000
A29: 46296 | C29: 155000 | E29: =C29-D29 -> 155000
A30: 46327 | C30: 155000 | E30: =C30-D30 -> 155000
A31: 46357 | C31: 155000 | E31: =C31-D31 -> 155000
A32: 46388 | C32: 155000 | E32: =C32-D32 -> 155000
A33: 46419 | C33: 155000 | E33: =C33-D33 -> 155000
... A45: 46784 | C45: 155000 | E45: =C45-D45 -> 155000
A46: Total à rembourser | C46: =SUM(C20:C45) -> 3720000 | D46: =SUM(D20:D45) -> 0 | E46: =SUM(E20:E45) -> 3720000

Sheet Tableau_amortissement_Sainclair
A1: ECHOLENNEMENT D'UNE DETTE DANS LA MICROFINANCE CAMDVI
A5: *Bien vouloir renseigner uniquement les cases vertes
A7: Secteur du prêteur: | E7: Diaspora | I7: Mois du prêt: | J7: Déc-2025
H9: Échéance du prêt | J9: 46152
A11: Nom du prêteur: | D11: SONGOU Sainclaire | I11: N° CNI:
A13: Montant prêt: | C13: 2500000 | D13: Durée du prêt: | F13: 4 | G13: mois | H13: Taux intérêt cumulé: | J13: =IF(C13<1000000,F13*1.5%,F13%) -> 0.04
H15: Intérêt sur prêt généré: | J15: =C13*J13 -> 100000
A17: Echolennement de la dette | G17: Montant global à rembourser: | J17: =C13+J15 -> 2600000
A19: Mois (Au plus tard le 10 de chaque mois) | C19: Montant à percevoir (1) | D19: Montant percu (2) | E19: (1)-(2)
A20: 45992 | E20: =C20-D20 -> 0
A21: 46023 | E21: =C21-D21 -> 0
A22: 46054 | C22: =J$17/F$13 -> 650000 | E22: =C22-D22 -> 650000
A23: 46082 | C23: =J$17/F$13 -> 650000 | E23: =C23-D23 -> 650000
A24: 46113 | C24: =J$17/F$13 -> 650000 | E24: =C24-D24 -> 650000
A25: 46143 | C25: =J$17/F$13 -> 650000 | E25: =C25-D25 -> 650000
A26: Total à rembourser | C26: =SUM(C20:C25) -> 2600000 | D26: =SUM(D20:D25) -> 0 | E26: =SUM(E20:E25) -> 2600000

Sheet Tableau_amortissement_Narcisse
A1: ECHOLENNEMENT D'UNE DETTE DANS LA MICROFINANCE CAMDVI
A5: *Bien vouloir renseigner uniquement les cases vertes
A7: Secteur du prêteur: | E7: Littoral | I7: Mois du prêt: | J7: Nov-2025
H9: Échéance du prêt | J9: 46366
A11: Nom du prêteur: | D11: TASSE Narcisse | I11: N° CNI:
A13: Montant prêt: | C13: 1570000 | D13: Durée du prêt: | F13: 12 | G13: mois | H13: Taux intérêt cumulé: | J13: =IF(C13<1000000,F13*1.5%,F13%) -> 0.12
H15: Intérêt sur prêt généré: | J15: =C13*J13 -> 188400
A17: Echolennement de la dette | G17: Montant global à rembourser: | J17: =C13+J15 -> 1758400
A19: Mois (Au plus tard le 10 de chaque mois) | C19: Montant à percevoir (1) | D19: Montant percu (2) | E19: (1)-(2)
A20: 45962 | E20: =C20-D20 -> 0
A21: 45992 | E21: =C21-D21 -> 0
A22: 46023 | C22: =J$17/F$13 -> 146533.33 | E22: =C22-D22 -> 146533.33
A23: 46054 | C23: =J$17/F$13 -> 146533.33 | E23: =C23-D23 -> 146533.33
A24: 46082 | C24: =J$17/F$13 -> 146533.33 | E24: =C24-D24 -> 146533.33
A25: 46113 | C25: =J$17/F$13 -> 146533.33 | E25: =C25-D25 -> 146533.33
A26: 46143 | C26: =J$17/F$13 -> 146533.33 | E26: =C26-D26 -> 146533.33
A27: 46174 | C27: =J$17/F$13 -> 146533.33 | E27: =C27-D27 -> 146533.33
A28: 46204 | C28: =J$17/F$13 -> 146533.33 | E28: =C28-D28 -> 146533.33
A29: 46235 | C29: =J$17/F$13 -> 146533.33 | E29: =C29-D29 -> 146533.33
A30: 46266 | C30: =J$17/F$13 -> 146533.33 | E30: =C30-D30 -> 146533.33
A31: 46296 | C31: =J$17/F$13 -> 146533.33 | E31: =C31-D31 -> 146533.33
A32: 46327 | C32: =J$17/F$13 -> 146533.33 | E32: =C32-D32 -> 146533.33
A33: 46357 | C33: =J$17/F$13 -> 146533.33 | E33: =C33-D33 -> 146533.33
A34: Total à rembourser | C34: =SUM(C20:C33) -> 1758400 | D34: =SUM(D20:D33) -> 0 | E34: =SUM(E20:E33) -> 1758400

Sheet Tableau_amortissement_Valdese
A1: ECHOLENNEMENT D'UNE DETTE DANS LA MICROFINANCE CAMDVI
A5: *Bien vouloir renseigner uniquement les cases vertes
A7: Secteur du prêteur: | E7: Diaspora | I7: Mois du prêt: | J7: Nov-2025
H9: Échéance du prêt | J9: 46091
A11: Nom du prêteur: | D11: MONTE Valdese | I11: N° CNI:
A13: Montant prêt: | C13: 3100000 | D13: Durée du prêt: | F13: 3 | G13: mois | H13: Taux intérêt cumulé: | J13: =IF(C13<1000000,F13*1.5%,F13%) -> 0.03
H15: Intérêt sur prêt généré: | J15: =C13*J13 -> 93000
A17: Echolennement de la dette | G17: Montant global à rembourser: | J17: =C13+J15 -> 3193000
A19: Mois (Au plus tard le 10 de chaque mois) | C19: Montant à percevoir (1) | D19: Montant percu (2) | E19: (1)-(2)
A20: 45962 | E20: =C20-D20 -> 0
A21: 45992 | E21: =C21-D21 -> 0
A22: 46023 | C22: =J$17/F$13 -> 1064333.3 | E22: =C22-D22 -> 1064333.3
A23: 46054 | C23: =J$17/F$13 -> 1064333.3 | E23: =C23-D23 -> 1064333.3
A24: 46082 | C24: =J$17/F$13 -> 1064333.3 | E24: =C24-D24 -> 1064333.3
A25: Total à rembourser | C25: =SUM(C20:C24) -> 3193000 | D25: =SUM(D20:D24) -> 0 | E25: =SUM(E20:E24) -> 3193000

Sheet Tableau_amortissement_Sammuel
A1: ECHOLENNEMENT D'UNE DETTE DANS LA MICROFINANCE CAMDVI
A5: *Bien vouloir renseigner uniquement les cases vertes
A7: Secteur du prêteur: | E7: Diaspora | I7: Mois du prêt: | J7: Oct-2025
H9: Échéance du prêt | J9: 46063
A11: Nom du prêteur: | D11: TOTUE Sammuel | I11: N° CNI:
A13: Montant prêt: | C13: 1000000 | D13: Durée du prêt: | F13: 3 | G13: mois | H13: Taux intérêt cumulé: | J13: =IF(C13<1000000,F13*1.5%,F13%) -> 0.03
H15: Intérêt sur prêt généré: | J15: =C13*J13 -> 30000
A17: Echolennement de la dette | G17: Montant global à rembourser: | J17: =C13+J15 -> 1030000
A19: Mois (Au plus tard le 10 de chaque mois) | C19: Montant à percevoir (1) | D19: Montant percu (2) | E19: (1)-(2)
A20: 45931 | E20: =C20-D20 -> 0
A21: 45962 | E21: =C21-D21 -> 0
A22: 45992 | C22: =J$17/F$13 -> 343333.33 | E22: =C22-D22 -> 343333.33
A23: 46023 | C23: =J$17/F$13 -> 343333.33 | E23: =C23-D23 -> 343333.33
A24: 46054 | C24: =J$17/F$13 -> 343333.33 | E24: =C24-D24 -> 343333.33
A25: Total à rembourser | C25: =SUM(C20:C24) -> 1030000 | D25: =SUM(D20:D24) -> 0 | E25: =SUM(E20:E24) -> 1030000

Sheet Tableau_amortissement_Clemence
A1: ECHOLENNEMENT D'UNE DETTE DANS LA MICROFINANCE CAMDVI
A5: *Bien vouloir renseigner uniquement les cases vertes
A7: Secteur du prêteur: | E7: Littoral | I7: Mois du prêt: | J7: Oct-2025
H9: Échéance du prêt | J9: 46275
A11: Nom du prêteur: | D11: DONGMO Clémence | I11: N° CNI:
A13: Montant prêt: | C13: 2500000 | D13: Durée du prêt: | F13: 10 | G13: mois | H13: Taux intérêt cumulé: | J13: =IF(C13<1000000,F13*1.5%,F13%) -> 0.1
H15: Intérêt sur prêt généré: | J15: =C13*J13 -> 250000
A17: Echolennement de la dette | G17: Montant global à rembourser: | J17: =C13+J15 -> 2750000
A19: Mois (Au plus tard le 10 de chaque mois) | C19: Montant à percevoir (1) | D19: Montant percu (2) | E19: (1)-(2)
A20: 45931 | E20: =C20-D20 -> 0
A21: 45962 | E21: =C21-D21 -> 0
A22: 45992 | C22: =J$17/F$13 -> 275000 | E22: =C22-D22 -> 275000
A23: 46023 | C23: =J$17/F$13 -> 275000 | E23: =C23-D23 -> 275000
A24: 46054 | C24: =J$17/F$13 -> 275000 | E24: =C24-D24 -> 275000
A25: 46082 | C25: =J$17/F$13 -> 275000 | E25: =C25-D25 -> 275000
A26: 46113 | C26: =J$17/F$13 -> 275000 | E26: =C26-D26 -> 275000
A27: 46143 | C27: =J$17/F$13 -> 275000 | E27: =C27-D27 -> 275000
A28: 46174 | C28: =J$17/F$13 -> 275000 | E28: =C28-D28 -> 275000
A29: 46204 | C29: =J$17/F$13 -> 275000 | E29: =C29-D29 -> 275000
A30: 46235 | C30: =J$17/F$13 -> 275000 | E30: =C30-D30 -> 275000
A31: 46266 | C31: =J$17/F$13 -> 275000 | E31: =C31-D31 -> 275000
A32: Total à rembourser | C32: =SUM(C20:C31) -> 2750000 | D32: =SUM(D20:D31) -> 0 | E32: =SUM(E20:E31) -> 2750000

Sheet Tableau_amortissement_Michel
A1: ECHOLENNEMENT D'UNE DETTE DANS LA MICROFINANCE CAMDVI
A5: *Bien vouloir renseigner uniquement les cases vertes
A7: Secteur du prêteur: | E7: Littoral | I7: Mois du prêt: | J7: Oct-2025
H9: Échéance du prêt | J9: 46517
A11: Nom du prêteur: | D11: PANGANG Michel | I11: N° CNI:
A13: Montant prêt: | C13: 3000000 | D13: Durée du prêt: | F13: 18 | G13: mois | H13: Taux intérêt cumulé: | J13: =IF(C13<1000000,F13*1.5%,F13%) -> 0.18
H15: Intérêt sur prêt généré: | J15: =C13*J13 -> 540000
A17: Echolennement de la dette | G17: Montant global à rembourser: | J17: =C13+J15 -> 3540000
A19: Mois (Au plus tard le 10 de chaque mois) | C19: Montant à percevoir (1) | D19: Montant percu (2) | E19: (1)-(2)
A20: 45931 | E20: =C20-D20 -> 0
A21: 45962 | E21: =C21-D21 -> 0
A22: 45992 | C22: =J$17/F$13 -> 196666.67 | E22: =C22-D22 -> 196666.67
A23: 46023 | C23: =J$17/F$13 -> 196666.67 | E23: =C23-D23 -> 196666.67
A24: 46054 | C24: =J$17/F$13 -> 196666.67 | E24: =C24-D24 -> 196666.67
A25: 46082 | C25: =J$17/F$13 -> 196666.67 | E25: =C25-D25 -> 196666.67
A26: 46113 | C26: =J$17/F$13 -> 196666.67 | E26: =C26-D26 -> 196666.67
A27: 46143 | C27: =J$17/F$13 -> 196666.67 | E27: =C27-D27 -> 196666.67
A28: 46174 | C28: =J$17/F$13 -> 196666.67 | E28: =C28-D28 -> 196666.67
A29: 46204 | C29: =J$17/F$13 -> 196666.67 | E29: =C29-D29 -> 196666.67
A30: 46235 | C30: =J$17/F$13 -> 196666.67 | E30: =C30-D30 -> 196666.67
A31: 46266 | C31: =J$17/F$13 -> 196666.67 | E31: =C31-D31 -> 196666.67
A32: 46296 | C32: =J$17/F$13 -> 196666.67 | E32: =C32-D32 -> 196666.67
A33: 46327 | C33: =J$17/F$13 -> 196666.67 | E33: =C33-D33 -> 196666.67
... A39: 46508 | C39: =J$17/F$13 -> 196666.67 | E39: =C39-D39 -> 196666.67
A40: Total à rembourser | C40: =SUM(C20:C39) -> 3540000 | D40: =SUM(D20:D39) -> 0 | E40: =SUM(E20:E39) -> 3540000

Sheet Tableau_amortissement_Kelly
A1: ECHOLENNEMENT D'UNE DETTE DANS LA MICROFINANCE CAMDVI
A5: *Bien vouloir renseigner uniquement les cases vertes
A7: Secteur du prêteur: | E7: Centre-Sud-Est | I7: Mois du prêt: | J7: Août-2025
H9: Échéance du prêt | J9: 46213
A11: Nom du prêteur: | D11: MAKOUGOUM Kelly | I11: N° CNI:
A13: Montant prêt: | C13: 1500000 | D13: Durée du prêt: | F13: 10 | G13: mois | H13: Taux intérêt cumulé: | J13: =IF(C13<1000000,F13*1.5%,F13%) -> 0.1
H15: Intérêt sur prêt généré: | J15: =C13*J13 -> 150000
A17: Echolennement de la dette | G17: Montant global à rembourser: | J17: =C13+J15 -> 1650000
A19: Mois (Au plus tard le 10 de chaque mois) | C19: Montant à percevoir (1) | D19: Montant percu (2) | E19: (1)-(2)
A20: 45870 | E20: =C20-D20 -> 0
A21: 45901 | E21: =C21-D21 -> 0
A22: 45931 | C22: =J$17/F$13 -> 165000 | E22: =C22-D22 -> 165000
A23: 45962 | C23: =J$17/F$13 -> 165000 | E23: =C23-D23 -> 165000
A24: 45992 | C24: =J$17/F$13 -> 165000 | E24: =C24-D24 -> 165000
A25: 46023 | C25: =J$17/F$13 -> 165000 | E25: =C25-D25 -> 165000
A26: 46054 | C26: =J$17/F$13 -> 165000 | E26: =C26-D26 -> 165000
A27: 46082 | C27: =J$17/F$13 -> 165000 | E27: =C27-D27 -> 165000
A28: 46113 | C28: =J$17/F$13 -> 165000 | E28: =C28-D28 -> 165000
A29: 46143 | C29: =J$17/F$13 -> 165000 | E29: =C29-D29 -> 165000
A30: 46174 | C30: =J$17/F$13 -> 165000 | E30: =C30-D30 -> 165000
A31: 46204 | C31: =J$17/F$13 -> 165000 | E31: =C31-D31 -> 165000
A32: Total à rembourser | C32: =SUM(C20:C31) -> 1650000 | D32: =SUM(D20:D31) -> 0 | E32: =SUM(E20:E31) -> 1650000

Sheet Tableau_amortissement_Dagober
A1: ECHOLENNEMENT D'UNE DETTE DANS LA MICROFINANCE CAMDVI
A5: *Bien vouloir renseigner uniquement les cases vertes
A7: Secteur du prêteur: | E7: Diaspora | I7: Mois du prêt: | J7: Août-2025
H9: Échéance du prêt | J9: 46275
A11: Nom du prêteur: | D11: NTETDE Dagobert | I11: N° CNI:
A13: Montant prêt: | C13: 3000000 | D13: Durée du prêt: | F13: 12 | G13: mois | H13: Taux intérêt cumulé: | J13: =IF(C13<1000000,F13*1.5%,F13%) -> 0.12
H15: Intérêt sur prêt généré: | J15: =C13*J13 -> 360000
A17: Echolennement de la dette | G17: Montant global à rembourser: | J17: =C13+J15 -> 3360000
A19: Mois (Au plus tard le 10 de chaque mois) | C19: Montant à percevoir (1) | D19: Montant percu (2) | E19: (1)-(2)
A20: 45870 | E20: =C20-D20 -> 0
A21: 45901 | E21: =C21-D21 -> 0
A22: 45931 | C22: =J$17/F$13 -> 280000 | E22: =C22-D22 -> 280000
A23: 45962 | C23: =J$17/F$13 -> 280000 | E23: =C23-D23 -> 280000
A24: 45992 | C24: =J$17/F$13 -> 280000 | E24: =C24-D24 -> 280000
A25: 46023 | C25: =J$17/F$13 -> 280000 | E25: =C25-D25 -> 280000
A26: 46054 | C26: =J$17/F$13 -> 280000 | E26: =C26-D26 -> 280000
A27: 46082 | C27: =J$17/F$13 -> 280000 | E27: =C27-D27 -> 280000
A28: 46113 | C28: =J$17/F$13 -> 280000 | E28: =C28-D28 -> 280000
A29: 46143 | C29: =J$17/F$13 -> 280000 | E29: =C29-D29 -> 280000
A30: 46174 | C30: =J$17/F$13 -> 280000 | E30: =C30-D30 -> 280000
A31: 46204 | C31: =J$17/F$13 -> 280000 | E31: =C31-D31 -> 280000
A32: 46235 | C32: =J$17/F$13 -> 280000 | E32: =C32-D32 -> 280000
A33: 46266 | C33: =J$17/F$13 -> 280000 | E33: =C33-D33 -> 280000
A34: Total à rembourser | C34: =SUM(C22:C33) -> 3360000 | D34: =SUM(D26:D33) -> 0 | E34: =SUM(E22:E33) -> 3360000

Sheet Tableau_amortissement_Brice
A1: ECHOLENNEMENT D'UNE DETTE DANS LA MICROFINANCE CAMDVI
A5: *Bien vouloir renseigner uniquement les cases vertes
A7: Secteur du prêteur: | E7: Diaspora | I7: Mois du prêt: | J7: Août-2025
H9: Échéance du prêt | J9: 46275
A11: Nom du prêteur: | D11: NONO Brice | I11: N° CNI:
A13: Montant prêt: | C13: 4000000 | D13: Durée du prêt: | F13: 12 | G13: mois | H13: Taux intérêt cumulé: | J13: =IF(C13<1000000,F13*1.5%,F13%) -> 0.12
H15: Intérêt sur prêt généré: | J15: =C13*J13 -> 480000
A17: Echolennement de la dette | G17: Montant global à rembourser: | J17: =C13+J15 -> 4480000
A19: Mois (Au plus tard le 10 de chaque mois) | C19: Montant à percevoir (1) | D19: Montant percu (2) | E19: (1)-(2)
A20: 45870 | E20: =C20-D20 -> 0
A21: 45901 | E21: =C21-D21 -> 0
A22: 45931 | C22: =J$17/F$13 -> 373333.33 | E22: =C22-D22 -> 373333.33
A23: 45962 | C23: =J$17/F$13 -> 373333.33 | E23: =C23-D23 -> 373333.33
A24: 45992 | C24: =J$17/F$13 -> 373333.33 | E24: =C24-D24 -> 373333.33
A25: 46023 | C25: =J$17/F$13 -> 373333.33 | E25: =C25-D25 -> 373333.33
A26: 46054 | C26: =J$17/F$13 -> 373333.33 | E26: =C26-D26 -> 373333.33
A27: 46082 | C27: =J$17/F$13 -> 373333.33 | E27: =C27-D27 -> 373333.33
A28: 46113 | C28: =J$17/F$13 -> 373333.33 | E28: =C28-D28 -> 373333.33
A29: 46143 | C29: =J$17/F$13 -> 373333.33 | E29: =C29-D29 -> 373333.33
A30: 46174 | C30: =J$17/F$13 -> 373333.33 | E30: =C30-D30 -> 373333.33
A31: 46204 | C31: =J$17/F$13 -> 373333.33 | E31: =C31-D31 -> 373333.33
A32: 46235 | C32: =J$17/F$13 -> 373333.33 | E32: =C32-D32 -> 373333.33
A33: 46266 | C33: =J$17/F$13 -> 373333.33 | E33: =C33-D33 -> 373333.33
A34: Total à rembourser | C34: =SUM(C20:C33) -> 4480000 | D34: =SUM(D20:D33) -> 0 | E34: =SUM(E20:E33) -> 4480000

Sheet Tableau_amortissement_Ricard
A1: ECHOLENNEMENT D'UNE DETTE DANS LA MICROFINANCE CAMDVI
A5: *Bien vouloir renseigner uniquement les cases vertes
A7: Secteur du prêteur: | E7: Ouest | I7: Mois du prêt: | J7: Août-2025
H9: Échéance du prêt | J9: 46275
A11: Nom du prêteur: | D11: TCHIO Ricardo | I11: N° CNI:
A13: Montant prêt: | C13: 1150000 | D13: Durée du prêt: | F13: 12 | G13: mois | H13: Taux intérêt cumulé: | J13: =IF(C13<1000000,F13*1.5%,F13%) -> 0.12
H15: Intérêt sur prêt généré: | J15: =C13*J13 -> 138000
A17: Echolennement de la dette | G17: Montant global à rembourser: | J17: =C13+J15 -> 1288000
A19: Mois (Au plus tard le 10 de chaque mois) | C19: Montant à percevoir (1) | D19: Montant percu (2) | E19: (1)-(2)
A20: 45870 | E20: =C20-D20 -> 0
A21: 45901 | E21: =C21-D21 -> 0
A22: 45931 | C22: =J$17/F$13 -> 107333.33 | E22: =C22-D22 -> 107333.33
A23: 45962 | C23: =J$17/F$13 -> 107333.33 | E23: =C23-D23 -> 107333.33
A24: 45992 | C24: =J$17/F$13 -> 107333.33 | E24: =C24-D24 -> 107333.33
A25: 46023 | C25: =J$17/F$13 -> 107333.33 | E25: =C25-D25 -> 107333.33
A26: 46054 | C26: =J$17/F$13 -> 107333.33 | E26: =C26-D26 -> 107333.33
A27: 46082 | C27: =J$17/F$13 -> 107333.33 | E27: =C27-D27 -> 107333.33
A28: 46113 | C28: =J$17/F$13 -> 107333.33 | E28: =C28-D28 -> 107333.33
A29: 46143 | C29: =J$17/F$13 -> 107333.33 | E29: =C29-D29 -> 107333.33
A30: 46174 | C30: =J$17/F$13 -> 107333.33 | E30: =C30-D30 -> 107333.33
A31: 46204 | C31: =J$17/F$13 -> 107333.33 | E31: =C31-D31 -> 107333.33
A32: 46235 | C32: =J$17/F$13 -> 107333.33 | E32: =C32-D32 -> 107333.33
A33: 46266 | C33: =J$17/F$13 -> 107333.33 | E33: =C33-D33 -> 107333.33
A34: Total à rembourser | C34: =SUM(C20:C33) -> 1288000 | D34: =SUM(D20:D33) -> 0 | E34: =SUM(E20:E33) -> 1288000

Sheet Tableau_amortissement_Tony
A1: ECHOLENNEMENT D'UNE DETTE DANS LA MICROFINANCE CAMDVI
A5: *Bien vouloir renseigner uniquement les cases vertes
A7: Secteur du prêteur: | E7: Diaspora | I7: Mois du prêt: | J7: Août-2025
H9: Échéance du prêt | J9: 46275
A11: Nom du prêteur: | D11: Tony | I11: N° CNI:
A13: Montant prêt: | C13: 300000 | D13: Durée du prêt: | F13: 12 | G13: mois | H13: Taux intérêt cumulé: | J13: =IF(C13<1000000,F13*1.5%,F13%) -> 0.18
H15: Intérêt sur prêt généré: | J15: =C13*J13 -> 54000
A17: Echolennement de la dette | G17: Montant global à rembourser: | J17: =C13+J15 -> 354000
A19: Mois (Au plus tard le 10 de chaque mois) | C19: Montant à percevoir (1) | D19: Montant percu (2) | E19: (1)-(2)
